Workbook

Sheet Exec Summ
C3: EXECUTIVE SUMMARY | L3: ='Exec Summ'!$F$6 -> Hudson View Park
D5: DEAL SUMMARY
D6: Property Name | F6: =OneLineRR!C67 -> Hudson View Park | G6: Financing:
D7: Street Address | F7: =OneLineRR!C68 -> 29 Hudson View Drive | G7: LTV | H7: 0.65
D8: City, State Zip | F8: =OneLineRR!C69 -> Beacon, NY 12508 | G8: Rate | H8: 0.055
D9: Rentable SF | F9: ='Unit Mix'!G74 -> 0 | G9: Amort. | H9: 30
D10: Total Units | E10: =COUNTIF(D40:D44,"*") -> 0 | F10: ='Unit Mix'!G70 -> 0 | G10: Interest Only | H10: No
D11: In-Place Occupancy | F11: ='Unit Mix'!G72 -> #DIV/0! | G11: Amount | H11: =$G$19*H7 -> #DIV/0!
D12: Year Built | F12: 1900 | G12: Annual Pmt | H12: =IF(H10="Yes",H11*$H$8,PMT(H8/12,H9*12,-H11,0)*12) -> #DIV/0!
D13: Google Maps Link | F13: www.google.com | G13: DSCR | H13: =$E$25/H12 -> #DIV/0!
D14: CapEx Required | E14: 0 | F14: =E14*F10 -> 0 | G14: Debt Yield | H14: =E25/H11 -> #DIV/0!
D17: VALUATION SUMMARY
F18: Low | G18: Medium | H18: Target | J18: Equity Summary | N18: Round Values: | O18: Closing Costs
D19: Purchase Price | F19: =ROUND($E$25/F25,-$N$19) -> #DIV/0! | G19: =ROUND($E$25/G25,-$N$19) -> #DIV/0! | H19: =ROUND($E$25/H25,-$N$19) -> #DIV/0! | J19: Equity | K19: =$G$19+$F$14-$H$11+($G$19*$O$19) -> #DIV/0! | N19: 0 | O19: 0.03
D20: Per Unit | F20: =F19/($F$10+$E$10) -> #DIV/0! | G20: =G19/($F$10+$E$10) -> #DIV/0! | H20: =H19/($F$10+$E$10) -> #DIV/0! | J20: In-Place CoC | K20: =+(E25-$H$12)/$K$19 -> #DIV/0!
D21: Per SF | F21: =F19/$F$9 -> #DIV/0! | G21: =G19/$F$9 -> #DIV/0! | H21: =H19/$F$9 -> #DIV/0! | J21: Stabilized CoC | K21: =+(E26-$H$12)/$K$19 -> #DIV/0!
E23: NOI | F23: Cap Rates | J23: ="*Includes $"&TEXT($F$14,"$0.0")/1000000&"M in capex and "&TEXT($O$19,"0.0%")&" closing costs" -> *Includes $0M in capex and 3.0% closing costs
D24: T12 | E24: ='P&Ls Summary'!I40 -> 6299663.2 | F24: =$E24/F$19 -> #DIV/0! | G24: =$E24/G$19 -> #DIV/0! | H24: =$E24/H$19 -> #DIV/0! | N24: Cap Increments:
D25: In-Place | E25: ='P&Ls Summary'!S40 -> #DIV/0! | F25: =G25+N25 -> 0.06 | G25: 0.0575 | H25: =G25-N25 -> 0.055 | N25: 0.0025
D26: Stabilized | E26: ='P&Ls Summary'!V40 -> #DIV/0! | F26: =$E26/F$19 -> #DIV/0! | G26: =$E26/G$19 -> #DIV/0! | H26: =$E26/H$19 -> #DIV/0!
D28: UNIT MIX SUMMARY
D29: Unit Type | E29: # Units | F29: % of Unit Mix | G29: Sq Ft | H29: Min Rent | I29: Max Rent | J29: In-Place Rent | K29: Market Rent | N29: **Enter Market Rents on 'Unit Mix' tab
D30: Studio | E30: =SUMIFS('Unit Mix'!$F$6:$F$62,'Unit Mix'!$AI$6:$AI$62,'Exec Summ'!D30) -> 0 | F30: =E30/$E$35 -> #DIV/0! | G30: =SUMIFS('Unit Mix'!$G$6:$G$62,'Unit Mix'!$AI$6:$AI$62,'Exec Summ'!D30)/E30 -> #DIV/0! | H30: =_xlfn.MINIFS('Unit Mix'!U$6:U$62,'Unit Mix'!$AI$6:$AI$62,'Exec Summ'!$D30) -> 0 | I30: =_xlfn.MAXIFS('Unit Mix'!V$6:V$62,'Unit Mix'!$AI$6:$AI$62,'Exec Summ'!$D30) -> 0 | J30: =SUMIFS('Unit Mix'!$I$6:$I$62,'Unit Mix'!$AI$6:$AI$62,'Exec Summ'!D30)/E30 -> #DIV/0! | K30: =SUMIFS('Unit Mix'!$O$6:$O$62,'Unit Mix'!$AI$6:$AI$62,'Exec Summ'!D30)/E30 -> #DIV/0!
D31: 1BR | E31: =SUMIFS('Unit Mix'!$F$6:$F$62,'Unit Mix'!$AI$6:$AI$62,'Exec Summ'!D31) -> 0 | F31: =E31/$E$35 -> #DIV/0! | G31: =SUMIFS('Unit Mix'!$G$6:$G$62,'Unit Mix'!$AI$6:$AI$62,'Exec Summ'!D31)/E31 -> #DIV/0! | H31: =_xlfn.MINIFS('Unit Mix'!U$6:U$62,'Unit Mix'!$AI$6:$AI$62,'Exec Summ'!$D31) -> 0 | I31: =_xlfn.MAXIFS('Unit Mix'!V$6:V$62,'Unit Mix'!$AI$6:$AI$62,'Exec Summ'!$D31) -> 0 | J31: =SUMIFS('Unit Mix'!$I$6:$I$62,'Unit Mix'!$AI$6:$AI$62,'Exec Summ'!D31)/E31 -> #DIV/0! | K31: =SUMIFS('Unit Mix'!$O$6:$O$62,'Unit Mix'!$AI$6:$AI$62,'Exec Summ'!D31)/E31 -> #DIV/0!
D32: 2BR | E32: =SUMIFS('Unit Mix'!$F$6:$F$62,'Unit Mix'!$AI$6:$AI$62,'Exec Summ'!D32) -> 0 | F32: =E32/$E$35 -> #DIV/0! | G32: =SUMIFS('Unit Mix'!$G$6:$G$62,'Unit Mix'!$AI$6:$AI$62,'Exec Summ'!D32)/E32 -> #DIV/0! | H32: =_xlfn.MINIFS('Unit Mix'!U$6:U$62,'Unit Mix'!$AI$6:$AI$62,'Exec Summ'!$D32) -> 0 | I32: =_xlfn.MAXIFS('Unit Mix'!V$6:V$62,'Unit Mix'!$AI$6:$AI$62,'Exec Summ'!$D32) -> 0 | J32: =SUMIFS('Unit Mix'!$I$6:$I$62,'Unit Mix'!$AI$6:$AI$62,'Exec Summ'!D32)/E32 -> #DIV/0! | K32: =SUMIFS('Unit Mix'!$O$6:$O$62,'Unit Mix'!$AI$6:$AI$62,'Exec Summ'!D32)/E32 -> #DIV/0!
D33: 3BR | E33: =SUMIFS('Unit Mix'!$F$6:$F$62,'Unit Mix'!$AI$6:$AI$62,'Exec Summ'!D33) -> 0 | F33: =E33/$E$35 -> #DIV/0! | G33: =SUMIFS('Unit Mix'!$G$6:$G$62,'Unit Mix'!$AI$6:$AI$62,'Exec Summ'!D33)/E33 -> #DIV/0! | H33: =_xlfn.MINIFS('Unit Mix'!U$6:U$62,'Unit Mix'!$AI$6:$AI$62,'Exec Summ'!$D33) -> 0 | I33: =_xlfn.MAXIFS('Unit Mix'!V$6:V$62,'Unit Mix'!$AI$6:$AI$62,'Exec Summ'!$D33) -> 0 | J33: =SUMIFS('Unit Mix'!$I$6:$I$62,'Unit Mix'!$AI$6:$AI$62,'Exec Summ'!D33)/E33 -> #DIV/0! | K33: =SUMIFS('Unit Mix'!$O$6:$O$62,'Unit Mix'!$AI$6:$AI$62,'Exec Summ'!D33)/E33 -> #DIV/0!
D34: 4BR | E34: =SUMIFS('Unit Mix'!$F$6:$F$62,'Unit Mix'!$AI$6:$AI$62,'Exec Summ'!D34) -> 0 | F34: =E34/$E$35 -> #DIV/0! | G34: =SUMIFS('Unit Mix'!$G$6:$G$62,'Unit Mix'!$AI$6:$AI$62,'Exec Summ'!D34)/E34 -> #DIV/0! | H34: =_xlfn.MINIFS('Unit Mix'!U$6:U$62,'Unit Mix'!$AI$6:$AI$62,'Exec Summ'!$D34) -> 0 | I34: =_xlfn.MAXIFS('Unit Mix'!V$6:V$62,'Unit Mix'!$AI$6:$AI$62,'Exec Summ'!$D34) -> 0 | J34: =SUMIFS('Unit Mix'!$I$6:$I$62,'Unit Mix'!$AI$6:$AI$62,'Exec Summ'!D34)/E34 -> #DIV/0! | K34: =SUMIFS('Unit Mix'!$O$6:$O$62,'Unit Mix'!$AI$6:$AI$62,'Exec Summ'!D34)/E34 -> #DIV/0!
D35: Total | E35: =SUM(E30:E34) -> 0 | F35: =SUM(F30:F34) -> #DIV/0! | G35: =SUMPRODUCT(G30:G34,$E$30:$E$34) -> #DIV/0! | J35: =SUMPRODUCT(J30:J34,$E$30:$E$34) -> #DIV/0! | K35: =SUMPRODUCT(K30:K34,$E$30:$E$34) -> #DIV/0! | N35: =J35='Rent Roll'!M516+'Rent Roll'!N516 -> #DIV/0! | O35: =K35='Rent Roll'!P516 -> #DIV/0!
D36: Wtd Average | G36: =SUMPRODUCT(G30:G34,$E$30:$E$34)/$E$35 -> #DIV/0! | J36: =SUMPRODUCT(J30:J34,$E$30:$E$34)/$E$35 -> #DIV/0! | K36: =SUMPRODUCT(K30:K34,$E$30:$E$34)/$E$35 -> #DIV/0! | N36: =J36='Unit Mix'!J63 -> #DIV/0! | O36: =K36='Unit Mix'!P63 -> #DIV/0!
D38: COMMERCIAL UNIT SUMMARY
D39: Unit | E39: Tenant | F39: Sq Ft | G39: Lease Term | H39: Lease Start | I39: Lease Exp | J39: In-Place Rent | K39: Market Rent
N40: [Link to source file]
D45: Total | J45: =SUM(J40:J44) -> 0 | K45: =SUM(K40:K44) -> 0

Sheet P&Ls Summary
B3: 0 | C3: INCOME STATEMENT SUMMARY | Y3: ='Exec Summ'!$F$6 -> Hudson View Park | AA3: ='Exec Summ'!$F$10+'Exec Summ'!$E$10 -> 0 | AB3: =IF(COUNTIF(H61:V63,"False")=0,"OK","ERROR") -> OK
D4: Choose if columns included in OM/BOV---> | H4: EXCLUDE FROM OM | O4: EXCLUDE FROM OM | R4: INCLUDE IN OM | U4: INCLUDE IN OM | AA4: Options for Assumptions
E5: ='P&Ls Detailed'!T5 -> YE 2022 | F5: ='P&Ls Detailed'!U5 -> YE 2023 | G5: ='P&Ls Detailed'!V5 -> YE 2024 | H5: ='P&Ls Detailed'!W5 -> T-12 (05.24-04.25) | J5: ='P&Ls Detailed'!X5 -> T-9 Ann. (08.24-04.25) | K5: ='P&Ls Detailed'!Y5 -> T-6 Ann. (11.24-04.25) | L5: ='P&Ls Detailed'!Z5 -> T-3 Ann. (02.25-04.25) | M5: ='P&Ls Detailed'!AA5 -> T-1 Ann. (04.25-04.25) | O5: ADJUSTED T12 | R5: IN-PLACE | U5: STABILIZED | X5: PROFORMA NOTES | AA5: 0 | AB5: Client | AC5: Choose | AD5: UW Assumption
H6: PER UNIT | I6: TOTAL | O6: PER UNIT | P6: TOTAL | R6: PER UNIT | S6: TOTAL | U6: PER UNIT | V6: TOTAL
AA7: Numbers Are Per Unit
D8: Income | AA8: 1 | AB8: 2 | AC8: --> # to Choose UW Assumption
D9: Market Rent | H9: =I9/$AA$3 -> #DIV/0! | I9: =SUMIFS('P&Ls Detailed'!W:W,'P&Ls Detailed'!$E:$E,'P&Ls Summary'!$D9,'P&Ls Detailed'!$D:$D,'P&Ls Summary'!$Y$3) -> 12277197 | J9: =SUMIFS('P&Ls Detailed'!X:X,'P&Ls Detailed'!$E:$E,'P&Ls Summary'!$D9,'P&Ls Detailed'!$D:$D,'P&Ls Summary'!$Y$3) -> 12312906 | K9: =SUMIFS('P&Ls Detailed'!Y:Y,'P&Ls Detailed'!$E:$E,'P&Ls Summary'!$D9,'P&Ls Detailed'!$D:$D,'P&Ls Summary'!$Y$3) -> 12332018 | L9: =SUMIFS('P&Ls Detailed'!Z:Z,'P&Ls Detailed'!$E:$E,'P&Ls Summary'!$D9,'P&Ls Detailed'!$D:$D,'P&Ls Summary'!$Y$3) -> 12350082 | M9: =SUMIFS('P&Ls Detailed'!AA:AA,'P&Ls Detailed'!$E:$E,'P&Ls Summary'!$D9,'P&Ls Detailed'!$D:$D,'P&Ls Summary'!$Y$3) -> 12369476 | R9: =S9/$AA$3 -> #DIV/0! | S9: ='Exec Summ'!K36*'Exec Summ'!E35*12 -> #DIV/0! | U9: =V9/$AA$3 -> #DIV/0! | V9: =S9*(1+$V$42) -> #DIV/0! | X9: See Unit Mix
D10: Loss to Lease | H10: =I10/$AA$3 -> #DIV/0! | I10: =SUMIFS('P&Ls Detailed'!W:W,'P&Ls Detailed'!$E:$E,'P&Ls Summary'!$D10,'P&Ls Detailed'!$D:$D,'P&Ls Summary'!$Y$3) -> -804454.39 | J10: =SUMIFS('P&Ls Detailed'!X:X,'P&Ls Detailed'!$E:$E,'P&Ls Summary'!$D10,'P&Ls Detailed'!$D:$D,'P&Ls Summary'!$Y$3) -> -672299.33 | K10: =SUMIFS('P&Ls Detailed'!Y:Y,'P&Ls Detailed'!$E:$E,'P&Ls Summary'!$D10,'P&Ls Detailed'!$D:$D,'P&Ls Summary'!$Y$3) -> -531451.14 | L10: =SUMIFS('P&Ls Detailed'!Z:Z,'P&Ls Detailed'!$E:$E,'P&Ls Summary'!$D10,'P&Ls Detailed'!$D:$D,'P&Ls Summary'!$Y$3) -> -418531.12 | M10: =SUMIFS('P&Ls Detailed'!AA:AA,'P&Ls Detailed'!$E:$E,'P&Ls Summary'!$D10,'P&Ls Detailed'!$D:$D,'P&Ls Summary'!$Y$3) -> -344011.92 | R10: =S10/$AA$3 -> #DIV/0! | S10: =S11-S9 -> #DIV/0! | U10: =V10/$AA$3 -> #DIV/0! | V10: =-$AC$10*V9 -> #DIV/0! | X10: Market Rents Less Gross Rents | AA10: =O10*(1+$AA$5) -> 0 | AB10: =IFERROR(S10/$AA$3,"n/a") -> n/a
D11: Gross Rental Income | H11: =I11/$AA$3 -> #DIV/0! | I11: =SUM(I9:I10) -> 11472742 | J11: =SUM(J9:J10) -> 11640607 | K11: =SUM(K9:K10) -> 11800566 | L11: =SUM(L9:L10) -> 11931551 | M11: =SUM(M9:M10) -> 12025464 | O11: =P11/$AA$3 -> #DIV/0! | P11: ='Unit Mix'!G80 -> 0 | R11: =S11/$AA$3 -> #DIV/0! | S11: =('Rent Roll'!M516+'Rent Roll'!N516)*12*(1+$S$42) -> 0 | U11: =V11/$AA$3 -> #DIV/0! | V11: =SUM(V9:V10) -> #DIV/0!
D12: Less Vacancy | H12: =I12/$AA$3 -> #DIV/0! | I12: =SUMIFS('P&Ls Detailed'!W:W,'P&Ls Detailed'!$E:$E,'P&Ls Summary'!$D12,'P&Ls Detailed'!$D:$D,'P&Ls Summary'!$Y$3) -> -193440.85 | J12: =SUMIFS('P&Ls Detailed'!X:X,'P&Ls Detailed'!$E:$E,'P&Ls Summary'!$D12,'P&Ls Detailed'!$D:$D,'P&Ls Summary'!$Y$3) -> -181087.95 | K12: =SUMIFS('P&Ls Detailed'!Y:Y,'P&Ls Detailed'!$E:$E,'P&Ls Summary'!$D12,'P&Ls Detailed'!$D:$D,'P&Ls Summary'!$Y$3) -> -178731.9 | L12: =SUMIFS('P&Ls Detailed'!Z:Z,'P&Ls Detailed'!$E:$E,'P&Ls Summary'!$D12,'P&Ls Detailed'!$D:$D,'P&Ls Summary'!$Y$3) -> -126680 | M12: =SUMIFS('P&Ls Detailed'!AA:AA,'P&Ls Detailed'!$E:$E,'P&Ls Summary'!$D12,'P&Ls Detailed'!$D:$D,'P&Ls Summary'!$Y$3) -> -96843.96 | O12: =P12/$AA$3 -> #DIV/0! | P12: =SUMIFS('P&Ls Detailed'!W:W,'P&Ls Detailed'!$E:$E,'P&Ls Summary'!$D12,'P&Ls Detailed'!$D:$D,'P&Ls Summary'!$Y$3)-SUMIFS('P&Ls Detailed'!W:W,'P&Ls Detailed'!$E:$E,'P&Ls Summary'!$D12,'P&Ls Detailed'!$D:$D,'P&Ls Summary'!$Y$3,'P&Ls Detailed'!$F:$F,"Exclude") -> 0 | R12: =S12/$AA$3 -> #DIV/0! | S12: =-$S$11*AC12 -> 0 | U12: =V12/$AA$3 -> #DIV/0! | V12: =-$V$11*AC12 -> #DIV/0! | X12: =TEXT(AC12,"#0.0%")&" of Gross Rental Income" -> 3.0% of Gross Rental Income | AA12: =O12*(1+$AA$5) -> #DIV/0! | AB12: =IFERROR(S12/$AA$3,"n/a") -> n/a | AC12: 0.03 | AE12: --> Default to 3.0%
D13: Less: Concessions | H13: =I13/$AA$3 -> #DIV/0! | I13: =SUMIFS('P&Ls Detailed'!W:W,'P&Ls Detailed'!$E:$E,'P&Ls Summary'!$D13,'P&Ls Detailed'!$D:$D,'P&Ls Summary'!$Y$3) -> -67386.31 | J13: =SUMIFS('P&Ls Detailed'!X:X,'P&Ls Detailed'!$E:$E,'P&Ls Summary'!$D13,'P&Ls Detailed'!$D:$D,'P&Ls Summary'!$Y$3) -> -68301.6 | K13: =SUMIFS('P&Ls Detailed'!Y:Y,'P&Ls Detailed'!$E:$E,'P&Ls Summary'!$D13,'P&Ls Detailed'!$D:$D,'P&Ls Summary'!$Y$3) -> -69410.44 | L13: =SUMIFS('P&Ls Detailed'!Z:Z,'P&Ls Detailed'!$E:$E,'P&Ls Summary'!$D13,'P&Ls Detailed'!$D:$D,'P&Ls Summary'!$Y$3) -> -71905.44 | M13: =SUMIFS('P&Ls Detailed'!AA:AA,'P&Ls Detailed'!$E:$E,'P&Ls Summary'!$D13,'P&Ls Detailed'!$D:$D,'P&Ls Summary'!$Y$3) -> -71905.44 | O13: =P13/$AA$3 -> #DIV/0! | P13: =SUMIFS('P&Ls Detailed'!W:W,'P&Ls Detailed'!$E:$E,'P&Ls Summary'!$D13,'P&Ls Detailed'!$D:$D,'P&Ls Summary'!$Y$3)-SUMIFS('P&Ls Detailed'!W:W,'P&Ls Detailed'!$E:$E,'P&Ls Summary'!$D13,'P&Ls Detailed'!$D:$D,'P&Ls Summary'!$Y$3,'P&Ls Detailed'!$F:$F,"Exclude") -> 0 | R13: =S13/$AA$3 -> #DIV/0! | S13: =-$S$11*AC13 -> 0 | U13: =V13/$AA$3 -> #DIV/0! | V13: =-$V$11*AC13 -> #DIV/0! | X13: =TEXT(AC13,"#0.0%")&" of Gross Rental Income" -> 0.0% of Gross Rental Income | AA13: =O13*(1+$AA$5) -> #DIV/0! | AB13: =IFERROR(S13/$AA$3,"n/a") -> n/a | AC13: 0
D14: Less: Bad Debt/Collection | H14: =I14/$AA$3 -> #DIV/0! | I14: =SUMIFS('P&Ls Detailed'!W:W,'P&Ls Detailed'!$E:$E,'P&Ls Summary'!$D14,'P&Ls Detailed'!$D:$D,'P&Ls Summary'!$Y$3) -> -280.89 | J14: =SUMIFS('P&Ls Detailed'!X:X,'P&Ls Detailed'!$E:$E,'P&Ls Summary'!$D14,'P&Ls Detailed'!$D:$D,'P&Ls Summary'!$Y$3) -> -675.61333 | K14: =SUMIFS('P&Ls Detailed'!Y:Y,'P&Ls Detailed'!$E:$E,'P&Ls Summary'!$D14,'P&Ls Detailed'!$D:$D,'P&Ls Summary'!$Y$3) -> -1013.42 | L14: =SUMIFS('P&Ls Detailed'!Z:Z,'P&Ls Detailed'!$E:$E,'P&Ls Summary'!$D14,'P&Ls Detailed'!$D:$D,'P&Ls Summary'!$Y$3) -> 1780.92 | M14: =SUMIFS('P&Ls Detailed'!AA:AA,'P&Ls Detailed'!$E:$E,'P&Ls Summary'!$D14,'P&Ls Detailed'!$D:$D,'P&Ls Summary'!$Y$3) -> 0 | O14: =P14/$AA$3 -> #DIV/0! | P14: =SUMIFS('P&Ls Detailed'!W:W,'P&Ls Detailed'!$E:$E,'P&Ls Summary'!$D14,'P&Ls Detailed'!$D:$D,'P&Ls Summary'!$Y$3)-SUMIFS('P&Ls Detailed'!W:W,'P&Ls Detailed'!$E:$E,'P&Ls Summary'!$D14,'P&Ls Detailed'!$D:$D,'P&Ls Summary'!$Y$3,'P&Ls Detailed'!$F:$F,"Exclude") -> 0 | R14: =S14/$AA$3 -> #DIV/0! | S14: =-$S$11*AC14 -> 0 | U14: =V14/$AA$3 -> #DIV/0! | V14: =-$V$11*AC14 -> #DIV/0! | X14: =TEXT(AC14,"#0.0%")&" of Gross Rental Income" -> 0.0% of Gross Rental Income | AA14: =O14*(1+$AA$5) -> #DIV/0! | AB14: =IFERROR(S14/$AA$3,"n/a") -> n/a | AC14: 0
D15: Pet Income | H15: =I15/$AA$3 -> #DIV/0! | I15: =SUMIFS('P&Ls Detailed'!W:W,'P&Ls Detailed'!$E:$E,'P&Ls Summary'!$D15,'P&Ls Detailed'!$D:$D,'P&Ls Summary'!$Y$3) -> 87864.1 | J15: =SUMIFS('P&Ls Detailed'!X:X,'P&Ls Detailed'!$E:$E,'P&Ls Summary'!$D15,'P&Ls Detailed'!$D:$D,'P&Ls Summary'!$Y$3) -> 86877.08 | K15: =SUMIFS('P&Ls Detailed'!Y:Y,'P&Ls Detailed'!$E:$E,'P&Ls Summary'!$D15,'P&Ls Detailed'!$D:$D,'P&Ls Summary'!$Y$3) -> 83124.8 | L15: =SUMIFS('P&Ls Detailed'!Z:Z,'P&Ls Detailed'!$E:$E,'P&Ls Summary'!$D15,'P&Ls Detailed'!$D:$D,'P&Ls Summary'!$Y$3) -> 81165.12 | M15: =SUMIFS('P&Ls Detailed'!AA:AA,'P&Ls Detailed'!$E:$E,'P&Ls Summary'!$D15,'P&Ls Detailed'!$D:$D,'P&Ls Summary'!$Y$3) -> 76110 | O15: =P15/$AA$3 -> #DIV/0! | P15: =SUMIFS('P&Ls Detailed'!W:W,'P&Ls Detailed'!$E:$E,'P&Ls Summary'!$D15,'P&Ls Detailed'!$D:$D,'P&Ls Summary'!$Y$3)-SUMIFS('P&Ls Detailed'!W:W,'P&Ls Detailed'!$E:$E,'P&Ls Summary'!$D15,'P&Ls Detailed'!$D:$D,'P&Ls Summary'!$Y$3,'P&Ls Detailed'!$F:$F,"Exclude") -> 87864.1 | R15: =AD15 -> #DIV/0! | S15: =R15*$AA$3 -> #DIV/0! | U15: =V15/$AA$3 -> #DIV/0! | V15: =S15*(1+$V$43) -> #DIV/0! | X15: =IF(AC15=1, IF(AND($AA$5=0,AC15=1),"T12","T12 + "&TEXT($AA$5,"0.0%")),TEXT(AB15,"$##,##0")&"/unit") -> T12 | AA15: =O15*(1+$AA$5) -> #DIV/0! | AB15: 0 | AC15: 1 | AD15: =CHOOSE(AC15,AA15,AB15) -> #DIV/0!
D16: Laundry Income | H16: =I16/$AA$3 -> #DIV/0! | I16: =SUMIFS('P&Ls Detailed'!W:W,'P&Ls Detailed'!$E:$E,'P&Ls Summary'!$D16,'P&Ls Detailed'!$D:$D,'P&Ls Summary'!$Y$3) -> 133399.46 | J16: =SUMIFS('P&Ls Detailed'!X:X,'P&Ls Detailed'!$E:$E,'P&Ls Summary'!$D16,'P&Ls Detailed'!$D:$D,'P&Ls Summary'!$Y$3) -> 134801.48 | K16: =SUMIFS('P&Ls Detailed'!Y:Y,'P&Ls Detailed'!$E:$E,'P&Ls Summary'!$D16,'P&Ls Detailed'!$D:$D,'P&Ls Summary'!$Y$3) -> 134453.06 | L16: =SUMIFS('P&Ls Detailed'!Z:Z,'P&Ls Detailed'!$E:$E,'P&Ls Summary'!$D16,'P&Ls Detailed'!$D:$D,'P&Ls Summary'!$Y$3) -> 140316.32 | M16: =SUMIFS('P&Ls Detailed'!AA:AA,'P&Ls Detailed'!$E:$E,'P&Ls Summary'!$D16,'P&Ls Detailed'!$D:$D,'P&Ls Summary'!$Y$3) -> 132407.76 | O16: =P16/$AA$3 -> #DIV/0! | P16: =SUMIFS('P&Ls Detailed'!W:W,'P&Ls Detailed'!$E:$E,'P&Ls Summary'!$D16,'P&Ls Detailed'!$D:$D,'P&Ls Summary'!$Y$3)-SUMIFS('P&Ls Detailed'!W:W,'P&Ls Detailed'!$E:$E,'P&Ls Summary'!$D16,'P&Ls Detailed'!$D:$D,'P&Ls Summary'!$Y$3,'P&Ls Detailed'!$F:$F,"Exclude") -> 133399.46 | R16: =AD16 -> #DIV/0! | S16: =R16*$AA$3 -> #DIV/0! | U16: =V16/$AA$3 -> #DIV/0! | V16: =S16*(1+$V$43) -> #DIV/0! | X16: =IF(AC16=1, IF(AND($AA$5=0,AC16=1),"T12","T12 + "&TEXT($AA$5,"0.0%")),TEXT(AB16,"$##,##0")&"/unit") -> T12 | AA16: =O16*(1+$AA$5) -> #DIV/0! | AB16: 0 | AC16: 1 | AD16: =CHOOSE(AC16,AA16,AB16) -> #DIV/0!
D17: Parking Income | H17: =I17/$AA$3 -> #DIV/0! | I17: =SUMIFS('P&Ls Detailed'!W:W,'P&Ls Detailed'!$E:$E,'P&Ls Summary'!$D17,'P&Ls Detailed'!$D:$D,'P&Ls Summary'!$Y$3) -> 0 | J17: =SUMIFS('P&Ls Detailed'!X:X,'P&Ls Detailed'!$E:$E,'P&Ls Summary'!$D17,'P&Ls Detailed'!$D:$D,'P&Ls Summary'!$Y$3) -> 0 | K17: =SUMIFS('P&Ls Detailed'!Y:Y,'P&Ls Detailed'!$E:$E,'P&Ls Summary'!$D17,'P&Ls Detailed'!$D:$D,'P&Ls Summary'!$Y$3) -> 0 | L17: =SUMIFS('P&Ls Detailed'!Z:Z,'P&Ls Detailed'!$E:$E,'P&Ls Summary'!$D17,'P&Ls Detailed'!$D:$D,'P&Ls Summary'!$Y$3) -> 0 | M17: =SUMIFS('P&Ls Detailed'!AA:AA,'P&Ls Detailed'!$E:$E,'P&Ls Summary'!$D17,'P&Ls Detailed'!$D:$D,'P&Ls Summary'!$Y$3) -> 0 | O17: =P17/$AA$3 -> #DIV/0! | P17: =SUMIFS('P&Ls Detailed'!W:W,'P&Ls Detailed'!$E:$E,'P&Ls Summary'!$D17,'P&Ls Detailed'!$D:$D,'P&Ls Summary'!$Y$3)-SUMIFS('P&Ls Detailed'!W:W,'P&Ls Detailed'!$E:$E,'P&Ls Summary'!$D17,'P&Ls Detailed'!$D:$D,'P&Ls Summary'!$Y$3,'P&Ls Detailed'!$F:$F,"Exclude") -> 0 | R17: =AD17 -> #DIV/0! | S17: =R17*$AA$3 -> #DIV/0! | U17: =V17/$AA$3 -> #DIV/0! | V17: =S17*(1+$V$43) -> #DIV/0! | X17: =IF(AC17=1, IF(AND($AA$5=0,AC17=1),"T12","T12 + "&TEXT($AA$5,"0.0%")),TEXT(AB17,"$##,##0")&"/unit") -> T12 | AA17: =O17*(1+$AA$5) -> #DIV/0! | AB17: 0 | AC17: 1 | AD17: =CHOOSE(AC17,AA17,AB17) -> #DIV/0!
D18: Storage Income | H18: =I18/$AA$3 -> #DIV/0! | I18: =SUMIFS('P&Ls Detailed'!W:W,'P&Ls Detailed'!$E:$E,'P&Ls Summary'!$D18,'P&Ls Detailed'!$D:$D,'P&Ls Summary'!$Y$3) -> 0 | J18: =SUMIFS('P&Ls Detailed'!X:X,'P&Ls Detailed'!$E:$E,'P&Ls Summary'!$D18,'P&Ls Detailed'!$D:$D,'P&Ls Summary'!$Y$3) -> 0 | K18: =SUMIFS('P&Ls Detailed'!Y:Y,'P&Ls Detailed'!$E:$E,'P&Ls Summary'!$D18,'P&Ls Detailed'!$D:$D,'P&Ls Summary'!$Y$3) -> 0 | L18: =SUMIFS('P&Ls Detailed'!Z:Z,'P&Ls Detailed'!$E:$E,'P&Ls Summary'!$D18,'P&Ls Detailed'!$D:$D,'P&Ls Summary'!$Y$3) -> 0 | M18: =SUMIFS('P&Ls Detailed'!AA:AA,'P&Ls Detailed'!$E:$E,'P&Ls Summary'!$D18,'P&Ls Detailed'!$D:$D,'P&Ls Summary'!$Y$3) -> 0 | O18: =P18/$AA$3 -> #DIV/0! | P18: =SUMIFS('P&Ls Detailed'!W:W,'P&Ls Detailed'!$E:$E,'P&Ls Summary'!$D18,'P&Ls Detailed'!$D:$D,'P&Ls Summary'!$Y$3)-SUMIFS('P&Ls Detailed'!W:W,'P&Ls Detailed'!$E:$E,'P&Ls Summary'!$D18,'P&Ls Detailed'!$D:$D,'P&Ls Summary'!$Y$3,'P&Ls Detailed'!$F:$F,"Exclude") -> 0 | R18: =AD18 -> #DIV/0! | S18: =R18*$AA$3 -> #DIV/0! | U18: =V18/$AA$3 -> #DIV/0! | V18: =S18*(1+$V$43) -> #DIV/0! | X18: =IF(AC18=1, IF(AND($AA$5=0,AC18=1),"T12","T12 + "&TEXT($AA$5,"0.0%")),TEXT(AB18,"$##,##0")&"/unit") -> T12 | AA18: =O18*(1+$AA$5) -> #DIV/0! | AB18: 0 | AC18: 1 | AD18: =CHOOSE(AC18,AA18,AB18) -> #DIV/0!
D19: Utility Reimbursement | H19: =I19/$AA$3 -> #DIV/0! | I19: =SUMIFS('P&Ls Detailed'!W:W,'P&Ls Detailed'!$E:$E,'P&Ls Summary'!$D19,'P&Ls Detailed'!$D:$D,'P&Ls Summary'!$Y$3) -> 17248.35 | J19: =SUMIFS('P&Ls Detailed'!X:X,'P&Ls Detailed'!$E:$E,'P&Ls Summary'!$D19,'P&Ls Detailed'!$D:$D,'P&Ls Summary'!$Y$3) -> 17379.733 | K19: =SUMIFS('P&Ls Detailed'!Y:Y,'P&Ls Detailed'!$E:$E,'P&Ls Summary'!$D19,'P&Ls Detailed'!$D:$D,'P&Ls Summary'!$Y$3) -> 17507.34 | L19: =SUMIFS('P&Ls Detailed'!Z:Z,'P&Ls Detailed'!$E:$E,'P&Ls Summary'!$D19,'P&Ls Detailed'!$D:$D,'P&Ls Summary'!$Y$3) -> 17839.2 | M19: =SUMIFS('P&Ls Detailed'!AA:AA,'P&Ls Detailed'!$E:$E,'P&Ls Summary'!$D19,'P&Ls Detailed'!$D:$D,'P&Ls Summary'!$Y$3) -> 18000 | O19: =P19/$AA$3 -> #DIV/0! | P19: =SUMIFS('P&Ls Detailed'!W:W,'P&Ls Detailed'!$E:$E,'P&Ls Summary'!$D19,'P&Ls Detailed'!$D:$D,'P&Ls Summary'!$Y$3)-SUMIFS('P&Ls Detailed'!W:W,'P&Ls Detailed'!$E:$E,'P&Ls Summary'!$D19,'P&Ls Detailed'!$D:$D,'P&Ls Summary'!$Y$3,'P&Ls Detailed'!$F:$F,"Exclude") -> 17248.35 | R19: =AD19 -> #DIV/0! | S19: =R19*$AA$3 -> #DIV/0! | U19: =V19/$AA$3 -> #DIV/0! | V19: =S19*(1+$V$43) -> #DIV/0! | X19: =IF(AC19=1, IF(AND($AA$5=0,AC19=1),"T12","T12 + "&TEXT($AA$5,"0.0%")),TEXT(AB19,"$##,##0")&"/unit") -> T12 | AA19: =O19*(1+$AA$5) -> #DIV/0! | AB19: 0 | AC19: 1 | AD19: =CHOOSE(AC19,AA19,AB19) -> #DIV/0!
D20: Other Income | H20: =I20/$AA$3 -> #DIV/0! | I20: =SUMIFS('P&Ls Detailed'!W:W,'P&Ls Detailed'!$E:$E,'P&Ls Summary'!$D20,'P&Ls Detailed'!$D:$D,'P&Ls Summary'!$Y$3) -> 367295.05 | J20: =SUMIFS('P&Ls Detailed'!X:X,'P&Ls Detailed'!$E:$E,'P&Ls Summary'!$D20,'P&Ls Detailed'!$D:$D,'P&Ls Summary'!$Y$3) -> 300617.01 | K20: =SUMIFS('P&Ls Detailed'!Y:Y,'P&Ls Detailed'!$E:$E,'P&Ls Summary'!$D20,'P&Ls Detailed'!$D:$D,'P&Ls Summary'!$Y$3) -> 244740.24 | L20: =SUMIFS('P&Ls Detailed'!Z:Z,'P&Ls Detailed'!$E:$E,'P&Ls Summary'!$D20,'P&Ls Detailed'!$D:$D,'P&Ls Summary'!$Y$3) -> 167834.28 | M20: =SUMIFS('P&Ls Detailed'!AA:AA,'P&Ls Detailed'!$E:$E,'P&Ls Summary'!$D20,'P&Ls Detailed'!$D:$D,'P&Ls Summary'!$Y$3) -> 110008.56 | O20: =P20/$AA$3 -> #DIV/0! | P20: =SUMIFS('P&Ls Detailed'!W:W,'P&Ls Detailed'!$E:$E,'P&Ls Summary'!$D20,'P&Ls Detailed'!$D:$D,'P&Ls Summary'!$Y$3)-SUMIFS('P&Ls Detailed'!W:W,'P&Ls Detailed'!$E:$E,'P&Ls Summary'!$D20,'P&Ls Detailed'!$D:$D,'P&Ls Summary'!$Y$3,'P&Ls Detailed'!$F:$F,"Exclude") -> 367295.05 | R20: =AD20 -> #DIV/0! | S20: =R20*$AA$3 -> #DIV/0! | U20: =V20/$AA$3 -> #DIV/0! | V20: =S20*(1+$V$43) -> #DIV/0! | X20: =IF(AC20=1, IF(AND($AA$5=0,AC20=1),"T12","T12 + "&TEXT($AA$5,"0.0%")),TEXT(AB20,"$##,##0")&"/unit") -> T12 | AA20: =O20*(1+$AA$5) -> #DIV/0! | AB20: 0 | AC20: 1 | AD20: =CHOOSE(AC20,AA20,AB20) -> #DIV/0!
D21: Commercial Income | H21: =I21/$AA$3 -> #DIV/0! | I21: =SUMIFS('P&Ls Detailed'!W:W,'P&Ls Detailed'!$E:$E,'P&Ls Summary'!$D21,'P&Ls Detailed'!$D:$D,'P&Ls Summary'!$Y$3) -> 0 | J21: =SUMIFS('P&Ls Detailed'!X:X,'P&Ls Detailed'!$E:$E,'P&Ls Summary'!$D21,'P&Ls Detailed'!$D:$D,'P&Ls Summary'!$Y$3) -> 0 | K21: =SUMIFS('P&Ls Detailed'!Y:Y,'P&Ls Detailed'!$E:$E,'P&Ls Summary'!$D21,'P&Ls Detailed'!$D:$D,'P&Ls Summary'!$Y$3) -> 0 | L21: =SUMIFS('P&Ls Detailed'!Z:Z,'P&Ls Detailed'!$E:$E,'P&Ls Summary'!$D21,'P&Ls Detailed'!$D:$D,'P&Ls Summary'!$Y$3) -> 0 | M21: =SUMIFS('P&Ls Detailed'!AA:AA,'P&Ls Detailed'!$E:$E,'P&Ls Summary'!$D21,'P&Ls Detailed'!$D:$D,'P&Ls Summary'!$Y$3) -> 0 | O21: =P21/$AA$3 -> #DIV/0! | P21: =SUMIFS('P&Ls Detailed'!W:W,'P&Ls Detailed'!$E:$E,'P&Ls Summary'!$D21,'P&Ls Detailed'!$D:$D,'P&Ls Summary'!$Y$3)-SUMIFS('P&Ls Detailed'!W:W,'P&Ls Detailed'!$E:$E,'P&Ls Summary'!$D21,'P&Ls Detailed'!$D:$D,'P&Ls Summary'!$Y$3,'P&Ls Detailed'!$F:$F,"Exclude") -> 0 | R21: =S21/$AA$3 -> #DIV/0! | S21: ='Exec Summ'!J45*12 -> 0 | U21: =V21/$AA$3 -> #DIV/0! | V21: ='Exec Summ'!K45*12 -> 0 | X21: See Commercial Unit Summary | AA21: =O21*(1+$AA$5) -> #DIV/0! | AB21: =IFERROR(S21/$AA$3,"n/a") -> n/a
D22: Less Commercial Vacancy | H22: =I22/$AA$3 -> #DIV/0! | I22: =SUMIFS('P&Ls Detailed'!W:W,'P&Ls Detailed'!$E:$E,'P&Ls Summary'!$D22,'P&Ls Detailed'!$D:$D,'P&Ls Summary'!$Y$3) -> 0 | J22: =SUMIFS('P&Ls Detailed'!X:X,'P&Ls Detailed'!$E:$E,'P&Ls Summary'!$D22,'P&Ls Detailed'!$D:$D,'P&Ls Summary'!$Y$3) -> 0 | K22: =SUMIFS('P&Ls Detailed'!Y:Y,'P&Ls Detailed'!$E:$E,'P&Ls Summary'!$D22,'P&Ls Detailed'!$D:$D,'P&Ls Summary'!$Y$3) -> 0 | L22: =SUMIFS('P&Ls Detailed'!Z:Z,'P&Ls Detailed'!$E:$E,'P&Ls Summary'!$D22,'P&Ls Detailed'!$D:$D,'P&Ls Summary'!$Y$3) -> 0 | M22: =SUMIFS('P&Ls Detailed'!AA:AA,'P&Ls Detailed'!$E:$E,'P&Ls Summary'!$D22,'P&Ls Detailed'!$D:$D,'P&Ls Summary'!$Y$3) -> 0 | O22: =P22/$AA$3 -> #DIV/0! | P22: =SUMIFS('P&Ls Detailed'!W:W,'P&Ls Detailed'!$E:$E,'P&Ls Summary'!$D22,'P&Ls Detailed'!$D:$D,'P&Ls Summary'!$Y$3)-SUMIFS('P&Ls Detailed'!W:W,'P&Ls Detailed'!$E:$E,'P&Ls Summary'!$D22,'P&Ls Detailed'!$D:$D,'P&Ls Summary'!$Y$3,'P&Ls Detailed'!$F:$F,"Exclude") -> 0 | R22: =S22/$AA$3 -> #DIV/0! | S22: =-$S$21*AC22 -> 0 | U22: =V22/$AA$3 -> #DIV/0! | V22: =-$V$21*AC22 -> 0 | X22: =TEXT(AC22,"#0.0%")&" of Retail Income" -> 5.0% of Retail Income | AA22: =O22*(1+$AA$5) -> #DIV/0! | AB22: =IFERROR(S22/$AA$3,"n/a") -> n/a | AC22: 0.05
D23: Effective Gross Income | E23: =SUM(E9:E22) -> 0 | F23: =SUM(F9:F22) -> 0 | G23: =SUM(G9:G22) -> 0 | H23: =I23/$AA$3 -> #DIV/0! | I23: =SUM(I11:I22) -> 11817441 | J23: =SUM(J11:J22) -> 11930217 | K23: =SUM(K11:K22) -> 12031236 | L23: =SUM(L11:L22) -> 12141901 | M23: =SUM(M11:M22) -> 12193241 | O23: =P23/$AA$3 -> #DIV/0! | P23: =SUM(P11:P22) -> 605806.96 | R23: =S23/$AA$3 -> #DIV/0! | S23: =SUM(S11:S22) -> #DIV/0! | U23: =V23/$AA$3 -> #DIV/0! | V23: =SUM(V11:V22) -> #DIV/0!
D25: Expenses
D26: Property Taxes | H26: =I26/$AA$3 -> #DIV/0! | I26: =SUMIFS('P&Ls Detailed'!W:W,'P&Ls Detailed'!$E:$E,'P&Ls Summary'!$D26,'P&Ls Detailed'!$D:$D,'P&Ls Summary'!$Y$3) -> 1218605.5 | J26: =SUMIFS('P&Ls Detailed'!X:X,'P&Ls Detailed'!$E:$E,'P&Ls Summary'!$D26,'P&Ls Detailed'!$D:$D,'P&Ls Summary'!$Y$3) -> 1229186.3 | K26: =SUMIFS('P&Ls Detailed'!Y:Y,'P&Ls Detailed'!$E:$E,'P&Ls Summary'!$D26,'P&Ls Detailed'!$D:$D,'P&Ls Summary'!$Y$3) -> 1241705.9 | L26: =SUMIFS('P&Ls Detailed'!Z:Z,'P&Ls Detailed'!$E:$E,'P&Ls Summary'!$D26,'P&Ls Detailed'!$D:$D,'P&Ls Summary'!$Y$3) -> 1260485.2 | M26: =SUMIFS('P&Ls Detailed'!AA:AA,'P&Ls Detailed'!$E:$E,'P&Ls Summary'!$D26,'P&Ls Detailed'!$D:$D,'P&Ls Summary'!$Y$3) -> 1260485.2 | O26: =P26/$AA$3 -> #DIV/0! | P26: =SUMIFS('P&Ls Detailed'!W:W,'P&Ls Detailed'!$E:$E,'P&Ls Summary'!$D26,'P&Ls Detailed'!$D:$D,'P&Ls Summary'!$Y$3)-SUMIFS('P&Ls Detailed'!W:W,'P&Ls Detailed'!$E:$E,'P&Ls Summary'!$D26,'P&Ls Detailed'!$D:$D,'P&Ls Summary'!$Y$3,'P&Ls Detailed'!$F:$F,"Exclude") -> 1218605.5 | R26: =AD26 -> #DIV/0! | S26: =R26*$AA$3 -> #DIV/0! | U26: =V26/$AA$3 -> #DIV/0! | V26: =S26*(1+$V$43) -> #DIV/0! | X26: =IF(AC26=1, IF(AND($AA$5=0,AC26=1),"T12","T12 + "&TEXT($AA$5,"0.0%")),"Actual Tax") -> T12 | AA26: =O26*(1+$AA$5) -> #DIV/0! | AB26: ='Tax-Assessor Info'!O16/'P&Ls Summary'!AA3 -> #DIV/0! | AC26: 1 | AD26: =CHOOSE(AC26,AA26,AB26) -> #DIV/0! | AE26: --> Default to prior four quarter actuals
D27: Insurance | H27: =I27/$AA$3 -> #DIV/0! | I27: =SUMIFS('P&Ls Detailed'!W:W,'P&Ls Detailed'!$E:$E,'P&Ls Summary'!$D27,'P&Ls Detailed'!$D:$D,'P&Ls Summary'!$Y$3) -> 369668.22 | J27: =SUMIFS('P&Ls Detailed'!X:X,'P&Ls Detailed'!$E:$E,'P&Ls Summary'!$D27,'P&Ls Detailed'!$D:$D,'P&Ls Summary'!$Y$3) -> 377159.95 | K27: =SUMIFS('P&Ls Detailed'!Y:Y,'P&Ls Detailed'!$E:$E,'P&Ls Summary'!$D27,'P&Ls Detailed'!$D:$D,'P&Ls Summary'!$Y$3) -> 380028.08 | L27: =SUMIFS('P&Ls Detailed'!Z:Z,'P&Ls Detailed'!$E:$E,'P&Ls Summary'!$D27,'P&Ls Detailed'!$D:$D,'P&Ls Summary'!$Y$3) -> 378922.68 | M27: =SUMIFS('P&Ls Detailed'!AA:AA,'P&Ls Detailed'!$E:$E,'P&Ls Summary'!$D27,'P&Ls Detailed'!$D:$D,'P&Ls Summary'!$Y$3) -> 378922.68 | O27: =P27/$AA$3 -> #DIV/0! | P27: =SUMIFS('P&Ls Detailed'!W:W,'P&Ls Detailed'!$E:$E,'P&Ls Summary'!$D27,'P&Ls Detailed'!$D:$D,'P&Ls Summary'!$Y$3)-SUMIFS('P&Ls Detailed'!W:W,'P&Ls Detailed'!$E:$E,'P&Ls Summary'!$D27,'P&Ls Detailed'!$D:$D,'P&Ls Summary'!$Y$3,'P&Ls Detailed'!$F:$F,"Exclude") -> 369668.22 | R27: =AD27 -> #DIV/0! | S27: =R27*$AA$3 -> #DIV/0! | U27: =V27/$AA$3 -> #DIV/0! | V27: =S27*(1+$V$43) -> #DIV/0! | X27: =IF(AC27=1, IF(AND($AA$5=0,AC27=1),"T12","T12 + "&TEXT($AA$5,"0.0%")),TEXT(AB27,"$##,##0")&"/unit") -> T12 | AA27: =O27*(1+$AA$5) -> #DIV/0! | AB27: 600 | AC27: 1 | AD27: =CHOOSE(AC27,AA27,AB27) -> #DIV/0!
D28: Utilities | H28: =I28/$AA$3 -> #DIV/0! | I28: =SUMIFS('P&Ls Detailed'!W:W,'P&Ls Detailed'!$E:$E,'P&Ls Summary'!$D28,'P&Ls Detailed'!$D:$D,'P&Ls Summary'!$Y$3) -> 0 | J28: =SUMIFS('P&Ls Detailed'!X:X,'P&Ls Detailed'!$E:$E,'P&Ls Summary'!$D28,'P&Ls Detailed'!$D:$D,'P&Ls Summary'!$Y$3) -> 0 | K28: =SUMIFS('P&Ls Detailed'!Y:Y,'P&Ls Detailed'!$E:$E,'P&Ls Summary'!$D28,'P&Ls Detailed'!$D:$D,'P&Ls Summary'!$Y$3) -> 0 | L28: =SUMIFS('P&Ls Detailed'!Z:Z,'P&Ls Detailed'!$E:$E,'P&Ls Summary'!$D28,'P&Ls Detailed'!$D:$D,'P&Ls Summary'!$Y$3) -> 0 | M28: =SUMIFS('P&Ls Detailed'!AA:AA,'P&Ls Detailed'!$E:$E,'P&Ls Summary'!$D28,'P&Ls Detailed'!$D:$D,'P&Ls Summary'!$Y$3) -> 0 | O28: =P28/$AA$3 -> #DIV/0! | P28: =SUMIFS('P&Ls Detailed'!W:W,'P&Ls Detailed'!$E:$E,'P&Ls Summary'!$D28,'P&Ls Detailed'!$D:$D,'P&Ls Summary'!$Y$3)-SUMIFS('P&Ls Detailed'!W:W,'P&Ls Detailed'!$E:$E,'P&Ls Summary'!$D28,'P&Ls Detailed'!$D:$D,'P&Ls Summary'!$Y$3,'P&Ls Detailed'!$F:$F,"Exclude") -> 0 | R28: =AD28 -> #DIV/0! | S28: =R28*$AA$3 -> #DIV/0! | U28: =V28/$AA$3 -> #DIV/0! | V28: =S28*(1+$V$43) -> #DIV/0! | X28: =IF(AC28=1, IF(AND($AA$5=0,AC28=1),"T12","T12 + "&TEXT($AA$5,"0.0%")),TEXT(AB28,"$##,##0")&"/unit") -> T12 | AA28: =O28*(1+$AA$5) -> #DIV/0! | AB28: 0 | AC28: 1 | AD28: =CHOOSE(AC28,AA28,AB28) -> #DIV/0! | AE28: --> Use this line item if there is no breakdown of utilities in the T12/historical
D29: Utilities - Sewer & Water | H29: =I29/$AA$3 -> #DIV/0! | I29: =SUMIFS('P&Ls Detailed'!W:W,'P&Ls Detailed'!$E:$E,'P&Ls Summary'!$D29,'P&Ls Detailed'!$D:$D,'P&Ls Summary'!$Y$3) -> 220163.19 | J29: =SUMIFS('P&Ls Detailed'!X:X,'P&Ls Detailed'!$E:$E,'P&Ls Summary'!$D29,'P&Ls Detailed'!$D:$D,'P&Ls Summary'!$Y$3) -> 216784 | K29: =SUMIFS('P&Ls Detailed'!Y:Y,'P&Ls Detailed'!$E:$E,'P&Ls Summary'!$D29,'P&Ls Detailed'!$D:$D,'P&Ls Summary'!$Y$3) -> 212497.32 | L29: =SUMIFS('P&Ls Detailed'!Z:Z,'P&Ls Detailed'!$E:$E,'P&Ls Summary'!$D29,'P&Ls Detailed'!$D:$D,'P&Ls Summary'!$Y$3) -> 217894.72 | M29: =SUMIFS('P&Ls Detailed'!AA:AA,'P&Ls Detailed'!$E:$E,'P&Ls Summary'!$D29,'P&Ls Detailed'!$D:$D,'P&Ls Summary'!$Y$3) -> 217200 | O29: =P29/$AA$3 -> #DIV/0! | P29: =SUMIFS('P&Ls Detailed'!W:W,'P&Ls Detailed'!$E:$E,'P&Ls Summary'!$D29,'P&Ls Detailed'!$D:$D,'P&Ls Summary'!$Y$3)-SUMIFS('P&Ls Detailed'!W:W,'P&Ls Detailed'!$E:$E,'P&Ls Summary'!$D29,'P&Ls Detailed'!$D:$D,'P&Ls Summary'!$Y$3,'P&Ls Detailed'!$F:$F,"Exclude") -> 220163.19 | R29: =AD29 -> #DIV/0! | S29: =R29*$AA$3 -> #DIV/0! | U29: =V29/$AA$3 -> #DIV/0! | V29: =S29*(1+$V$43) -> #DIV/0! | X29: =IF(AC29=1, IF(AND($AA$5=0,AC29=1),"T12","T12 + "&TEXT($AA$5,"0.0%")),TEXT(AB29,"$##,##0")&"/unit") -> T12 | AA29: =O29*(1+$AA$5) -> #DIV/0! | AB29: 0 | AC29: 1 | AD29: =CHOOSE(AC29,AA29,AB29) -> #DIV/0!
D30: Utilities - Gas | H30: =I30/$AA$3 -> #DIV/0! | I30: =SUMIFS('P&Ls Detailed'!W:W,'P&Ls Detailed'!$E:$E,'P&Ls Summary'!$D30,'P&Ls Detailed'!$D:$D,'P&Ls Summary'!$Y$3) -> 282912.28 | J30: =SUMIFS('P&Ls Detailed'!X:X,'P&Ls Detailed'!$E:$E,'P&Ls Summary'!$D30,'P&Ls Detailed'!$D:$D,'P&Ls Summary'!$Y$3) -> 330328.85 | K30: =SUMIFS('P&Ls Detailed'!Y:Y,'P&Ls Detailed'!$E:$E,'P&Ls Summary'!$D30,'P&Ls Detailed'!$D:$D,'P&Ls Summary'!$Y$3) -> 415231.8 | L30: =SUMIFS('P&Ls Detailed'!Z:Z,'P&Ls Detailed'!$E:$E,'P&Ls Summary'!$D30,'P&Ls Detailed'!$D:$D,'P&Ls Summary'!$Y$3) -> 382871.8 | M30: =SUMIFS('P&Ls Detailed'!AA:AA,'P&Ls Detailed'!$E:$E,'P&Ls Summary'!$D30,'P&Ls Detailed'!$D:$D,'P&Ls Summary'!$Y$3) -> 309325.08 | O30: =P30/$AA$3 -> #DIV/0! | P30: =SUMIFS('P&Ls Detailed'!W:W,'P&Ls Detailed'!$E:$E,'P&Ls Summary'!$D30,'P&Ls Detailed'!$D:$D,'P&Ls Summary'!$Y$3)-SUMIFS('P&Ls Detailed'!W:W,'P&Ls Detailed'!$E:$E,'P&Ls Summary'!$D30,'P&Ls Detailed'!$D:$D,'P&Ls Summary'!$Y$3,'P&Ls Detailed'!$F:$F,"Exclude") -> 282912.28 | R30: =AD30 -> #DIV/0! | S30: =R30*$AA$3 -> #DIV/0! | U30: =V30/$AA$3 -> #DIV/0! | V30: =S30*(1+$V$43) -> #DIV/0! | X30: =IF(AC30=1, IF(AND($AA$5=0,AC30=1),"T12","T12 + "&TEXT($AA$5,"0.0%")),TEXT(AB30,"$##,##0")&"/unit") -> T12 | AA30: =O30*(1+$AA$5) -> #DIV/0! | AB30: 0 | AC30: 1 | AD30: =CHOOSE(AC30,AA30,AB30) -> #DIV/0!
D31: Utilities - Electric | H31: =I31/$AA$3 -> #DIV/0! | I31: =SUMIFS('P&Ls Detailed'!W:W,'P&Ls Detailed'!$E:$E,'P&Ls Summary'!$D31,'P&Ls Detailed'!$D:$D,'P&Ls Summary'!$Y$3) -> 83165.2 | J31: =SUMIFS('P&Ls Detailed'!X:X,'P&Ls Detailed'!$E:$E,'P&Ls Summary'!$D31,'P&Ls Detailed'!$D:$D,'P&Ls Summary'!$Y$3) -> 89129.067 | K31: =SUMIFS('P&Ls Detailed'!Y:Y,'P&Ls Detailed'!$E:$E,'P&Ls Summary'!$D31,'P&Ls Detailed'!$D:$D,'P&Ls Summary'!$Y$3) -> 92464.12 | L31: =SUMIFS('P&Ls Detailed'!Z:Z,'P&Ls Detailed'!$E:$E,'P&Ls Summary'!$D31,'P&Ls Detailed'!$D:$D,'P&Ls Summary'!$Y$3) -> 85245.64 | M31: =SUMIFS('P&Ls Detailed'!AA:AA,'P&Ls Detailed'!$E:$E,'P&Ls Summary'!$D31,'P&Ls Detailed'!$D:$D,'P&Ls Summary'!$Y$3) -> 88002.48 | O31: =P31/$AA$3 -> #DIV/0! | P31: =SUMIFS('P&Ls Detailed'!W:W,'P&Ls Detailed'!$E:$E,'P&Ls Summary'!$D31,'P&Ls Detailed'!$D:$D,'P&Ls Summary'!$Y$3)-SUMIFS('P&Ls Detailed'!W:W,'P&Ls Detailed'!$E:$E,'P&Ls Summary'!$D31,'P&Ls Detailed'!$D:$D,'P&Ls Summary'!$Y$3,'P&Ls Detailed'!$F:$F,"Exclude") -> 83165.2 | R31: =AD31 -> #DIV/0! | S31: =R31*$AA$3 -> #DIV/0! | U31: =V31/$AA$3 -> #DIV/0! | V31: =S31*(1+$V$43) -> #DIV/0! | X31: =IF(AC31=1, IF(AND($AA$5=0,AC31=1),"T12","T12 + "&TEXT($AA$5,"0.0%")),TEXT(AB31,"$##,##0")&"/unit") -> T12 | AA31: =O31*(1+$AA$5) -> #DIV/0! | AB31: 0 | AC31: 1 | AD31: =CHOOSE(AC31,AA31,AB31) -> #DIV/0!
D32: Repairs & Maintenance | H32: =I32/$AA$3 -> #DIV/0! | I32: =SUMIFS('P&Ls Detailed'!W:W,'P&Ls Detailed'!$E:$E,'P&Ls Summary'!$D32,'P&Ls Detailed'!$D:$D,'P&Ls Summary'!$Y$3) -> 508962.48 | J32: =SUMIFS('P&Ls Detailed'!X:X,'P&Ls Detailed'!$E:$E,'P&Ls Summary'!$D32,'P&Ls Detailed'!$D:$D,'P&Ls Summary'!$Y$3) -> 491326.83 | K32: =SUMIFS('P&Ls Detailed'!Y:Y,'P&Ls Detailed'!$E:$E,'P&Ls Summary'!$D32,'P&Ls Detailed'!$D:$D,'P&Ls Summary'!$Y$3) -> 447983.62 | L32: =SUMIFS('P&Ls Detailed'!Z:Z,'P&Ls Detailed'!$E:$E,'P&Ls Summary'!$D32,'P&Ls Detailed'!$D:$D,'P&Ls Summary'!$Y$3) -> 406646.92 | M32: =SUMIFS('P&Ls Detailed'!AA:AA,'P&Ls Detailed'!$E:$E,'P&Ls Summary'!$D32,'P&Ls Detailed'!$D:$D,'P&Ls Summary'!$Y$3) -> 454985.16 | O32: =P32/$AA$3 -> #DIV/0! | P32: =SUMIFS('P&Ls Detailed'!W:W,'P&Ls Detailed'!$E:$E,'P&Ls Summary'!$D32,'P&Ls Detailed'!$D:$D,'P&Ls Summary'!$Y$3)-SUMIFS('P&Ls Detailed'!W:W,'P&Ls Detailed'!$E:$E,'P&Ls Summary'!$D32,'P&Ls Detailed'!$D:$D,'P&Ls Summary'!$Y$3,'P&Ls Detailed'!$F:$F,"Exclude") -> 508962.48 | R32: =AD32 -> #DIV/0! | S32: =R32*$AA$3 -> #DIV/0! | U32: =V32/$AA$3 -> #DIV/0! | V32: =S32*(1+$V$43) -> #DIV/0! | X32: =IF(AC32=1, IF(AND($AA$5=0,AC32=1),"T12","T12 + "&TEXT($AA$5,"0.0%")),TEXT(AB32,"$##,##0")&"/unit") -> T12 | AA32: =O32*(1+$AA$5) -> #DIV/0! | AB32: 0 | AC32: 1 | AD32: =CHOOSE(AC32,AA32,AB32) -> #DIV/0!
D33: Contract Services | H33: =I33/$AA$3 -> #DIV/0! | I33: =SUMIFS('P&Ls Detailed'!W:W,'P&Ls Detailed'!$E:$E,'P&Ls Summary'!$D33,'P&Ls Detailed'!$D:$D,'P&Ls Summary'!$Y$3) -> 666619.11 | J33: =SUMIFS('P&Ls Detailed'!X:X,'P&Ls Detailed'!$E:$E,'P&Ls Summary'!$D33,'P&Ls Detailed'!$D:$D,'P&Ls Summary'!$Y$3) -> 650416.35 | K33: =SUMIFS('P&Ls Detailed'!Y:Y,'P&Ls Detailed'!$E:$E,'P&Ls Summary'!$D33,'P&Ls Detailed'!$D:$D,'P&Ls Summary'!$Y$3) -> 586004.46 | L33: =SUMIFS('P&Ls Detailed'!Z:Z,'P&Ls Detailed'!$E:$E,'P&Ls Summary'!$D33,'P&Ls Detailed'!$D:$D,'P&Ls Summary'!$Y$3) -> 571757.16 | M33: =SUMIFS('P&Ls Detailed'!AA:AA,'P&Ls Detailed'!$E:$E,'P&Ls Summary'!$D33,'P&Ls Detailed'!$D:$D,'P&Ls Summary'!$Y$3) -> 603813.72 | O33: =P33/$AA$3 -> #DIV/0! | P33: =SUMIFS('P&Ls Detailed'!W:W,'P&Ls Detailed'!$E:$E,'P&Ls Summary'!$D33,'P&Ls Detailed'!$D:$D,'P&Ls Summary'!$Y$3)-SUMIFS('P&Ls Detailed'!W:W,'P&Ls Detailed'!$E:$E,'P&Ls Summary'!$D33,'P&Ls Detailed'!$D:$D,'P&Ls Summary'!$Y$3,'P&Ls Detailed'!$F:$F,"Exclude") -> 666619.11 | R33: =AD33 -> #DIV/0! | S33: =R33*$AA$3 -> #DIV/0! | U33: =V33/$AA$3 -> #DIV/0! | V33: =S33*(1+$V$43) -> #DIV/0! | X33: =IF(AC33=1, IF(AND($AA$5=0,AC33=1),"T12","T12 + "&TEXT($AA$5,"0.0%")),TEXT(AB33,"$##,##0")&"/unit") -> T12 | AA33: =O33*(1+$AA$5) -> #DIV/0! | AB33: 0 | AC33: 1 | AD33: =CHOOSE(AC33,AA33,AB33) -> #DIV/0!
D34: General & Administrative | H34: =I34/$AA$3 -> #DIV/0! | I34: =SUMIFS('P&Ls Detailed'!W:W,'P&Ls Detailed'!$E:$E,'P&Ls Summary'!$D34,'P&Ls Detailed'!$D:$D,'P&Ls Summary'!$Y$3) -> 239070.86 | J34: =SUMIFS('P&Ls Detailed'!X:X,'P&Ls Detailed'!$E:$E,'P&Ls Summary'!$D34,'P&Ls Detailed'!$D:$D,'P&Ls Summary'!$Y$3) -> 234530.68 | K34: =SUMIFS('P&Ls Detailed'!Y:Y,'P&Ls Detailed'!$E:$E,'P&Ls Summary'!$D34,'P&Ls Detailed'!$D:$D,'P&Ls Summary'!$Y$3) -> 222801.2 | L34: =SUMIFS('P&Ls Detailed'!Z:Z,'P&Ls Detailed'!$E:$E,'P&Ls Summary'!$D34,'P&Ls Detailed'!$D:$D,'P&Ls Summary'!$Y$3) -> 206203.96 | M34: =SUMIFS('P&Ls Detailed'!AA:AA,'P&Ls Detailed'!$E:$E,'P&Ls Summary'!$D34,'P&Ls Detailed'!$D:$D,'P&Ls Summary'!$Y$3) -> 171118.68 | O34: =P34/$AA$3 -> #DIV/0! | P34: =SUMIFS('P&Ls Detailed'!W:W,'P&Ls Detailed'!$E:$E,'P&Ls Summary'!$D34,'P&Ls Detailed'!$D:$D,'P&Ls Summary'!$Y$3)-SUMIFS('P&Ls Detailed'!W:W,'P&Ls Detailed'!$E:$E,'P&Ls Summary'!$D34,'P&Ls Detailed'!$D:$D,'P&Ls Summary'!$Y$3,'P&Ls Detailed'!$F:$F,"Exclude") -> 239070.86 | R34: =AD34 -> #DIV/0! | S34: =R34*$AA$3 -> #DIV/0! | U34: =V34/$AA$3 -> #DIV/0! | V34: =S34*(1+$V$43) -> #DIV/0! | X34: =IF(AC34=1, IF(AND($AA$5=0,AC34=1),"T12","T12 + "&TEXT($AA$5,"0.0%")),TEXT(AB34,"$##,##0")&"/unit") -> T12 | AA34: =O34*(1+$AA$5) -> #DIV/0! | AB34: 0 | AC34: 1 | AD34: =CHOOSE(AC34,AA34,AB34) -> #DIV/0!
D35: Advertising & Marketing | H35: =I35/$AA$3 -> #DIV/0! | I35: =SUMIFS('P&Ls Detailed'!W:W,'P&Ls Detailed'!$E:$E,'P&Ls Summary'!$D35,'P&Ls Detailed'!$D:$D,'P&Ls Summary'!$Y$3) -> 16948.87 | J35: =SUMIFS('P&Ls Detailed'!X:X,'P&Ls Detailed'!$E:$E,'P&Ls Summary'!$D35,'P&Ls Detailed'!$D:$D,'P&Ls Summary'!$Y$3) -> 15091.827 | K35: =SUMIFS('P&Ls Detailed'!Y:Y,'P&Ls Detailed'!$E:$E,'P&Ls Summary'!$D35,'P&Ls Detailed'!$D:$D,'P&Ls Summary'!$Y$3) -> 16140 | L35: =SUMIFS('P&Ls Detailed'!Z:Z,'P&Ls Detailed'!$E:$E,'P&Ls Summary'!$D35,'P&Ls Detailed'!$D:$D,'P&Ls Summary'!$Y$3) -> 13700 | M35: =SUMIFS('P&Ls Detailed'!AA:AA,'P&Ls Detailed'!$E:$E,'P&Ls Summary'!$D35,'P&Ls Detailed'!$D:$D,'P&Ls Summary'!$Y$3) -> 10500 | O35: =P35/$AA$3 -> #DIV/0! | P35: =SUMIFS('P&Ls Detailed'!W:W,'P&Ls Detailed'!$E:$E,'P&Ls Summary'!$D35,'P&Ls Detailed'!$D:$D,'P&Ls Summary'!$Y$3)-SUMIFS('P&Ls Detailed'!W:W,'P&Ls Detailed'!$E:$E,'P&Ls Summary'!$D35,'P&Ls Detailed'!$D:$D,'P&Ls Summary'!$Y$3,'P&Ls Detailed'!$F:$F,"Exclude") -> 16948.87 | R35: =AD35 -> #DIV/0! | S35: =R35*$AA$3 -> #DIV/0! | U35: =V35/$AA$3 -> #DIV/0! | V35: =S35*(1+$V$43) -> #DIV/0! | X35: =IF(AC35=1, IF(AND($AA$5=0,AC35=1),"T12","T12 + "&TEXT($AA$5,"0.0%")),TEXT(AB35,"$##,##0")&"/unit") -> T12 | AA35: =O35*(1+$AA$5) -> #DIV/0! | AB35: 0 | AC35: 1 | AD35: =CHOOSE(AC35,AA35,AB35) -> #DIV/0!
D36: Personnel | H36: =I36/$AA$3 -> #DIV/0! | I36: =SUMIFS('P&Ls Detailed'!W:W,'P&Ls Detailed'!$E:$E,'P&Ls Summary'!$D36,'P&Ls Detailed'!$D:$D,'P&Ls Summary'!$Y$3) -> 1381090.5 | J36: =SUMIFS('P&Ls Detailed'!X:X,'P&Ls Detailed'!$E:$E,'P&Ls Summary'!$D36,'P&Ls Detailed'!$D:$D,'P&Ls Summary'!$Y$3) -> 1410938.2 | K36: =SUMIFS('P&Ls Detailed'!Y:Y,'P&Ls Detailed'!$E:$E,'P&Ls Summary'!$D36,'P&Ls Detailed'!$D:$D,'P&Ls Summary'!$Y$3) -> 1423219.7 | L36: =SUMIFS('P&Ls Detailed'!Z:Z,'P&Ls Detailed'!$E:$E,'P&Ls Summary'!$D36,'P&Ls Detailed'!$D:$D,'P&Ls Summary'!$Y$3) -> 1289361.5 | M36: =SUMIFS('P&Ls Detailed'!AA:AA,'P&Ls Detailed'!$E:$E,'P&Ls Summary'!$D36,'P&Ls Detailed'!$D:$D,'P&Ls Summary'!$Y$3) -> 1253655.5 | O36: =P36/$AA$3 -> #DIV/0! | P36: =SUMIFS('P&Ls Detailed'!W:W,'P&Ls Detailed'!$E:$E,'P&Ls Summary'!$D36,'P&Ls Detailed'!$D:$D,'P&Ls Summary'!$Y$3)-SUMIFS('P&Ls Detailed'!W:W,'P&Ls Detailed'!$E:$E,'P&Ls Summary'!$D36,'P&Ls Detailed'!$D:$D,'P&Ls Summary'!$Y$3,'P&Ls Detailed'!$F:$F,"Exclude") -> 512779.6 | R36: =AD36 -> #DIV/0! | S36: =R36*$AA$3 -> #DIV/0! | U36: =V36/$AA$3 -> #DIV/0! | V36: =S36*(1+$V$43) -> #DIV/0! | X36: =IF(AC36=1, IF(AND($AA$5=0,AC36=1),"T12","T12 + "&TEXT($AA$5,"0.0%")),TEXT(AB36,"$##,##0")&"/unit") -> T12 | AA36: =O36*(1+$AA$5) -> #DIV/0! | AB36: 0 | AC36: 1 | AD36: =CHOOSE(AC36,AA36,AB36) -> #DIV/0!
D37: Management Fee | H37: =I37/$AA$3 -> #DIV/0! | I37: =SUMIFS('P&Ls Detailed'!W:W,'P&Ls Detailed'!$E:$E,'P&Ls Summary'!$D37,'P&Ls Detailed'!$D:$D,'P&Ls Summary'!$Y$3) -> 530572 | J37: =SUMIFS('P&Ls Detailed'!X:X,'P&Ls Detailed'!$E:$E,'P&Ls Summary'!$D37,'P&Ls Detailed'!$D:$D,'P&Ls Summary'!$Y$3) -> 537656 | K37: =SUMIFS('P&Ls Detailed'!Y:Y,'P&Ls Detailed'!$E:$E,'P&Ls Summary'!$D37,'P&Ls Detailed'!$D:$D,'P&Ls Summary'!$Y$3) -> 545684 | L37: =SUMIFS('P&Ls Detailed'!Z:Z,'P&Ls Detailed'!$E:$E,'P&Ls Summary'!$D37,'P&Ls Detailed'!$D:$D,'P&Ls Summary'!$Y$3) -> 540784 | M37: =SUMIFS('P&Ls Detailed'!AA:AA,'P&Ls Detailed'!$E:$E,'P&Ls Summary'!$D37,'P&Ls Detailed'!$D:$D,'P&Ls Summary'!$Y$3) -> 542424 | O37: =P37/$AA$3 -> #DIV/0! | P37: =SUMIFS('P&Ls Detailed'!W:W,'P&Ls Detailed'!$E:$E,'P&Ls Summary'!$D37,'P&Ls Detailed'!$D:$D,'P&Ls Summary'!$Y$3)-SUMIFS('P&Ls Detailed'!W:W,'P&Ls Detailed'!$E:$E,'P&Ls Summary'!$D37,'P&Ls Detailed'!$D:$D,'P&Ls Summary'!$Y$3,'P&Ls Detailed'!$F:$F,"Exclude") -> 530572 | R37: =S37/$AA$3 -> #DIV/0! | S37: =$AC$37*S23 -> #DIV/0! | U37: =V37/$AA$3 -> #DIV/0! | V37: =$AC$37*V23 -> #DIV/0! | X37: =TEXT(AC37,"##.0%")&" of EGI" -> 3.0% of EGI | AA37: =O37*(1+$AA$5) -> #DIV/0! | AB37: =S37/'P&Ls Summary'!$AA$3 -> #DIV/0! | AC37: 0.03 | AD37: =-AB37 -> #DIV/0! | AE37: --> Default to 3.0%
D38: Replacement Reserves | H38: =I38/$AA$3 -> #DIV/0! | I38: =SUMIFS('P&Ls Detailed'!W:W,'P&Ls Detailed'!$E:$E,'P&Ls Summary'!$D38,'P&Ls Detailed'!$D:$D,'P&Ls Summary'!$Y$3) -> 0 | J38: =SUMIFS('P&Ls Detailed'!X:X,'P&Ls Detailed'!$E:$E,'P&Ls Summary'!$D38,'P&Ls Detailed'!$D:$D,'P&Ls Summary'!$Y$3) -> 0 | K38: =SUMIFS('P&Ls Detailed'!Y:Y,'P&Ls Detailed'!$E:$E,'P&Ls Summary'!$D38,'P&Ls Detailed'!$D:$D,'P&Ls Summary'!$Y$3) -> 0 | L38: =SUMIFS('P&Ls Detailed'!Z:Z,'P&Ls Detailed'!$E:$E,'P&Ls Summary'!$D38,'P&Ls Detailed'!$D:$D,'P&Ls Summary'!$Y$3) -> 0 | M38: =SUMIFS('P&Ls Detailed'!AA:AA,'P&Ls Detailed'!$E:$E,'P&Ls Summary'!$D38,'P&Ls Detailed'!$D:$D,'P&Ls Summary'!$Y$3) -> 0 | O38: =P38/$AA$3 -> #DIV/0! | P38: =SUMIFS('P&Ls Detailed'!W:W,'P&Ls Detailed'!$E:$E,'P&Ls Summary'!$D38,'P&Ls Detailed'!$D:$D,'P&Ls Summary'!$Y$3)-SUMIFS('P&Ls Detailed'!W:W,'P&Ls Detailed'!$E:$E,'P&Ls Summary'!$D38,'P&Ls Detailed'!$D:$D,'P&Ls Summary'!$Y$3,'P&Ls Detailed'!$F:$F,"Exclude") -> 0 | R38: =AD38 -> #DIV/0! | S38: =R38*$AA$3 -> #DIV/0! | U38: =V38/$AA$3 -> #DIV/0! | V38: =S38*(1+$V$43) -> #DIV/0! | X38: =IF(AC38=1, IF(AND($AA$5=0,AC38=1),"T12","T12 + "&TEXT($AA$5,"0.0%")),TEXT(AB38,"$##,##0")&"/unit") -> T12 | AA38: =O38*(1+$AA$5) -> #DIV/0! | AB38: 250 | AC38: 1 | AD38: =CHOOSE(AC38,AA38,AB38) -> #DIV/0! | AE38: --> Default to $0
D39: Total Operating Expenses | E39: =SUM(E26:E38) -> 0 | F39: =SUM(F26:F38) -> 0 | G39: =SUM(G26:G38) -> 0 | H39: =I39/$AA$3 -> #DIV/0! | I39: =SUM(I26:I38) -> 5517778.2 | J39: =SUM(J26:J38) -> 5582548 | K39: =SUM(K26:K38) -> 5583760.2 | L39: =SUM(L26:L38) -> 5353873.6 | M39: =SUM(M26:M38) -> 5290432.4 | O39: =P39/$AA$3 -> #DIV/0! | P39: =SUM(P26:P38) -> 4649467.3 | R39: =S39/$AA$3 -> #DIV/0! | S39: =SUM(S26:S38) -> #DIV/0! | U39: =V39/$AA$3 -> #DIV/0! | V39: =SUM(V26:V38) -> #DIV/0!
D40: Net Operating Income | E40: =E23-E39 -> 0 | F40: =F23-F39 -> 0 | G40: =G23-G39 -> 0 | H40: =I40/$AA$3 -> #DIV/0! | I40: =I23-I39 -> 6299663.2 | J40: =J23-J39 -> 6347669.3 | K40: =K23-K39 -> 6447476 | L40: =L23-L39 -> 6788027.7 | M40: =M23-M39 -> 6902808.5 | O40: =P40/$AA$3 -> #DIV/0! | P40: =P23-P39 -> -4043660.3 | R40: =S40/$AA$3 -> #DIV/0! | S40: =S23-S39 -> #DIV/0! | U40: =V40/$AA$3 -> #DIV/0! | V40: =V23-V39 -> #DIV/0!
O42: In-Place Notes: | R42: Rent Inc > IP --> | S42: 0 | U42: Rent Inc > IP--> | V42: 0
O43: - In-Place rental revenue from RR | R43: IP Notes: | U43: Oth Inc / OpEx Inc > IP--> | V43: 0
O44: - OpEx is T12 Minus Exclusions on 'P&L Detailed' Tab | R44: - In-Place rental revenue from RR plus market rates for vacant units, plus growth factor above | U44: Stabilized Notes:
R45: - OpEx from Column AD (T12 plus inflation or client override) | U45: *Difference b/w Yr 1 & Stabilzed is LTL and growth factors above
D61: Income | I61: =I23='P&Ls Detailed'!W43 -> TRUE | J61: =J23='P&Ls Detailed'!X43 -> TRUE | K61: =K23='P&Ls Detailed'!Y43 -> TRUE | L61: =L23='P&Ls Detailed'!Z43 -> TRUE | M61: =M23='P&Ls Detailed'!AA43 -> TRUE | S61: =S23='External UW'!F22 -> #DIV/0! | V61: =V23='External UW'!I22 -> #DIV/0!
D62: Expense | I62: =I39='P&Ls Detailed'!W128 -> TRUE | J62: =J39='P&Ls Detailed'!X128 -> TRUE | K62: =K39='P&Ls Detailed'!Y128 -> TRUE | L62: =L39='P&Ls Detailed'!Z128 -> TRUE | M62: =M39='P&Ls Detailed'!AA128 -> TRUE | S62: =S39='External UW'!F38 -> #DIV/0! | V62: =V39='External UW'!I38 -> #DIV/0!
D63: NOI | I63: =I40='P&Ls Detailed'!W129 -> TRUE | J63: =J40='P&Ls Detailed'!X129 -> TRUE | K63: =K40='P&Ls Detailed'!Y129 -> TRUE | L63: =L40='P&Ls Detailed'!Z129 -> TRUE | M63: =M40='P&Ls Detailed'!AA129 -> TRUE | S63: =S40='External UW'!F39 -> #DIV/0! | V63: =V40='External UW'!I39 -> #DIV/0!
D99: Data Validation
D100: =D9 -> Market Rent
D101: =D10 -> Loss to Lease
D102: =D12 -> Less Vacancy
D103: =D13 -> Less: Concessions
D104: =D14 -> Less: Bad Debt/Collection
D105: =D15 -> Pet Income
D106: =D16 -> Laundry Income
D107: =D17 -> Parking Income
D108: =D18 -> Storage Income
D109: =D19 -> Utility Reimbursement
D110: =D20 -> Other Income
D111: =D21 -> Commercial Income
D112: =D22 -> Less Commercial Vacancy
D114: =D36 -> Personnel
D115: =D26 -> Property Taxes
D116: =D27 -> Insurance
D117: =D28 -> Utilities
D118: =D29 -> Utilities - Sewer & Water
D119: =D30 -> Utilities - Gas
D120: =D31 -> Utilities - Electric
D121: =D32 -> Repairs & Maintenance
D122: =D33 -> Contract Services
D123: =D34 -> General & Administrative
D124: =D35 -> Advertising & Marketing
D125: =D37 -> Management Fee
D126: =D38 -> Replacement Reserves

Sheet 10-Yr CF
B3: 0 | C3: 10-YEAR CASH FLOW | O3: ='Exec Summ'!$F$6 -> Hudson View Park
E5: 1 | F5: =E5+1 -> 2 | G5: =F5+1 -> 3 | H5: =G5+1 -> 4 | I5: =H5+1 -> 5 | J5: =I5+1 -> 6 | K5: =J5+1 -> 7 | L5: =K5+1 -> 8 | M5: =L5+1 -> 9 | N5: =M5+1 -> 10 | Q5: % Growth / Assumption
D7: Income
D8: Market Rent | E8: =INDEX('P&Ls Summary'!$S$9:$S$40,MATCH('10-Yr CF'!D8,'P&Ls Summary'!$D$9:$D$40,0)) -> #DIV/0! | F8: =E8*(1+$Q8) -> #DIV/0! | G8: =F8*(1+$Q8) -> #DIV/0! | H8: =G8*(1+$Q8) -> #DIV/0! | I8: =H8*(1+$Q8) -> #DIV/0! | J8: =I8*(1+$Q8) -> #DIV/0! | K8: =J8*(1+$Q8) -> #DIV/0! | L8: =K8*(1+$Q8) -> #DIV/0! | M8: =L8*(1+$Q8) -> #DIV/0! | N8: =M8*(1+$Q8) -> #DIV/0! | Q8: 0.03 | T8: Yrs to Stabilize
D9: Loss to Lease | E9: =INDEX('P&Ls Summary'!$S$9:$S$40,MATCH('10-Yr CF'!D9,'P&Ls Summary'!$D$9:$D$40,0)) -> #DIV/0! | F9: =IF(F5>$T$9,-F8*$Q$9,(1-(E5/$T$9))*$E$9) -> #DIV/0! | G9: =IF(G5>$T$9,-G8*$Q$9,(1-(F5/$T$9))*$E$9) -> #DIV/0! | H9: =IF(H5>$T$9,-H8*$Q$9,(1-(G5/$T$9))*$E$9) -> #DIV/0! | I9: =IF(I5>$T$9,-I8*$Q$9,(1-(H5/$T$9))*$E$9) -> #DIV/0! | J9: =IF(J5>$T$9,-J8*$Q$9,(1-(I5/$T$9))*$E$9) -> #DIV/0! | K9: =IF(K5>$T$9,-K8*$Q$9,(1-(J5/$T$9))*$E$9) -> #DIV/0! | L9: =IF(L5>$T$9,-L8*$Q$9,(1-(K5/$T$9))*$E$9) -> #DIV/0! | M9: =IF(M5>$T$9,-M8*$Q$9,(1-(L5/$T$9))*$E$9) -> #DIV/0! | N9: =IF(N5>$T$9,-N8*$Q$9,(1-(M5/$T$9))*$E$9) -> #DIV/0! | Q9: 0.015 | R9: Stabilized % | T9: 4 | U9: ="--> after Y"&T9&", LTL will be based on "&TEXT(Q9,"0.0%")&" of Market Rent" -> --> after Y4, LTL will be based on 1.5% of Market Rent
D10: Gross Rental Income | E10: =SUM(E8:E9) -> #DIV/0! | F10: =SUM(F8:F9) -> #DIV/0! | G10: =SUM(G8:G9) -> #DIV/0! | H10: =SUM(H8:H9) -> #DIV/0! | I10: =SUM(I8:I9) -> #DIV/0! | J10: =SUM(J8:J9) -> #DIV/0! | K10: =SUM(K8:K9) -> #DIV/0! | L10: =SUM(L8:L9) -> #DIV/0! | ... N10: =SUM(N8:N9) -> #DIV/0!
D11: Less Vacancy | E11: =INDEX('P&Ls Summary'!$S$9:$S$40,MATCH('10-Yr CF'!D11,'P&Ls Summary'!$D$9:$D$40,0)) -> 0 | F11: =-$Q11*F$10 -> #DIV/0! | G11: =-$Q11*G$10 -> #DIV/0! | H11: =-$Q11*H$10 -> #DIV/0! | I11: =-$Q11*I$10 -> #DIV/0! | J11: =-$Q11*J$10 -> #DIV/0! | K11: =-$Q11*K$10 -> #DIV/0! | L11: =-$Q11*L$10 -> #DIV/0! | M11: =-$Q11*M$10 -> #DIV/0! | N11: =-$Q11*N$10 -> #DIV/0! | Q11: ='P&Ls Summary'!AC12 -> 0.03 | R11: of Gross Rental Income
D12: Less: Concessions | E12: =INDEX('P&Ls Summary'!$S$9:$S$40,MATCH('10-Yr CF'!D12,'P&Ls Summary'!$D$9:$D$40,0)) -> 0 | F12: =-$Q12*F$10 -> #DIV/0! | G12: =-$Q12*G$10 -> #DIV/0! | H12: =-$Q12*H$10 -> #DIV/0! | I12: =-$Q12*I$10 -> #DIV/0! | J12: =-$Q12*J$10 -> #DIV/0! | K12: =-$Q12*K$10 -> #DIV/0! | L12: =-$Q12*L$10 -> #DIV/0! | M12: =-$Q12*M$10 -> #DIV/0! | N12: =-$Q12*N$10 -> #DIV/0! | Q12: ='P&Ls Summary'!AC13 -> 0 | R12: of Gross Rental Income
D13: Less: Bad Debt/Collection | E13: =INDEX('P&Ls Summary'!$S$9:$S$40,MATCH('10-Yr CF'!D13,'P&Ls Summary'!$D$9:$D$40,0)) -> 0 | F13: =-$Q13*F$10 -> #DIV/0! | G13: =-$Q13*G$10 -> #DIV/0! | H13: =-$Q13*H$10 -> #DIV/0! | I13: =-$Q13*I$10 -> #DIV/0! | J13: =-$Q13*J$10 -> #DIV/0! | K13: =-$Q13*K$10 -> #DIV/0! | L13: =-$Q13*L$10 -> #DIV/0! | M13: =-$Q13*M$10 -> #DIV/0! | N13: =-$Q13*N$10 -> #DIV/0! | Q13: ='P&Ls Summary'!AC14 -> 0 | R13: of Gross Rental Income
D14: Pet Income | E14: =INDEX('P&Ls Summary'!$S$9:$S$40,MATCH('10-Yr CF'!D14,'P&Ls Summary'!$D$9:$D$40,0)) -> #DIV/0! | F14: =E14*(1+$Q14) -> #DIV/0! | G14: =F14*(1+$Q14) -> #DIV/0! | H14: =G14*(1+$Q14) -> #DIV/0! | I14: =H14*(1+$Q14) -> #DIV/0! | J14: =I14*(1+$Q14) -> #DIV/0! | K14: =J14*(1+$Q14) -> #DIV/0! | L14: =K14*(1+$Q14) -> #DIV/0! | M14: =L14*(1+$Q14) -> #DIV/0! | N14: =M14*(1+$Q14) -> #DIV/0! | Q14: 0.025
D15: Laundry Income | E15: =INDEX('P&Ls Summary'!$S$9:$S$40,MATCH('10-Yr CF'!D15,'P&Ls Summary'!$D$9:$D$40,0)) -> #DIV/0! | F15: =E15*(1+$Q15) -> #DIV/0! | G15: =F15*(1+$Q15) -> #DIV/0! | H15: =G15*(1+$Q15) -> #DIV/0! | I15: =H15*(1+$Q15) -> #DIV/0! | J15: =I15*(1+$Q15) -> #DIV/0! | K15: =J15*(1+$Q15) -> #DIV/0! | L15: =K15*(1+$Q15) -> #DIV/0! | M15: =L15*(1+$Q15) -> #DIV/0! | N15: =M15*(1+$Q15) -> #DIV/0! | Q15: =$Q$14 -> 0.025
D16: Parking Income | E16: =INDEX('P&Ls Summary'!$S$9:$S$40,MATCH('10-Yr CF'!D16,'P&Ls Summary'!$D$9:$D$40,0)) -> #DIV/0! | F16: =E16*(1+$Q16) -> #DIV/0! | G16: =F16*(1+$Q16) -> #DIV/0! | H16: =G16*(1+$Q16) -> #DIV/0! | I16: =H16*(1+$Q16) -> #DIV/0! | J16: =I16*(1+$Q16) -> #DIV/0! | K16: =J16*(1+$Q16) -> #DIV/0! | L16: =K16*(1+$Q16) -> #DIV/0! | M16: =L16*(1+$Q16) -> #DIV/0! | N16: =M16*(1+$Q16) -> #DIV/0! | Q16: =$Q$14 -> 0.025
D17: Storage Income | E17: =INDEX('P&Ls Summary'!$S$9:$S$40,MATCH('10-Yr CF'!D17,'P&Ls Summary'!$D$9:$D$40,0)) -> #DIV/0! | F17: =E17*(1+$Q17) -> #DIV/0! | G17: =F17*(1+$Q17) -> #DIV/0! | H17: =G17*(1+$Q17) -> #DIV/0! | I17: =H17*(1+$Q17) -> #DIV/0! | J17: =I17*(1+$Q17) -> #DIV/0! | K17: =J17*(1+$Q17) -> #DIV/0! | L17: =K17*(1+$Q17) -> #DIV/0! | M17: =L17*(1+$Q17) -> #DIV/0! | N17: =M17*(1+$Q17) -> #DIV/0! | Q17: =$Q$14 -> 0.025
D18: Utility Reimbursement | E18: =INDEX('P&Ls Summary'!$S$9:$S$40,MATCH('10-Yr CF'!D18,'P&Ls Summary'!$D$9:$D$40,0)) -> #DIV/0! | F18: =E18*(1+$Q18) -> #DIV/0! | G18: =F18*(1+$Q18) -> #DIV/0! | H18: =G18*(1+$Q18) -> #DIV/0! | I18: =H18*(1+$Q18) -> #DIV/0! | J18: =I18*(1+$Q18) -> #DIV/0! | K18: =J18*(1+$Q18) -> #DIV/0! | L18: =K18*(1+$Q18) -> #DIV/0! | M18: =L18*(1+$Q18) -> #DIV/0! | N18: =M18*(1+$Q18) -> #DIV/0! | Q18: =$Q$14 -> 0.025
D19: Other Income | E19: =INDEX('P&Ls Summary'!$S$9:$S$40,MATCH('10-Yr CF'!D19,'P&Ls Summary'!$D$9:$D$40,0)) -> #DIV/0! | F19: =E19*(1+$Q19) -> #DIV/0! | G19: =F19*(1+$Q19) -> #DIV/0! | H19: =G19*(1+$Q19) -> #DIV/0! | I19: =H19*(1+$Q19) -> #DIV/0! | J19: =I19*(1+$Q19) -> #DIV/0! | K19: =J19*(1+$Q19) -> #DIV/0! | L19: =K19*(1+$Q19) -> #DIV/0! | M19: =L19*(1+$Q19) -> #DIV/0! | N19: =M19*(1+$Q19) -> #DIV/0! | Q19: =$Q$14 -> 0.025
D20: Commercial Income | E20: =INDEX('P&Ls Summary'!$S$9:$S$40,MATCH('10-Yr CF'!D20,'P&Ls Summary'!$D$9:$D$40,0)) -> 0 | F20: =E20*(1+$Q20) -> 0 | G20: =F20*(1+$Q20) -> 0 | H20: =G20*(1+$Q20) -> 0 | I20: =H20*(1+$Q20) -> 0 | J20: =I20*(1+$Q20) -> 0 | K20: =J20*(1+$Q20) -> 0 | L20: =K20*(1+$Q20) -> 0 | M20: =L20*(1+$Q20) -> 0 | N20: =M20*(1+$Q20) -> 0 | Q20: =$Q$14 -> 0.025
D21: Less Commercial Vacancy | E21: =INDEX('P&Ls Summary'!$S$9:$S$40,MATCH('10-Yr CF'!D21,'P&Ls Summary'!$D$9:$D$40,0)) -> 0 | F21: =-$Q21*F$20 -> 0 | G21: =-$Q21*G$20 -> 0 | H21: =-$Q21*H$20 -> 0 | I21: =-$Q21*I$20 -> 0 | J21: =-$Q21*J$20 -> 0 | K21: =-$Q21*K$20 -> 0 | L21: =-$Q21*L$20 -> 0 | M21: =-$Q21*M$20 -> 0 | N21: =-$Q21*N$20 -> 0 | Q21: ='P&Ls Summary'!AC22 -> 0.05 | R21: of Commercial Income
D22: Effective Gross Income | E22: =SUM(E10:E21) -> #DIV/0! | F22: =SUM(F10:F21) -> #DIV/0! | G22: =SUM(G10:G21) -> #DIV/0! | H22: =SUM(H10:H21) -> #DIV/0! | I22: =SUM(I10:I21) -> #DIV/0! | J22: =SUM(J10:J21) -> #DIV/0! | K22: =SUM(K10:K21) -> #DIV/0! | L22: =SUM(L10:L21) -> #DIV/0! | ... N22: =SUM(N10:N21) -> #DIV/0!
D24: Expenses
D25: Property Taxes | E25: =INDEX('P&Ls Summary'!$S$9:$S$40,MATCH('10-Yr CF'!D25,'P&Ls Summary'!$D$9:$D$40,0)) -> #DIV/0! | F25: =E25*(1+$Q25) -> #DIV/0! | G25: =F25*(1+$Q25) -> #DIV/0! | H25: =G25*(1+$Q25) -> #DIV/0! | I25: =H25*(1+$Q25) -> #DIV/0! | J25: =I25*(1+$Q25) -> #DIV/0! | K25: =J25*(1+$Q25) -> #DIV/0! | L25: =K25*(1+$Q25) -> #DIV/0! | M25: =L25*(1+$Q25) -> #DIV/0! | N25: =M25*(1+$Q25) -> #DIV/0! | Q25: =$Q$14 -> 0.025
D26: Insurance | E26: =INDEX('P&Ls Summary'!$S$9:$S$40,MATCH('10-Yr CF'!D26,'P&Ls Summary'!$D$9:$D$40,0)) -> #DIV/0! | F26: =E26*(1+$Q26) -> #DIV/0! | G26: =F26*(1+$Q26) -> #DIV/0! | H26: =G26*(1+$Q26) -> #DIV/0! | I26: =H26*(1+$Q26) -> #DIV/0! | J26: =I26*(1+$Q26) -> #DIV/0! | K26: =J26*(1+$Q26) -> #DIV/0! | L26: =K26*(1+$Q26) -> #DIV/0! | M26: =L26*(1+$Q26) -> #DIV/0! | N26: =M26*(1+$Q26) -> #DIV/0! | Q26: =$Q$14 -> 0.025
D27: Utilities | E27: =INDEX('P&Ls Summary'!$S$9:$S$40,MATCH('10-Yr CF'!D27,'P&Ls Summary'!$D$9:$D$40,0)) -> #DIV/0! | F27: =E27*(1+$Q27) -> #DIV/0! | G27: =F27*(1+$Q27) -> #DIV/0! | H27: =G27*(1+$Q27) -> #DIV/0! | I27: =H27*(1+$Q27) -> #DIV/0! | J27: =I27*(1+$Q27) -> #DIV/0! | K27: =J27*(1+$Q27) -> #DIV/0! | L27: =K27*(1+$Q27) -> #DIV/0! | M27: =L27*(1+$Q27) -> #DIV/0! | N27: =M27*(1+$Q27) -> #DIV/0! | Q27: =$Q$14 -> 0.025
D28: Utilities - Sewer & Water | E28: =INDEX('P&Ls Summary'!$S$9:$S$40,MATCH('10-Yr CF'!D28,'P&Ls Summary'!$D$9:$D$40,0)) -> #DIV/0! | F28: =E28*(1+$Q28) -> #DIV/0! | G28: =F28*(1+$Q28) -> #DIV/0! | H28: =G28*(1+$Q28) -> #DIV/0! | I28: =H28*(1+$Q28) -> #DIV/0! | J28: =I28*(1+$Q28) -> #DIV/0! | K28: =J28*(1+$Q28) -> #DIV/0! | L28: =K28*(1+$Q28) -> #DIV/0! | M28: =L28*(1+$Q28) -> #DIV/0! | N28: =M28*(1+$Q28) -> #DIV/0! | Q28: =$Q$14 -> 0.025
D29: Utilities - Gas | E29: =INDEX('P&Ls Summary'!$S$9:$S$40,MATCH('10-Yr CF'!D29,'P&Ls Summary'!$D$9:$D$40,0)) -> #DIV/0! | F29: =E29*(1+$Q29) -> #DIV/0! | G29: =F29*(1+$Q29) -> #DIV/0! | H29: =G29*(1+$Q29) -> #DIV/0! | I29: =H29*(1+$Q29) -> #DIV/0! | J29: =I29*(1+$Q29) -> #DIV/0! | K29: =J29*(1+$Q29) -> #DIV/0! | L29: =K29*(1+$Q29) -> #DIV/0! | M29: =L29*(1+$Q29) -> #DIV/0! | N29: =M29*(1+$Q29) -> #DIV/0! | Q29: =$Q$14 -> 0.025
D30: Utilities - Electric | E30: =INDEX('P&Ls Summary'!$S$9:$S$40,MATCH('10-Yr CF'!D30,'P&Ls Summary'!$D$9:$D$40,0)) -> #DIV/0! | F30: =E30*(1+$Q30) -> #DIV/0! | G30: =F30*(1+$Q30) -> #DIV/0! | H30: =G30*(1+$Q30) -> #DIV/0! | I30: =H30*(1+$Q30) -> #DIV/0! | J30: =I30*(1+$Q30) -> #DIV/0! | K30: =J30*(1+$Q30) -> #DIV/0! | L30: =K30*(1+$Q30) -> #DIV/0! | M30: =L30*(1+$Q30) -> #DIV/0! | N30: =M30*(1+$Q30) -> #DIV/0! | Q30: =$Q$14 -> 0.025
D31: Repairs & Maintenance | E31: =INDEX('P&Ls Summary'!$S$9:$S$40,MATCH('10-Yr CF'!D31,'P&Ls Summary'!$D$9:$D$40,0)) -> #DIV/0! | F31: =E31*(1+$Q31) -> #DIV/0! | G31: =F31*(1+$Q31) -> #DIV/0! | H31: =G31*(1+$Q31) -> #DIV/0! | I31: =H31*(1+$Q31) -> #DIV/0! | J31: =I31*(1+$Q31) -> #DIV/0! | K31: =J31*(1+$Q31) -> #DIV/0! | L31: =K31*(1+$Q31) -> #DIV/0! | M31: =L31*(1+$Q31) -> #DIV/0! | N31: =M31*(1+$Q31) -> #DIV/0! | Q31: =$Q$14 -> 0.025
D32: Contract Services | E32: =INDEX('P&Ls Summary'!$S$9:$S$40,MATCH('10-Yr CF'!D32,'P&Ls Summary'!$D$9:$D$40,0)) -> #DIV/0! | F32: =E32*(1+$Q32) -> #DIV/0! | G32: =F32*(1+$Q32) -> #DIV/0! | H32: =G32*(1+$Q32) -> #DIV/0! | I32: =H32*(1+$Q32) -> #DIV/0! | J32: =I32*(1+$Q32) -> #DIV/0! | K32: =J32*(1+$Q32) -> #DIV/0! | L32: =K32*(1+$Q32) -> #DIV/0! | M32: =L32*(1+$Q32) -> #DIV/0! | N32: =M32*(1+$Q32) -> #DIV/0! | Q32: =$Q$14 -> 0.025
D33: General & Administrative | E33: =INDEX('P&Ls Summary'!$S$9:$S$40,MATCH('10-Yr CF'!D33,'P&Ls Summary'!$D$9:$D$40,0)) -> #DIV/0! | F33: =E33*(1+$Q33) -> #DIV/0! | G33: =F33*(1+$Q33) -> #DIV/0! | H33: =G33*(1+$Q33) -> #DIV/0! | I33: =H33*(1+$Q33) -> #DIV/0! | J33: =I33*(1+$Q33) -> #DIV/0! | K33: =J33*(1+$Q33) -> #DIV/0! | L33: =K33*(1+$Q33) -> #DIV/0! | M33: =L33*(1+$Q33) -> #DIV/0! | N33: =M33*(1+$Q33) -> #DIV/0! | Q33: =$Q$14 -> 0.025
D34: Advertising & Marketing | E34: =INDEX('P&Ls Summary'!$S$9:$S$40,MATCH('10-Yr CF'!D34,'P&Ls Summary'!$D$9:$D$40,0)) -> #DIV/0! | F34: =E34*(1+$Q34) -> #DIV/0! | G34: =F34*(1+$Q34) -> #DIV/0! | H34: =G34*(1+$Q34) -> #DIV/0! | I34: =H34*(1+$Q34) -> #DIV/0! | J34: =I34*(1+$Q34) -> #DIV/0! | K34: =J34*(1+$Q34) -> #DIV/0! | L34: =K34*(1+$Q34) -> #DIV/0! | M34: =L34*(1+$Q34) -> #DIV/0! | N34: =M34*(1+$Q34) -> #DIV/0! | Q34: =$Q$14 -> 0.025
D35: Personnel | E35: =INDEX('P&Ls Summary'!$S$9:$S$40,MATCH('10-Yr CF'!D35,'P&Ls Summary'!$D$9:$D$40,0)) -> #DIV/0! | F35: =E35*(1+$Q35) -> #DIV/0! | G35: =F35*(1+$Q35) -> #DIV/0! | H35: =G35*(1+$Q35) -> #DIV/0! | I35: =H35*(1+$Q35) -> #DIV/0! | J35: =I35*(1+$Q35) -> #DIV/0! | K35: =J35*(1+$Q35) -> #DIV/0! | L35: =K35*(1+$Q35) -> #DIV/0! | M35: =L35*(1+$Q35) -> #DIV/0! | N35: =M35*(1+$Q35) -> #DIV/0! | Q35: =$Q$14 -> 0.025
D36: Management Fee | E36: =INDEX('P&Ls Summary'!$S$9:$S$40,MATCH('10-Yr CF'!D36,'P&Ls Summary'!$D$9:$D$40,0)) -> #DIV/0! | F36: =$Q$36*F22 -> #DIV/0! | G36: =$Q$36*G22 -> #DIV/0! | H36: =$Q$36*H22 -> #DIV/0! | I36: =$Q$36*I22 -> #DIV/0! | J36: =$Q$36*J22 -> #DIV/0! | K36: =$Q$36*K22 -> #DIV/0! | L36: =$Q$36*L22 -> #DIV/0! | M36: =$Q$36*M22 -> #DIV/0! | N36: =$Q$36*N22 -> #DIV/0! | Q36: ='P&Ls Summary'!AC37 -> 0.03 | R36: of EGI
D37: Replacement Reserves | E37: =INDEX('P&Ls Summary'!$S$9:$S$40,MATCH('10-Yr CF'!D37,'P&Ls Summary'!$D$9:$D$40,0)) -> #DIV/0! | F37: =E37*(1+$Q37) -> #DIV/0! | G37: =F37*(1+$Q37) -> #DIV/0! | H37: =G37*(1+$Q37) -> #DIV/0! | I37: =H37*(1+$Q37) -> #DIV/0! | J37: =I37*(1+$Q37) -> #DIV/0! | K37: =J37*(1+$Q37) -> #DIV/0! | L37: =K37*(1+$Q37) -> #DIV/0! | M37: =L37*(1+$Q37) -> #DIV/0! | N37: =M37*(1+$Q37) -> #DIV/0! | Q37: 0
D38: Total Operating Expenses | E38: =SUM(E25:E37) -> #DIV/0! | F38: =SUM(F25:F37) -> #DIV/0! | G38: =SUM(G25:G37) -> #DIV/0! | H38: =SUM(H25:H37) -> #DIV/0! | I38: =SUM(I25:I37) -> #DIV/0! | J38: =SUM(J25:J37) -> #DIV/0! | K38: =SUM(K25:K37) -> #DIV/0! | L38: =SUM(L25:L37) -> #DIV/0! | ... N38: =SUM(N25:N37) -> #DIV/0!
D39: Net Operating Income | E39: =E22-E38 -> #DIV/0! | F39: =F22-F38 -> #DIV/0! | G39: =G22-G38 -> #DIV/0! | H39: =H22-H38 -> #DIV/0! | I39: =I22-I38 -> #DIV/0! | J39: =J22-J38 -> #DIV/0! | K39: =K22-K38 -> #DIV/0! | L39: =L22-L38 -> #DIV/0! | ... N39: =N22-N38 -> #DIV/0!
D43: Market Rent | F43: =F8/E8-1 -> #DIV/0! | G43: =G8/F8-1 -> #DIV/0! | H43: =H8/G8-1 -> #DIV/0! | I43: =I8/H8-1 -> #DIV/0! | J43: =J8/I8-1 -> #DIV/0! | K43: =K8/J8-1 -> #DIV/0! | L43: =L8/K8-1 -> #DIV/0! | M43: =M8/L8-1 -> #DIV/0! | N43: =N8/M8-1 -> #DIV/0!
D44: LTL | E44: =IF(E5>$T$9,"",E9/$E$9) -> #DIV/0! | F44: =IF(F5>$T$9,"",F9/$E$9) -> #DIV/0! | G44: =IF(G5>$T$9,"",G9/$E$9) -> #DIV/0! | H44: =IF(H5>$T$9,"",H9/$E$9) -> #DIV/0! | I44: =IF(I5>$T$9,"",I9/$E$9) | J44: =IF(J5>$T$9,"",J9/$E$9) | K44: =IF(K5>$T$9,"",K9/$E$9) | L44: =IF(L5>$T$9,"",L9/$E$9) | ... N44: =IF(N5>$T$9,"",N9/$E$9)
D45: Gross Rental Income | F45: =F10/E10-1 -> #DIV/0! | G45: =G10/F10-1 -> #DIV/0! | H45: =H10/G10-1 -> #DIV/0! | I45: =I10/H10-1 -> #DIV/0! | J45: =J10/I10-1 -> #DIV/0! | K45: =K10/J10-1 -> #DIV/0! | L45: =L10/K10-1 -> #DIV/0! | M45: =M10/L10-1 -> #DIV/0! | N45: =N10/M10-1 -> #DIV/0!
D46: EGI | F46: =F22/E22-1 -> #DIV/0! | G46: =G22/F22-1 -> #DIV/0! | H46: =H22/G22-1 -> #DIV/0! | I46: =I22/H22-1 -> #DIV/0! | J46: =J22/I22-1 -> #DIV/0! | K46: =K22/J22-1 -> #DIV/0! | L46: =L22/K22-1 -> #DIV/0! | M46: =M22/L22-1 -> #DIV/0! | N46: =N22/M22-1 -> #DIV/0!
D47: OpEx | F47: =F38/E38-1 -> #DIV/0! | G47: =G38/F38-1 -> #DIV/0! | H47: =H38/G38-1 -> #DIV/0! | I47: =I38/H38-1 -> #DIV/0! | J47: =J38/I38-1 -> #DIV/0! | K47: =K38/J38-1 -> #DIV/0! | L47: =L38/K38-1 -> #DIV/0! | M47: =M38/L38-1 -> #DIV/0! | N47: =N38/M38-1 -> #DIV/0!
D48: NOI | F48: =F39/E39-1 -> #DIV/0! | G48: =G39/F39-1 -> #DIV/0! | H48: =H39/G39-1 -> #DIV/0! | I48: =I39/H39-1 -> #DIV/0! | J48: =J39/I39-1 -> #DIV/0! | K48: =K39/J39-1 -> #DIV/0! | L48: =L39/K39-1 -> #DIV/0! | M48: =M39/L39-1 -> #DIV/0! | N48: =N39/M39-1 -> #DIV/0!
D103: Data Validation
D104: =D8 -> Market Rent
D105: =D9 -> Loss to Lease
D106: =D11 -> Less Vacancy
D107: =D12 -> Less: Concessions
D108: =D13 -> Less: Bad Debt/Collection
D109: =D14 -> Pet Income
D110: =D15 -> Laundry Income
D111: =D16 -> Parking Income
D112: =D18 -> Utility Reimbursement
D113: =D19 -> Other Income
D114: =D20 -> Commercial Income
D115: =D21 -> Less Commercial Vacancy
D117: =D35 -> Personnel
D118: =D25 -> Property Taxes
D119: =D26 -> Insurance
D120: =D27 -> Utilities
D121: =D28 -> Utilities - Sewer & Water
D122: =D29 -> Utilities - Gas
D123: =D30 -> Utilities - Electric
D124: =D31 -> Repairs & Maintenance
D125: =D32 -> Contract Services
D126: =D33 -> General & Administrative
D127: =D34 -> Advertising & Marketing
D128: =D36 -> Management Fee
D129: =D37 -> Replacement Reserves

Sheet P&Ls Detailed
C3: DETAILED INCOME STATEMENT | AB3: ='Exec Summ'!F6 -> Hudson View Park | AD3: ='P&Ls Summary'!AA3 -> 0 | AE3: =IF(COUNTIF(AF155:AR157,"False")=0,"OK","ERROR") -> OK
D5: Property | E5: General CoA | F5: Exc. In IP NOI? | G5: Seller's CoA | H5: 45443 | I5: =EOMONTH(H5,1) -> 45473 | J5: =EOMONTH(I5,1) -> 45504 | K5: =EOMONTH(J5,1) -> 45535 | L5: =EOMONTH(K5,1) -> 45565 | M5: =EOMONTH(L5,1) -> 45596 | N5: =EOMONTH(M5,1) -> 45626 | O5: =EOMONTH(N5,1) -> 45657 | P5: =EOMONTH(O5,1) -> 45688 | ... S5: =EOMONTH(R5,1) -> 45777 | T5: YE 2022 | U5: YE 2023 | V5: YE 2024 | W5: ="T-12"&CHAR(10)&TEXT($H$5,"(mm.yy"&"-")&TEXT($S$5,"mm.yy)") -> T-12 (05.24-04.25) | X5: ="T-9 Ann."&CHAR(10)&TEXT($K$5,"(mm.yy"&"-")&TEXT($S$5,"mm.yy)") -> T-9 Ann. (08.24-04.25) | Y5: ="T-6 Ann."&CHAR(10)&TEXT($N$5,"(mm.yy"&"-")&TEXT($S$5,"mm.yy)") -> T-6 Ann. (11.24-04.25) | Z5: ="T-3 Ann."&CHAR(10)&TEXT($Q$5,"(mm.yy"&"-")&TEXT($S$5,"mm.yy)") -> T-3 Ann. (02.25-04.25) | AA5: ="T-1 Ann."&CHAR(10)&TEXT($S$5,"(mm.yy"&"-")&TEXT($S$5,"mm.yy)") -> T-1 Ann. (04.25-04.25)
D7: =$AB$3 -> Hudson View Park | G7: Operating Income & Expense
D8: =$AB$3 -> Hudson View Park | G8: Income
D9: =$AB$3 -> Hudson View Park | G9: EFFECTIVE RENTAL REVENUE
D10: =$AB$3 -> Hudson View Park | E10: Market Rent | G10: MARKET RENT | H10: =SUMIFS('HVP T12'!C:C,'HVP T12'!$B:$B,'P&Ls Detailed'!$G10) -> 1010104.9 | I10: =SUMIFS('HVP T12'!D:D,'HVP T12'!$B:$B,'P&Ls Detailed'!$G10) -> 1022834 | J10: =SUMIFS('HVP T12'!E:E,'HVP T12'!$B:$B,'P&Ls Detailed'!$G10) -> 1023194.7 | K10: =SUMIFS('HVP T12'!F:F,'HVP T12'!$B:$B,'P&Ls Detailed'!$G10) -> 1024622.6 | L10: =SUMIFS('HVP T12'!G:G,'HVP T12'!$B:$B,'P&Ls Detailed'!$G10) -> 1028082.5 | M10: =SUMIFS('HVP T12'!H:H,'HVP T12'!$B:$B,'P&Ls Detailed'!$G10) -> 1029616 | N10: =SUMIFS('HVP T12'!I:I,'HVP T12'!$B:$B,'P&Ls Detailed'!$G10) -> 1030093.7 | O10: =SUMIFS('HVP T12'!J:J,'HVP T12'!$B:$B,'P&Ls Detailed'!$G10) -> 1030688.4 | P10: =SUMIFS('HVP T12'!K:K,'HVP T12'!$B:$B,'P&Ls Detailed'!$G10) -> 1031356.3 | Q10: =SUMIFS('HVP T12'!L:L,'HVP T12'!$B:$B,'P&Ls Detailed'!$G10) -> 1031931.2 | R10: =SUMIFS('HVP T12'!M:M,'HVP T12'!$B:$B,'P&Ls Detailed'!$G10) -> 1033899.6 | S10: =SUMIFS('HVP T12'!N:N,'HVP T12'!$B:$B,'P&Ls Detailed'!$G10) -> 1035339.7 | W10: =SUM(H10:S10) -> 12331763 | X10: =SUM(K10:S10)/9*12 -> 12367506 | Y10: =SUM(N10:S10)/6*12 -> 12386618 | Z10: =SUM(Q10:S10)/3*12 -> 12404682 | AA10: =S10*12 -> 12424076
D11: =$AB$3 -> Hudson View Park | E11: Less: Concessions | F11: Exclude | G11: RENT CONCESSIONS | H11: =SUMIFS('HVP T12'!C:C,'HVP T12'!$B:$B,'P&Ls Detailed'!$G11) -> -5125 | I11: =SUMIFS('HVP T12'!D:D,'HVP T12'!$B:$B,'P&Ls Detailed'!$G11) -> -5413.37 | J11: =SUMIFS('HVP T12'!E:E,'HVP T12'!$B:$B,'P&Ls Detailed'!$G11) -> -5621.74 | K11: =SUMIFS('HVP T12'!F:F,'HVP T12'!$B:$B,'P&Ls Detailed'!$G11) -> -5621.74 | L11: =SUMIFS('HVP T12'!G:G,'HVP T12'!$B:$B,'P&Ls Detailed'!$G11) -> -5449.62 | M11: =SUMIFS('HVP T12'!H:H,'HVP T12'!$B:$B,'P&Ls Detailed'!$G11) -> -5449.62 | N11: =SUMIFS('HVP T12'!I:I,'HVP T12'!$B:$B,'P&Ls Detailed'!$G11) -> -5449.62 | O11: =SUMIFS('HVP T12'!J:J,'HVP T12'!$B:$B,'P&Ls Detailed'!$G11) -> -5449.62 | P11: =SUMIFS('HVP T12'!K:K,'HVP T12'!$B:$B,'P&Ls Detailed'!$G11) -> -5829.62 | Q11: =SUMIFS('HVP T12'!L:L,'HVP T12'!$B:$B,'P&Ls Detailed'!$G11) -> -5992.12 | R11: =SUMIFS('HVP T12'!M:M,'HVP T12'!$B:$B,'P&Ls Detailed'!$G11) -> -5992.12 | S11: =SUMIFS('HVP T12'!N:N,'HVP T12'!$B:$B,'P&Ls Detailed'!$G11) -> -5992.12 | W11: =SUM(H11:S11) -> -67386.31 | X11: =SUM(K11:S11)/9*12 -> -68301.6 | Y11: =SUM(N11:S11)/6*12 -> -69410.44 | Z11: =SUM(Q11:S11)/3*12 -> -71905.44 | AA11: =S11*12 -> -71905.44
D12: =$AB$3 -> Hudson View Park | E12: Less Vacancy | F12: Exclude | G12: VACANCIES | H12: =SUMIFS('HVP T12'!C:C,'HVP T12'!$B:$B,'P&Ls Detailed'!$G12) -> -11419.04 | I12: =SUMIFS('HVP T12'!D:D,'HVP T12'!$B:$B,'P&Ls Detailed'!$G12) -> -21882.15 | J12: =SUMIFS('HVP T12'!E:E,'HVP T12'!$B:$B,'P&Ls Detailed'!$G12) -> -24323.7 | K12: =SUMIFS('HVP T12'!F:F,'HVP T12'!$B:$B,'P&Ls Detailed'!$G12) -> -17876.46 | L12: =SUMIFS('HVP T12'!G:G,'HVP T12'!$B:$B,'P&Ls Detailed'!$G12) -> -11790.66 | M12: =SUMIFS('HVP T12'!H:H,'HVP T12'!$B:$B,'P&Ls Detailed'!$G12) -> -16782.89 | N12: =SUMIFS('HVP T12'!I:I,'HVP T12'!$B:$B,'P&Ls Detailed'!$G12) -> -17383.83 | O12: =SUMIFS('HVP T12'!J:J,'HVP T12'!$B:$B,'P&Ls Detailed'!$G12) -> -21465.19 | P12: =SUMIFS('HVP T12'!K:K,'HVP T12'!$B:$B,'P&Ls Detailed'!$G12) -> -18846.93 | Q12: =SUMIFS('HVP T12'!L:L,'HVP T12'!$B:$B,'P&Ls Detailed'!$G12) -> -14556.77 | R12: =SUMIFS('HVP T12'!M:M,'HVP T12'!$B:$B,'P&Ls Detailed'!$G12) -> -9042.9 | S12: =SUMIFS('HVP T12'!N:N,'HVP T12'!$B:$B,'P&Ls Detailed'!$G12) -> -8070.33 | W12: =SUM(H12:S12) -> -193440.85 | X12: =SUM(K12:S12)/9*12 -> -181087.95 | Y12: =SUM(N12:S12)/6*12 -> -178731.9 | Z12: =SUM(Q12:S12)/3*12 -> -126680 | AA12: =S12*12 -> -96843.96
D13: =$AB$3 -> Hudson View Park | E13: Market Rent | G13: COMPANY APT OFFICE | H13: =SUMIFS('HVP T12'!C:C,'HVP T12'!$B:$B,'P&Ls Detailed'!$G13) -> -4516.62 | I13: =SUMIFS('HVP T12'!D:D,'HVP T12'!$B:$B,'P&Ls Detailed'!$G13) -> -4550 | J13: =SUMIFS('HVP T12'!E:E,'HVP T12'!$B:$B,'P&Ls Detailed'!$G13) -> -4550 | K13: =SUMIFS('HVP T12'!F:F,'HVP T12'!$B:$B,'P&Ls Detailed'!$G13) -> -4550 | L13: =SUMIFS('HVP T12'!G:G,'HVP T12'!$B:$B,'P&Ls Detailed'!$G13) -> -4550 | M13: =SUMIFS('HVP T12'!H:H,'HVP T12'!$B:$B,'P&Ls Detailed'!$G13) -> -4550 | N13: =SUMIFS('HVP T12'!I:I,'HVP T12'!$B:$B,'P&Ls Detailed'!$G13) -> -4550 | O13: =SUMIFS('HVP T12'!J:J,'HVP T12'!$B:$B,'P&Ls Detailed'!$G13) -> -4550 | P13: =SUMIFS('HVP T12'!K:K,'HVP T12'!$B:$B,'P&Ls Detailed'!$G13) -> -4550 | Q13: =SUMIFS('HVP T12'!L:L,'HVP T12'!$B:$B,'P&Ls Detailed'!$G13) -> -4550 | R13: =SUMIFS('HVP T12'!M:M,'HVP T12'!$B:$B,'P&Ls Detailed'!$G13) -> -4550 | S13: =SUMIFS('HVP T12'!N:N,'HVP T12'!$B:$B,'P&Ls Detailed'!$G13) -> -4550 | W13: =SUM(H13:S13) -> -54566.62 | X13: =SUM(K13:S13)/9*12 -> -54600 | Y13: =SUM(N13:S13)/6*12 -> -54600 | Z13: =SUM(Q13:S13)/3*12 -> -54600 | AA13: =S13*12 -> -54600
D14: =$AB$3 -> Hudson View Park | E14: Loss to Lease | G14: LOSS/GAIN TO MARKET | H14: =SUMIFS('HVP T12'!C:C,'HVP T12'!$B:$B,'P&Ls Detailed'!$G14) -> -101519.25 | I14: =SUMIFS('HVP T12'!D:D,'HVP T12'!$B:$B,'P&Ls Detailed'!$G14) -> -103859 | J14: =SUMIFS('HVP T12'!E:E,'HVP T12'!$B:$B,'P&Ls Detailed'!$G14) -> -94851.64 | K14: =SUMIFS('HVP T12'!F:F,'HVP T12'!$B:$B,'P&Ls Detailed'!$G14) -> -87548.35 | L14: =SUMIFS('HVP T12'!G:G,'HVP T12'!$B:$B,'P&Ls Detailed'!$G14) -> -79842.19 | M14: =SUMIFS('HVP T12'!H:H,'HVP T12'!$B:$B,'P&Ls Detailed'!$G14) -> -71108.39 | N14: =SUMIFS('HVP T12'!I:I,'HVP T12'!$B:$B,'P&Ls Detailed'!$G14) -> -59557 | O14: =SUMIFS('HVP T12'!J:J,'HVP T12'!$B:$B,'P&Ls Detailed'!$G14) -> -54865.79 | P14: =SUMIFS('HVP T12'!K:K,'HVP T12'!$B:$B,'P&Ls Detailed'!$G14) -> -46670 | Q14: =SUMIFS('HVP T12'!L:L,'HVP T12'!$B:$B,'P&Ls Detailed'!$G14) -> -40747.14 | R14: =SUMIFS('HVP T12'!M:M,'HVP T12'!$B:$B,'P&Ls Detailed'!$G14) -> -35217.98 | S14: =SUMIFS('HVP T12'!N:N,'HVP T12'!$B:$B,'P&Ls Detailed'!$G14) -> -28667.66 | W14: =SUM(H14:S14) -> -804454.39 | X14: =SUM(K14:S14)/9*12 -> -672299.33 | Y14: =SUM(N14:S14)/6*12 -> -531451.14 | Z14: =SUM(Q14:S14)/3*12 -> -418531.12 | AA14: =S14*12 -> -344011.92
D15: =$AB$3 -> Hudson View Park | G15: Total EFFECTIVE RENTAL REVENUE | H15: =SUM(H10:H14) -> 887525 | I15: =SUM(I10:I14) -> 887129.48 | J15: =SUM(J10:J14) -> 893847.61 | K15: =SUM(K10:K14) -> 909026 | L15: =SUM(L10:L14) -> 926450.04 | M15: =SUM(M10:M14) -> 931725.07 | N15: =SUM(N10:N14) -> 943153.22 | O15: =SUM(O10:O14) -> 944357.78 | ... S15: =SUM(S10:S14) -> 988059.55 | W15: =SUM(W10:W14) -> 11211915 | X15: =SUM(X10:X14) -> 11391218 | Y15: =SUM(Y10:Y14) -> 11552424 | Z15: =SUM(Z10:Z14) -> 11732965 | AA15: =SUM(AA10:AA14) -> 11856715
D16: =$AB$3 -> Hudson View Park | G16: OTHER REVENUE
D17: =$AB$3 -> Hudson View Park | E17: Less: Bad Debt/Collection | F17: Exclude | G17: FMR TENANT UNCOLLECTABLE BAL | H17: =SUMIFS('HVP T12'!C:C,'HVP T12'!$B:$B,'P&Ls Detailed'!$G17) -> 225.82 | I17: =SUMIFS('HVP T12'!D:D,'HVP T12'!$B:$B,'P&Ls Detailed'!$G17) -> 0 | J17: =SUMIFS('HVP T12'!E:E,'HVP T12'!$B:$B,'P&Ls Detailed'!$G17) -> 0 | K17: =SUMIFS('HVP T12'!F:F,'HVP T12'!$B:$B,'P&Ls Detailed'!$G17) -> 0 | L17: =SUMIFS('HVP T12'!G:G,'HVP T12'!$B:$B,'P&Ls Detailed'!$G17) -> 0 | M17: =SUMIFS('HVP T12'!H:H,'HVP T12'!$B:$B,'P&Ls Detailed'!$G17) -> 0 | N17: =SUMIFS('HVP T12'!I:I,'HVP T12'!$B:$B,'P&Ls Detailed'!$G17) -> 0 | O17: =SUMIFS('HVP T12'!J:J,'HVP T12'!$B:$B,'P&Ls Detailed'!$G17) -> -951.94 | P17: =SUMIFS('HVP T12'!K:K,'HVP T12'!$B:$B,'P&Ls Detailed'!$G17) -> 0 | Q17: =SUMIFS('HVP T12'!L:L,'HVP T12'!$B:$B,'P&Ls Detailed'!$G17) -> 0 | R17: =SUMIFS('HVP T12'!M:M,'HVP T12'!$B:$B,'P&Ls Detailed'!$G17) -> 445.23 | S17: =SUMIFS('HVP T12'!N:N,'HVP T12'!$B:$B,'P&Ls Detailed'!$G17) -> 0 | W17: =SUM(H17:S17) -> -280.89 | X17: =SUM(K17:S17)/9*12 -> -675.61333 | Y17: =SUM(N17:S17)/6*12 -> -1013.42 | Z17: =SUM(Q17:S17)/3*12 -> 1780.92 | AA17: =S17*12 -> 0
D18: =$AB$3 -> Hudson View Park | E18: Other Income | G18: RECREATION FEE | H18: =SUMIFS('HVP T12'!C:C,'HVP T12'!$B:$B,'P&Ls Detailed'!$G18) -> 37772.24 | I18: =SUMIFS('HVP T12'!D:D,'HVP T12'!$B:$B,'P&Ls Detailed'!$G18) -> 36305.84 | J18: =SUMIFS('HVP T12'!E:E,'HVP T12'!$B:$B,'P&Ls Detailed'!$G18) -> 32775.48 | K18: =SUMIFS('HVP T12'!F:F,'HVP T12'!$B:$B,'P&Ls Detailed'!$G18) -> 29421.6 | L18: =SUMIFS('HVP T12'!G:G,'HVP T12'!$B:$B,'P&Ls Detailed'!$G18) -> 25511.67 | M18: =SUMIFS('HVP T12'!H:H,'HVP T12'!$B:$B,'P&Ls Detailed'!$G18) -> 21895.96 | N18: =SUMIFS('HVP T12'!I:I,'HVP T12'!$B:$B,'P&Ls Detailed'!$G18) -> 18430 | O18: =SUMIFS('HVP T12'!J:J,'HVP T12'!$B:$B,'P&Ls Detailed'!$G18) -> 15673.56 | P18: =SUMIFS('HVP T12'!K:K,'HVP T12'!$B:$B,'P&Ls Detailed'!$G18) -> 12936.78 | Q18: =SUMIFS('HVP T12'!L:L,'HVP T12'!$B:$B,'P&Ls Detailed'!$G18) -> 10537.15 | R18: =SUMIFS('HVP T12'!M:M,'HVP T12'!$B:$B,'P&Ls Detailed'!$G18) -> 7747.1 | S18: =SUMIFS('HVP T12'!N:N,'HVP T12'!$B:$B,'P&Ls Detailed'!$G18) -> 4608 | W18: =SUM(H18:S18) -> 253615.38 | X18: =SUM(K18:S18)/9*12 -> 195682.43 | Y18: =SUM(N18:S18)/6*12 -> 139865.18 | Z18: =SUM(Q18:S18)/3*12 -> 91569 | AA18: =S18*12 -> 55296
D19: =$AB$3 -> Hudson View Park | E19: Other Income | G19: APPLICATION FEE INCOME | H19: =SUMIFS('HVP T12'!C:C,'HVP T12'!$B:$B,'P&Ls Detailed'!$G19) -> 420 | I19: =SUMIFS('HVP T12'!D:D,'HVP T12'!$B:$B,'P&Ls Detailed'!$G19) -> 315 | J19: =SUMIFS('HVP T12'!E:E,'HVP T12'!$B:$B,'P&Ls Detailed'!$G19) -> 225 | K19: =SUMIFS('HVP T12'!F:F,'HVP T12'!$B:$B,'P&Ls Detailed'!$G19) -> 420 | L19: =SUMIFS('HVP T12'!G:G,'HVP T12'!$B:$B,'P&Ls Detailed'!$G19) -> 320 | M19: =SUMIFS('HVP T12'!H:H,'HVP T12'!$B:$B,'P&Ls Detailed'!$G19) -> 195 | N19: =SUMIFS('HVP T12'!I:I,'HVP T12'!$B:$B,'P&Ls Detailed'!$G19) -> 405 | O19: =SUMIFS('HVP T12'!J:J,'HVP T12'!$B:$B,'P&Ls Detailed'!$G19) -> 225 | P19: =SUMIFS('HVP T12'!K:K,'HVP T12'!$B:$B,'P&Ls Detailed'!$G19) -> 180 | Q19: =SUMIFS('HVP T12'!L:L,'HVP T12'!$B:$B,'P&Ls Detailed'!$G19) -> 270 | R19: =SUMIFS('HVP T12'!M:M,'HVP T12'!$B:$B,'P&Ls Detailed'!$G19) -> 390 | S19: =SUMIFS('HVP T12'!N:N,'HVP T12'!$B:$B,'P&Ls Detailed'!$G19) -> 195 | W19: =SUM(H19:S19) -> 3560 | X19: =SUM(K19:S19)/9*12 -> 3466.6667 | Y19: =SUM(N19:S19)/6*12 -> 3330 | Z19: =SUM(Q19:S19)/3*12 -> 3420 | AA19: =S19*12 -> 2340
D20: =$AB$3 -> Hudson View Park | E20: Other Income | G20: NSF FEE INCOME | H20: =SUMIFS('HVP T12'!C:C,'HVP T12'!$B:$B,'P&Ls Detailed'!$G20) -> 0 | I20: =SUMIFS('HVP T12'!D:D,'HVP T12'!$B:$B,'P&Ls Detailed'!$G20) -> 210 | J20: =SUMIFS('HVP T12'!E:E,'HVP T12'!$B:$B,'P&Ls Detailed'!$G20) -> 140 | K20: =SUMIFS('HVP T12'!F:F,'HVP T12'!$B:$B,'P&Ls Detailed'!$G20) -> 70 | L20: =SUMIFS('HVP T12'!G:G,'HVP T12'!$B:$B,'P&Ls Detailed'!$G20) -> 245 | M20: =SUMIFS('HVP T12'!H:H,'HVP T12'!$B:$B,'P&Ls Detailed'!$G20) -> 35 | N20: =SUMIFS('HVP T12'!I:I,'HVP T12'!$B:$B,'P&Ls Detailed'!$G20) -> 35 | O20: =SUMIFS('HVP T12'!J:J,'HVP T12'!$B:$B,'P&Ls Detailed'!$G20) -> 35 | P20: =SUMIFS('HVP T12'!K:K,'HVP T12'!$B:$B,'P&Ls Detailed'!$G20) -> 210 | Q20: =SUMIFS('HVP T12'!L:L,'HVP T12'!$B:$B,'P&Ls Detailed'!$G20) -> 105 | R20: =SUMIFS('HVP T12'!M:M,'HVP T12'!$B:$B,'P&Ls Detailed'!$G20) -> 175 | S20: =SUMIFS('HVP T12'!N:N,'HVP T12'!$B:$B,'P&Ls Detailed'!$G20) -> 70 | W20: =SUM(H20:S20) -> 1330 | X20: =SUM(K20:S20)/9*12 -> 1306.6667 | Y20: =SUM(N20:S20)/6*12 -> 1260 | Z20: =SUM(Q20:S20)/3*12 -> 1400 | AA20: =S20*12 -> 840
D21: =$AB$3 -> Hudson View Park | E21: Other Income | G21: LATE FEE | H21: =SUMIFS('HVP T12'!C:C,'HVP T12'!$B:$B,'P&Ls Detailed'!$G21) -> 900 | I21: =SUMIFS('HVP T12'!D:D,'HVP T12'!$B:$B,'P&Ls Detailed'!$G21) -> 950 | J21: =SUMIFS('HVP T12'!E:E,'HVP T12'!$B:$B,'P&Ls Detailed'!$G21) -> 750 | K21: =SUMIFS('HVP T12'!F:F,'HVP T12'!$B:$B,'P&Ls Detailed'!$G21) -> 1200 | L21: =SUMIFS('HVP T12'!G:G,'HVP T12'!$B:$B,'P&Ls Detailed'!$G21) -> 1250 | M21: =SUMIFS('HVP T12'!H:H,'HVP T12'!$B:$B,'P&Ls Detailed'!$G21) -> 1300 | N21: =SUMIFS('HVP T12'!I:I,'HVP T12'!$B:$B,'P&Ls Detailed'!$G21) -> 1450 | O21: =SUMIFS('HVP T12'!J:J,'HVP T12'!$B:$B,'P&Ls Detailed'!$G21) -> 950 | P21: =SUMIFS('HVP T12'!K:K,'HVP T12'!$B:$B,'P&Ls Detailed'!$G21) -> 1350 | Q21: =SUMIFS('HVP T12'!L:L,'HVP T12'!$B:$B,'P&Ls Detailed'!$G21) -> 700 | R21: =SUMIFS('HVP T12'!M:M,'HVP T12'!$B:$B,'P&Ls Detailed'!$G21) -> 1100 | S21: =SUMIFS('HVP T12'!N:N,'HVP T12'!$B:$B,'P&Ls Detailed'!$G21) -> 1150 | W21: =SUM(H21:S21) -> 13050 | X21: =SUM(K21:S21)/9*12 -> 13933.333 | Y21: =SUM(N21:S21)/6*12 -> 13400 | Z21: =SUM(Q21:S21)/3*12 -> 11800 | AA21: =S21*12 -> 13800
D22: =$AB$3 -> Hudson View Park | E22: Pet Income | G22: PET FEE DOG | H22: =SUMIFS('HVP T12'!C:C,'HVP T12'!$B:$B,'P&Ls Detailed'!$G22) -> 4393.55 | I22: =SUMIFS('HVP T12'!D:D,'HVP T12'!$B:$B,'P&Ls Detailed'!$G22) -> 3836.68 | J22: =SUMIFS('HVP T12'!E:E,'HVP T12'!$B:$B,'P&Ls Detailed'!$G22) -> 3850 | K22: =SUMIFS('HVP T12'!F:F,'HVP T12'!$B:$B,'P&Ls Detailed'!$G22) -> 4393.55 | L22: =SUMIFS('HVP T12'!G:G,'HVP T12'!$B:$B,'P&Ls Detailed'!$G22) -> 3841.67 | M22: =SUMIFS('HVP T12'!H:H,'HVP T12'!$B:$B,'P&Ls Detailed'!$G22) -> 4890.32 | N22: =SUMIFS('HVP T12'!I:I,'HVP T12'!$B:$B,'P&Ls Detailed'!$G22) -> 3865 | O22: =SUMIFS('HVP T12'!J:J,'HVP T12'!$B:$B,'P&Ls Detailed'!$G22) -> 3581.45 | P22: =SUMIFS('HVP T12'!K:K,'HVP T12'!$B:$B,'P&Ls Detailed'!$G22) -> 3679.03 | Q22: =SUMIFS('HVP T12'!L:L,'HVP T12'!$B:$B,'P&Ls Detailed'!$G22) -> 3250 | R22: =SUMIFS('HVP T12'!M:M,'HVP T12'!$B:$B,'P&Ls Detailed'!$G22) -> 3791.93 | S22: =SUMIFS('HVP T12'!N:N,'HVP T12'!$B:$B,'P&Ls Detailed'!$G22) -> 3250 | W22: =SUM(H22:S22) -> 46623.18 | X22: =SUM(K22:S22)/9*12 -> 46057.267 | Y22: =SUM(N22:S22)/6*12 -> 42834.82 | Z22: =SUM(Q22:S22)/3*12 -> 41167.72 | AA22: =S22*12 -> 39000
D23: =$AB$3 -> Hudson View Park | E23: Pet Income | G23: PET FEE CAT | H23: =SUMIFS('HVP T12'!C:C,'HVP T12'!$B:$B,'P&Ls Detailed'!$G23) -> 3715.32 | I23: =SUMIFS('HVP T12'!D:D,'HVP T12'!$B:$B,'P&Ls Detailed'!$G23) -> 3108.32 | J23: =SUMIFS('HVP T12'!E:E,'HVP T12'!$B:$B,'P&Ls Detailed'!$G23) -> 3802.42 | K23: =SUMIFS('HVP T12'!F:F,'HVP T12'!$B:$B,'P&Ls Detailed'!$G23) -> 3571.77 | L23: =SUMIFS('HVP T12'!G:G,'HVP T12'!$B:$B,'P&Ls Detailed'!$G23) -> 3166.66 | M23: =SUMIFS('HVP T12'!H:H,'HVP T12'!$B:$B,'P&Ls Detailed'!$G23) -> 3731.44 | N23: =SUMIFS('HVP T12'!I:I,'HVP T12'!$B:$B,'P&Ls Detailed'!$G23) -> 3515 | O23: =SUMIFS('HVP T12'!J:J,'HVP T12'!$B:$B,'P&Ls Detailed'!$G23) -> 3735.48 | P23: =SUMIFS('HVP T12'!K:K,'HVP T12'!$B:$B,'P&Ls Detailed'!$G23) -> 2895.16 | Q23: =SUMIFS('HVP T12'!L:L,'HVP T12'!$B:$B,'P&Ls Detailed'!$G23) -> 3312.5 | R23: =SUMIFS('HVP T12'!M:M,'HVP T12'!$B:$B,'P&Ls Detailed'!$G23) -> 3594.35 | S23: =SUMIFS('HVP T12'!N:N,'HVP T12'!$B:$B,'P&Ls Detailed'!$G23) -> 3092.5 | W23: =SUM(H23:S23) -> 41240.92 | X23: =SUM(K23:S23)/9*12 -> 40819.813 | Y23: =SUM(N23:S23)/6*12 -> 40289.98 | Z23: =SUM(Q23:S23)/3*12 -> 39997.4 | AA23: =S23*12 -> 37110
D24: =$AB$3 -> Hudson View Park | E24: Other Income | G24: KEYS & LOCKS INCOME | H24: =SUMIFS('HVP T12'!C:C,'HVP T12'!$B:$B,'P&Ls Detailed'!$G24) -> 0 | I24: =SUMIFS('HVP T12'!D:D,'HVP T12'!$B:$B,'P&Ls Detailed'!$G24) -> 75 | J24: =SUMIFS('HVP T12'!E:E,'HVP T12'!$B:$B,'P&Ls Detailed'!$G24) -> 175 | K24: =SUMIFS('HVP T12'!F:F,'HVP T12'!$B:$B,'P&Ls Detailed'!$G24) -> 175 | L24: =SUMIFS('HVP T12'!G:G,'HVP T12'!$B:$B,'P&Ls Detailed'!$G24) -> 225 | M24: =SUMIFS('HVP T12'!H:H,'HVP T12'!$B:$B,'P&Ls Detailed'!$G24) -> 145 | N24: =SUMIFS('HVP T12'!I:I,'HVP T12'!$B:$B,'P&Ls Detailed'!$G24) -> 125 | O24: =SUMIFS('HVP T12'!J:J,'HVP T12'!$B:$B,'P&Ls Detailed'!$G24) -> 100 | P24: =SUMIFS('HVP T12'!K:K,'HVP T12'!$B:$B,'P&Ls Detailed'!$G24) -> 100 | Q24: =SUMIFS('HVP T12'!L:L,'HVP T12'!$B:$B,'P&Ls Detailed'!$G24) -> 100 | R24: =SUMIFS('HVP T12'!M:M,'HVP T12'!$B:$B,'P&Ls Detailed'!$G24) -> 225 | S24: =SUMIFS('HVP T12'!N:N,'HVP T12'!$B:$B,'P&Ls Detailed'!$G24) -> 25 | W24: =SUM(H24:S24) -> 1470 | X24: =SUM(K24:S24)/9*12 -> 1626.6667 | Y24: =SUM(N24:S24)/6*12 -> 1350 | Z24: =SUM(Q24:S24)/3*12 -> 1400 | AA24: =S24*12 -> 300
D25: =$AB$3 -> Hudson View Park | E25: Other Income | G25: APT BLINDS INCOME | H25: =SUMIFS('HVP T12'!C:C,'HVP T12'!$B:$B,'P&Ls Detailed'!$G25) -> 0 | I25: =SUMIFS('HVP T12'!D:D,'HVP T12'!$B:$B,'P&Ls Detailed'!$G25) -> 0 | J25: =SUMIFS('HVP T12'!E:E,'HVP T12'!$B:$B,'P&Ls Detailed'!$G25) -> 0 | K25: =SUMIFS('HVP T12'!F:F,'HVP T12'!$B:$B,'P&Ls Detailed'!$G25) -> 0 | L25: =SUMIFS('HVP T12'!G:G,'HVP T12'!$B:$B,'P&Ls Detailed'!$G25) -> 0 | M25: =SUMIFS('HVP T12'!H:H,'HVP T12'!$B:$B,'P&Ls Detailed'!$G25) -> 0 | N25: =SUMIFS('HVP T12'!I:I,'HVP T12'!$B:$B,'P&Ls Detailed'!$G25) -> 0 | O25: =SUMIFS('HVP T12'!J:J,'HVP T12'!$B:$B,'P&Ls Detailed'!$G25) -> 0 | P25: =SUMIFS('HVP T12'!K:K,'HVP T12'!$B:$B,'P&Ls Detailed'!$G25) -> 0 | Q25: =SUMIFS('HVP T12'!L:L,'HVP T12'!$B:$B,'P&Ls Detailed'!$G25) -> 0 | R25: =SUMIFS('HVP T12'!M:M,'HVP T12'!$B:$B,'P&Ls Detailed'!$G25) -> 0 | S25: =SUMIFS('HVP T12'!N:N,'HVP T12'!$B:$B,'P&Ls Detailed'!$G25) -> 349.38 | W25: =SUM(H25:S25) -> 349.38 | X25: =SUM(K25:S25)/9*12 -> 465.84 | Y25: =SUM(N25:S25)/6*12 -> 698.76 | Z25: =SUM(Q25:S25)/3*12 -> 1397.52 | AA25: =S25*12 -> 4192.56
D26: =$AB$3 -> Hudson View Park | E26: Laundry Income | G26: LAUNDRY INCOME | H26: =SUMIFS('HVP T12'!C:C,'HVP T12'!$B:$B,'P&Ls Detailed'!$G26) -> 11225.77 | I26: =SUMIFS('HVP T12'!D:D,'HVP T12'!$B:$B,'P&Ls Detailed'!$G26) -> 10073.67 | J26: =SUMIFS('HVP T12'!E:E,'HVP T12'!$B:$B,'P&Ls Detailed'!$G26) -> 10998.91 | K26: =SUMIFS('HVP T12'!F:F,'HVP T12'!$B:$B,'P&Ls Detailed'!$G26) -> 10386.98 | L26: =SUMIFS('HVP T12'!G:G,'HVP T12'!$B:$B,'P&Ls Detailed'!$G26) -> 11928.3 | M26: =SUMIFS('HVP T12'!H:H,'HVP T12'!$B:$B,'P&Ls Detailed'!$G26) -> 11559.3 | N26: =SUMIFS('HVP T12'!I:I,'HVP T12'!$B:$B,'P&Ls Detailed'!$G26) -> 10852.35 | O26: =SUMIFS('HVP T12'!J:J,'HVP T12'!$B:$B,'P&Ls Detailed'!$G26) -> 12165.53 | P26: =SUMIFS('HVP T12'!K:K,'HVP T12'!$B:$B,'P&Ls Detailed'!$G26) -> 9129.57 | Q26: =SUMIFS('HVP T12'!L:L,'HVP T12'!$B:$B,'P&Ls Detailed'!$G26) -> 11600.72 | R26: =SUMIFS('HVP T12'!M:M,'HVP T12'!$B:$B,'P&Ls Detailed'!$G26) -> 12444.38 | S26: =SUMIFS('HVP T12'!N:N,'HVP T12'!$B:$B,'P&Ls Detailed'!$G26) -> 11033.98 | W26: =SUM(H26:S26) -> 133399.46 | X26: =SUM(K26:S26)/9*12 -> 134801.48 | Y26: =SUM(N26:S26)/6*12 -> 134453.06 | Z26: =SUM(Q26:S26)/3*12 -> 140316.32 | AA26: =S26*12 -> 132407.76
D27: =$AB$3 -> Hudson View Park | E27: Other Income | G27: POOL FEE | H27: =SUMIFS('HVP T12'!C:C,'HVP T12'!$B:$B,'P&Ls Detailed'!$G27) -> 0 | I27: =SUMIFS('HVP T12'!D:D,'HVP T12'!$B:$B,'P&Ls Detailed'!$G27) -> 0 | J27: =SUMIFS('HVP T12'!E:E,'HVP T12'!$B:$B,'P&Ls Detailed'!$G27) -> 0 | K27: =SUMIFS('HVP T12'!F:F,'HVP T12'!$B:$B,'P&Ls Detailed'!$G27) -> 40 | L27: =SUMIFS('HVP T12'!G:G,'HVP T12'!$B:$B,'P&Ls Detailed'!$G27) -> 0 | M27: =SUMIFS('HVP T12'!H:H,'HVP T12'!$B:$B,'P&Ls Detailed'!$G27) -> 0 | N27: =SUMIFS('HVP T12'!I:I,'HVP T12'!$B:$B,'P&Ls Detailed'!$G27) -> 0 | O27: =SUMIFS('HVP T12'!J:J,'HVP T12'!$B:$B,'P&Ls Detailed'!$G27) -> 0 | P27: =SUMIFS('HVP T12'!K:K,'HVP T12'!$B:$B,'P&Ls Detailed'!$G27) -> 0 | Q27: =SUMIFS('HVP T12'!L:L,'HVP T12'!$B:$B,'P&Ls Detailed'!$G27) -> 0 | R27: =SUMIFS('HVP T12'!M:M,'HVP T12'!$B:$B,'P&Ls Detailed'!$G27) -> 0 | S27: =SUMIFS('HVP T12'!N:N,'HVP T12'!$B:$B,'P&Ls Detailed'!$G27) -> 0 | W27: =SUM(H27:S27) -> 40 | X27: =SUM(K27:S27)/9*12 -> 53.333333 | Y27: =SUM(N27:S27)/6*12 -> 0 | Z27: =SUM(Q27:S27)/3*12 -> 0 | AA27: =S27*12 -> 0
D28: =$AB$3 -> Hudson View Park | E28: Other Income | G28: PARKING FEE | H28: =SUMIFS('HVP T12'!C:C,'HVP T12'!$B:$B,'P&Ls Detailed'!$G28) -> 2365.32 | I28: =SUMIFS('HVP T12'!D:D,'HVP T12'!$B:$B,'P&Ls Detailed'!$G28) -> 2345.83 | J28: =SUMIFS('HVP T12'!E:E,'HVP T12'!$B:$B,'P&Ls Detailed'!$G28) -> 2325 | K28: =SUMIFS('HVP T12'!F:F,'HVP T12'!$B:$B,'P&Ls Detailed'!$G28) -> 2321.77 | L28: =SUMIFS('HVP T12'!G:G,'HVP T12'!$B:$B,'P&Ls Detailed'!$G28) -> 2320.83 | M28: =SUMIFS('HVP T12'!H:H,'HVP T12'!$B:$B,'P&Ls Detailed'!$G28) -> 2275.81 | N28: =SUMIFS('HVP T12'!I:I,'HVP T12'!$B:$B,'P&Ls Detailed'!$G28) -> 2350 | O28: =SUMIFS('HVP T12'!J:J,'HVP T12'!$B:$B,'P&Ls Detailed'!$G28) -> 2300 | P28: =SUMIFS('HVP T12'!K:K,'HVP T12'!$B:$B,'P&Ls Detailed'!$G28) -> 2271.77 | Q28: =SUMIFS('HVP T12'!L:L,'HVP T12'!$B:$B,'P&Ls Detailed'!$G28) -> 2250 | R28: =SUMIFS('HVP T12'!M:M,'HVP T12'!$B:$B,'P&Ls Detailed'!$G28) -> 2266.94 | S28: =SUMIFS('HVP T12'!N:N,'HVP T12'!$B:$B,'P&Ls Detailed'!$G28) -> 2270 | W28: =SUM(H28:S28) -> 27663.27 | X28: =SUM(K28:S28)/9*12 -> 27502.827 | Y28: =SUM(N28:S28)/6*12 -> 27417.42 | Z28: =SUM(Q28:S28)/3*12 -> 27147.76 | AA28: =S28*12 -> 27240
D29: =$AB$3 -> Hudson View Park | G29: DAMAGE BY TENANT
D30: =$AB$3 -> Hudson View Park | E30: Other Income | G30: CARPET CLEANING | H30: =SUMIFS('HVP T12'!C:C,'HVP T12'!$B:$B,'P&Ls Detailed'!$G30) -> 0 | I30: =SUMIFS('HVP T12'!D:D,'HVP T12'!$B:$B,'P&Ls Detailed'!$G30) -> 175 | J30: =SUMIFS('HVP T12'!E:E,'HVP T12'!$B:$B,'P&Ls Detailed'!$G30) -> 170 | K30: =SUMIFS('HVP T12'!F:F,'HVP T12'!$B:$B,'P&Ls Detailed'!$G30) -> 0 | L30: =SUMIFS('HVP T12'!G:G,'HVP T12'!$B:$B,'P&Ls Detailed'!$G30) -> 0 | M30: =SUMIFS('HVP T12'!H:H,'HVP T12'!$B:$B,'P&Ls Detailed'!$G30) -> 365 | N30: =SUMIFS('HVP T12'!I:I,'HVP T12'!$B:$B,'P&Ls Detailed'!$G30) -> 0 | O30: =SUMIFS('HVP T12'!J:J,'HVP T12'!$B:$B,'P&Ls Detailed'!$G30) -> 185 | P30: =SUMIFS('HVP T12'!K:K,'HVP T12'!$B:$B,'P&Ls Detailed'!$G30) -> 0 | Q30: =SUMIFS('HVP T12'!L:L,'HVP T12'!$B:$B,'P&Ls Detailed'!$G30) -> 0 | R30: =SUMIFS('HVP T12'!M:M,'HVP T12'!$B:$B,'P&Ls Detailed'!$G30) -> 475 | S30: =SUMIFS('HVP T12'!N:N,'HVP T12'!$B:$B,'P&Ls Detailed'!$G30) -> 0 | W30: =SUM(H30:S30) -> 1370 | X30: =SUM(K30:S30)/9*12 -> 1366.6667 | Y30: =SUM(N30:S30)/6*12 -> 1320 | Z30: =SUM(Q30:S30)/3*12 -> 1900 | AA30: =S30*12 -> 0
D31: =$AB$3 -> Hudson View Park | E31: Other Income | G31: CARPET REPLACEMENT | H31: =SUMIFS('HVP T12'!C:C,'HVP T12'!$B:$B,'P&Ls Detailed'!$G31) -> 0 | I31: =SUMIFS('HVP T12'!D:D,'HVP T12'!$B:$B,'P&Ls Detailed'!$G31) -> 289.08 | J31: =SUMIFS('HVP T12'!E:E,'HVP T12'!$B:$B,'P&Ls Detailed'!$G31) -> 0 | K31: =SUMIFS('HVP T12'!F:F,'HVP T12'!$B:$B,'P&Ls Detailed'!$G31) -> 0 | L31: =SUMIFS('HVP T12'!G:G,'HVP T12'!$B:$B,'P&Ls Detailed'!$G31) -> 0 | M31: =SUMIFS('HVP T12'!H:H,'HVP T12'!$B:$B,'P&Ls Detailed'!$G31) -> 0 | N31: =SUMIFS('HVP T12'!I:I,'HVP T12'!$B:$B,'P&Ls Detailed'!$G31) -> 0 | O31: =SUMIFS('HVP T12'!J:J,'HVP T12'!$B:$B,'P&Ls Detailed'!$G31) -> 0 | P31: =SUMIFS('HVP T12'!K:K,'HVP T12'!$B:$B,'P&Ls Detailed'!$G31) -> 0 | Q31: =SUMIFS('HVP T12'!L:L,'HVP T12'!$B:$B,'P&Ls Detailed'!$G31) -> 0 | R31: =SUMIFS('HVP T12'!M:M,'HVP T12'!$B:$B,'P&Ls Detailed'!$G31) -> 0 | S31: =SUMIFS('HVP T12'!N:N,'HVP T12'!$B:$B,'P&Ls Detailed'!$G31) -> 0 | W31: =SUM(H31:S31) -> 289.08 | X31: =SUM(K31:S31)/9*12 -> 0 | Y31: =SUM(N31:S31)/6*12 -> 0 | Z31: =SUM(Q31:S31)/3*12 -> 0 | AA31: =S31*12 -> 0
D32: =$AB$3 -> Hudson View Park | E32: Other Income | G32: APT REPAIRS | H32: =SUMIFS('HVP T12'!C:C,'HVP T12'!$B:$B,'P&Ls Detailed'!$G32) -> 200 | I32: =SUMIFS('HVP T12'!D:D,'HVP T12'!$B:$B,'P&Ls Detailed'!$G32) -> 1700 | J32: =SUMIFS('HVP T12'!E:E,'HVP T12'!$B:$B,'P&Ls Detailed'!$G32) -> 1000 | K32: =SUMIFS('HVP T12'!F:F,'HVP T12'!$B:$B,'P&Ls Detailed'!$G32) -> 0 | L32: =SUMIFS('HVP T12'!G:G,'HVP T12'!$B:$B,'P&Ls Detailed'!$G32) -> 0 | M32: =SUMIFS('HVP T12'!H:H,'HVP T12'!$B:$B,'P&Ls Detailed'!$G32) -> 0 | N32: =SUMIFS('HVP T12'!I:I,'HVP T12'!$B:$B,'P&Ls Detailed'!$G32) -> 100 | O32: =SUMIFS('HVP T12'!J:J,'HVP T12'!$B:$B,'P&Ls Detailed'!$G32) -> 656.94 | P32: =SUMIFS('HVP T12'!K:K,'HVP T12'!$B:$B,'P&Ls Detailed'!$G32) -> 0 | Q32: =SUMIFS('HVP T12'!L:L,'HVP T12'!$B:$B,'P&Ls Detailed'!$G32) -> 0 | R32: =SUMIFS('HVP T12'!M:M,'HVP T12'!$B:$B,'P&Ls Detailed'!$G32) -> 0 | S32: =SUMIFS('HVP T12'!N:N,'HVP T12'!$B:$B,'P&Ls Detailed'!$G32) -> 0 | W32: =SUM(H32:S32) -> 3656.94 | X32: =SUM(K32:S32)/9*12 -> 1009.2533 | Y32: =SUM(N32:S32)/6*12 -> 1513.88 | Z32: =SUM(Q32:S32)/3*12 -> 0 | AA32: =S32*12 -> 0
D33: =$AB$3 -> Hudson View Park | E33: Other Income | G33: APT CLEANING | H33: =SUMIFS('HVP T12'!C:C,'HVP T12'!$B:$B,'P&Ls Detailed'!$G33) -> 549 | I33: =SUMIFS('HVP T12'!D:D,'HVP T12'!$B:$B,'P&Ls Detailed'!$G33) -> 2944 | J33: =SUMIFS('HVP T12'!E:E,'HVP T12'!$B:$B,'P&Ls Detailed'!$G33) -> 737 | K33: =SUMIFS('HVP T12'!F:F,'HVP T12'!$B:$B,'P&Ls Detailed'!$G33) -> 325 | L33: =SUMIFS('HVP T12'!G:G,'HVP T12'!$B:$B,'P&Ls Detailed'!$G33) -> 0 | M33: =SUMIFS('HVP T12'!H:H,'HVP T12'!$B:$B,'P&Ls Detailed'!$G33) -> 978 | N33: =SUMIFS('HVP T12'!I:I,'HVP T12'!$B:$B,'P&Ls Detailed'!$G33) -> 412 | O33: =SUMIFS('HVP T12'!J:J,'HVP T12'!$B:$B,'P&Ls Detailed'!$G33) -> 275 | P33: =SUMIFS('HVP T12'!K:K,'HVP T12'!$B:$B,'P&Ls Detailed'!$G33) -> 300 | Q33: =SUMIFS('HVP T12'!L:L,'HVP T12'!$B:$B,'P&Ls Detailed'!$G33) -> 0 | R33: =SUMIFS('HVP T12'!M:M,'HVP T12'!$B:$B,'P&Ls Detailed'!$G33) -> 205 | S33: =SUMIFS('HVP T12'!N:N,'HVP T12'!$B:$B,'P&Ls Detailed'!$G33) -> 0 | W33: =SUM(H33:S33) -> 6725 | X33: =SUM(K33:S33)/9*12 -> 3326.6667 | Y33: =SUM(N33:S33)/6*12 -> 2384 | Z33: =SUM(Q33:S33)/3*12 -> 820 | AA33: =S33*12 -> 0
D34: =$AB$3 -> Hudson View Park | G34: Total DAMAGE BY TENANT | H34: =SUM(H30:H33) -> 749 | I34: =SUM(I30:I33) -> 5108.08 | J34: =SUM(J30:J33) -> 1907 | K34: =SUM(K30:K33) -> 325 | L34: =SUM(L30:L33) -> 0 | M34: =SUM(M30:M33) -> 1343 | N34: =SUM(N30:N33) -> 512 | O34: =SUM(O30:O33) -> 1116.94 | ... S34: =SUM(S30:S33) -> 0 | W34: =SUM(W30:W33) -> 12041.02 | X34: =SUM(X30:X33) -> 5702.5867 | Y34: =SUM(Y30:Y33) -> 5217.88 | Z34: =SUM(Z30:Z33) -> 2720 | AA34: =SUM(AA30:AA33) -> 0
D35: =$AB$3 -> Hudson View Park | E35: Other Income | G35: FORFEIT INCOME (BL) | H35: =SUMIFS('HVP T12'!C:C,'HVP T12'!$B:$B,'P&Ls Detailed'!$G35) -> 4765 | I35: =SUMIFS('HVP T12'!D:D,'HVP T12'!$B:$B,'P&Ls Detailed'!$G35) -> 1815 | J35: =SUMIFS('HVP T12'!E:E,'HVP T12'!$B:$B,'P&Ls Detailed'!$G35) -> 7865 | K35: =SUMIFS('HVP T12'!F:F,'HVP T12'!$B:$B,'P&Ls Detailed'!$G35) -> 0 | L35: =SUMIFS('HVP T12'!G:G,'HVP T12'!$B:$B,'P&Ls Detailed'!$G35) -> 4780 | M35: =SUMIFS('HVP T12'!H:H,'HVP T12'!$B:$B,'P&Ls Detailed'!$G35) -> 3720 | N35: =SUMIFS('HVP T12'!I:I,'HVP T12'!$B:$B,'P&Ls Detailed'!$G35) -> 7870 | O35: =SUMIFS('HVP T12'!J:J,'HVP T12'!$B:$B,'P&Ls Detailed'!$G35) -> 2220 | P35: =SUMIFS('HVP T12'!K:K,'HVP T12'!$B:$B,'P&Ls Detailed'!$G35) -> 7810 | Q35: =SUMIFS('HVP T12'!L:L,'HVP T12'!$B:$B,'P&Ls Detailed'!$G35) -> 1400 | R35: =SUMIFS('HVP T12'!M:M,'HVP T12'!$B:$B,'P&Ls Detailed'!$G35) -> 3845 | S35: =SUMIFS('HVP T12'!N:N,'HVP T12'!$B:$B,'P&Ls Detailed'!$G35) -> 0 | W35: =SUM(H35:S35) -> 46090 | X35: =SUM(K35:S35)/9*12 -> 42193.333 | Y35: =SUM(N35:S35)/6*12 -> 46290 | Z35: =SUM(Q35:S35)/3*12 -> 20980 | AA35: =S35*12 -> 0
D36: =$AB$3 -> Hudson View Park | E36: Other Income | G36: FORFEIT INCOME (TRANSFER) | H36: =SUMIFS('HVP T12'!C:C,'HVP T12'!$B:$B,'P&Ls Detailed'!$G36) -> 1500 | I36: =SUMIFS('HVP T12'!D:D,'HVP T12'!$B:$B,'P&Ls Detailed'!$G36) -> 0 | J36: =SUMIFS('HVP T12'!E:E,'HVP T12'!$B:$B,'P&Ls Detailed'!$G36) -> 0 | K36: =SUMIFS('HVP T12'!F:F,'HVP T12'!$B:$B,'P&Ls Detailed'!$G36) -> 2000 | L36: =SUMIFS('HVP T12'!G:G,'HVP T12'!$B:$B,'P&Ls Detailed'!$G36) -> 1000 | M36: =SUMIFS('HVP T12'!H:H,'HVP T12'!$B:$B,'P&Ls Detailed'!$G36) -> 500 | N36: =SUMIFS('HVP T12'!I:I,'HVP T12'!$B:$B,'P&Ls Detailed'!$G36) -> 500 | O36: =SUMIFS('HVP T12'!J:J,'HVP T12'!$B:$B,'P&Ls Detailed'!$G36) -> 1000 | P36: =SUMIFS('HVP T12'!K:K,'HVP T12'!$B:$B,'P&Ls Detailed'!$G36) -> 0 | Q36: =SUMIFS('HVP T12'!L:L,'HVP T12'!$B:$B,'P&Ls Detailed'!$G36) -> 1000 | R36: =SUMIFS('HVP T12'!M:M,'HVP T12'!$B:$B,'P&Ls Detailed'!$G36) -> 0 | S36: =SUMIFS('HVP T12'!N:N,'HVP T12'!$B:$B,'P&Ls Detailed'!$G36) -> 500 | W36: =SUM(H36:S36) -> 8000 | X36: =SUM(K36:S36)/9*12 -> 8666.6667 | Y36: =SUM(N36:S36)/6*12 -> 6000 | Z36: =SUM(Q36:S36)/3*12 -> 6000 | AA36: =S36*12 -> 6000
D37: =$AB$3 -> Hudson View Park | E37: Other Income | G37: INSURANCE SERVICES | H37: =SUMIFS('HVP T12'!C:C,'HVP T12'!$B:$B,'P&Ls Detailed'!$G37) -> -9.5 | I37: =SUMIFS('HVP T12'!D:D,'HVP T12'!$B:$B,'P&Ls Detailed'!$G37) -> -8.5 | J37: =SUMIFS('HVP T12'!E:E,'HVP T12'!$B:$B,'P&Ls Detailed'!$G37) -> -7.5 | K37: =SUMIFS('HVP T12'!F:F,'HVP T12'!$B:$B,'P&Ls Detailed'!$G37) -> -9.5 | L37: =SUMIFS('HVP T12'!G:G,'HVP T12'!$B:$B,'P&Ls Detailed'!$G37) -> -8.5 | M37: =SUMIFS('HVP T12'!H:H,'HVP T12'!$B:$B,'P&Ls Detailed'!$G37) -> 0 | N37: =SUMIFS('HVP T12'!I:I,'HVP T12'!$B:$B,'P&Ls Detailed'!$G37) -> 21 | O37: =SUMIFS('HVP T12'!J:J,'HVP T12'!$B:$B,'P&Ls Detailed'!$G37) -> -62 | P37: =SUMIFS('HVP T12'!K:K,'HVP T12'!$B:$B,'P&Ls Detailed'!$G37) -> -51.5 | Q37: =SUMIFS('HVP T12'!L:L,'HVP T12'!$B:$B,'P&Ls Detailed'!$G37) -> 0 | R37: =SUMIFS('HVP T12'!M:M,'HVP T12'!$B:$B,'P&Ls Detailed'!$G37) -> 0 | S37: =SUMIFS('HVP T12'!N:N,'HVP T12'!$B:$B,'P&Ls Detailed'!$G37) -> 0 | W37: =SUM(H37:S37) -> -136 | X37: =SUM(K37:S37)/9*12 -> -147.33333 | Y37: =SUM(N37:S37)/6*12 -> -185 | Z37: =SUM(Q37:S37)/3*12 -> 0 | AA37: =S37*12 -> 0
D38: =$AB$3 -> Hudson View Park | E38: Other Income | G38: INSURANCE SERVICE - ADMIN FEE | H38: =SUMIFS('HVP T12'!C:C,'HVP T12'!$B:$B,'P&Ls Detailed'!$G38) -> 36 | I38: =SUMIFS('HVP T12'!D:D,'HVP T12'!$B:$B,'P&Ls Detailed'!$G38) -> 33 | J38: =SUMIFS('HVP T12'!E:E,'HVP T12'!$B:$B,'P&Ls Detailed'!$G38) -> 30 | K38: =SUMIFS('HVP T12'!F:F,'HVP T12'!$B:$B,'P&Ls Detailed'!$G38) -> 27 | L38: =SUMIFS('HVP T12'!G:G,'HVP T12'!$B:$B,'P&Ls Detailed'!$G38) -> 24 | M38: =SUMIFS('HVP T12'!H:H,'HVP T12'!$B:$B,'P&Ls Detailed'!$G38) -> 24 | N38: =SUMIFS('HVP T12'!I:I,'HVP T12'!$B:$B,'P&Ls Detailed'!$G38) -> 30 | O38: =SUMIFS('HVP T12'!J:J,'HVP T12'!$B:$B,'P&Ls Detailed'!$G38) -> 18 | P38: =SUMIFS('HVP T12'!K:K,'HVP T12'!$B:$B,'P&Ls Detailed'!$G38) -> 0 | Q38: =SUMIFS('HVP T12'!L:L,'HVP T12'!$B:$B,'P&Ls Detailed'!$G38) -> 0 | R38: =SUMIFS('HVP T12'!M:M,'HVP T12'!$B:$B,'P&Ls Detailed'!$G38) -> 0 | S38: =SUMIFS('HVP T12'!N:N,'HVP T12'!$B:$B,'P&Ls Detailed'!$G38) -> 0 | W38: =SUM(H38:S38) -> 222 | X38: =SUM(K38:S38)/9*12 -> 164 | Y38: =SUM(N38:S38)/6*12 -> 96 | Z38: =SUM(Q38:S38)/3*12 -> 0 | AA38: =S38*12 -> 0
D39: =$AB$3 -> Hudson View Park | E39: Utility Reimbursement | G39: WATER FEE | H39: =SUMIFS('HVP T12'!C:C,'HVP T12'!$B:$B,'P&Ls Detailed'!$G39) -> 1407.1 | I39: =SUMIFS('HVP T12'!D:D,'HVP T12'!$B:$B,'P&Ls Detailed'!$G39) -> 1380 | J39: =SUMIFS('HVP T12'!E:E,'HVP T12'!$B:$B,'P&Ls Detailed'!$G39) -> 1426.45 | K39: =SUMIFS('HVP T12'!F:F,'HVP T12'!$B:$B,'P&Ls Detailed'!$G39) -> 1410 | L39: =SUMIFS('HVP T12'!G:G,'HVP T12'!$B:$B,'P&Ls Detailed'!$G39) -> 1435 | M39: =SUMIFS('HVP T12'!H:H,'HVP T12'!$B:$B,'P&Ls Detailed'!$G39) -> 1436.13 | N39: =SUMIFS('HVP T12'!I:I,'HVP T12'!$B:$B,'P&Ls Detailed'!$G39) -> 1440 | O39: =SUMIFS('HVP T12'!J:J,'HVP T12'!$B:$B,'P&Ls Detailed'!$G39) -> 1413.87 | P39: =SUMIFS('HVP T12'!K:K,'HVP T12'!$B:$B,'P&Ls Detailed'!$G39) -> 1440 | Q39: =SUMIFS('HVP T12'!L:L,'HVP T12'!$B:$B,'P&Ls Detailed'!$G39) -> 1464.64 | R39: =SUMIFS('HVP T12'!M:M,'HVP T12'!$B:$B,'P&Ls Detailed'!$G39) -> 1495.16 | S39: =SUMIFS('HVP T12'!N:N,'HVP T12'!$B:$B,'P&Ls Detailed'!$G39) -> 1500 | W39: =SUM(H39:S39) -> 17248.35 | X39: =SUM(K39:S39)/9*12 -> 17379.733 | Y39: =SUM(N39:S39)/6*12 -> 17507.34 | Z39: =SUM(Q39:S39)/3*12 -> 17839.2 | AA39: =S39*12 -> 18000
D40: =$AB$3 -> Hudson View Park | G40: Total OTHER REVENUE | H40: =SUM(H17:H28,H34,H35:H39) -> 69465.62 | I40: =SUM(I17:I28,I34,I35:I39) -> 65547.92 | J40: =SUM(J17:J28,J34,J35:J39) -> 66262.76 | K40: =SUM(K17:K28,K34,K35:K39) -> 55753.17 | L40: =SUM(L17:L28,L34,L35:L39) -> 56039.63 | M40: =SUM(M17:M28,M34,M35:M39) -> 53050.96 | N40: =SUM(N17:N28,N34,N35:N39) -> 51400.35 | O40: =SUM(O17:O28,O34,O35:O39) -> 43520.89 | ... S40: =SUM(S17:S28,S34,S35:S39) -> 28043.86 | W40: =SUM(W17:W28,W34,W35:W39) -> 605526.07 | X40: =SUM(X17:X28,X34,X35:X39) -> 538999.69 | Y40: =SUM(Y17:Y28,Y34,Y35:Y39) -> 478812.02 | Z40: =SUM(Z17:Z28,Z34,Z35:Z39) -> 408935.84 | AA40: =SUM(AA17:AA28,AA34,AA35:AA39) -> 336526.32
D41: =$AB$3 -> Hudson View Park
D42: =$AB$3 -> Hudson View Park
D43: =$AB$3 -> Hudson View Park | G43: TOTAL INCOME | H43: =SUM(H15,H40) -> 956990.62 | I43: =SUM(I15,I40) -> 952677.4 | J43: =SUM(J15,J40) -> 960110.37 | K43: =SUM(K15,K40) -> 964779.17 | L43: =SUM(L15,L40) -> 982489.67 | M43: =SUM(M15,M40) -> 984776.03 | N43: =SUM(N15,N40) -> 994553.57 | O43: =SUM(O15,O40) -> 987878.67 | ... S43: =SUM(S15,S40) -> 1016103.4 | W43: =SUM(W15,W40) -> 11817441 | X43: =SUM(X15,X40) -> 11930217 | Y43: =SUM(Y15,Y40) -> 12031236 | Z43: =SUM(Z15,Z40) -> 12141901 | AA43: =SUM(AA15,AA40) -> 12193241
D44: =$AB$3 -> Hudson View Park
D45: =$AB$3 -> Hudson View Park
D46: =$AB$3 -> Hudson View Park | G46: Expense
D47: =$AB$3 -> Hudson View Park | G47: PAYROLL AND RELATED
D48: =$AB$3 -> Hudson View Park | E48: Personnel | F48: Exclude | G48: SALARIES-MAINT | H48: =SUMIFS('HVP T12'!C:C,'HVP T12'!$B:$B,'P&Ls Detailed'!$G48) -> 67272.04 | I48: =SUMIFS('HVP T12'!D:D,'HVP T12'!$B:$B,'P&Ls Detailed'!$G48) -> 64084.28 | J48: =SUMIFS('HVP T12'!E:E,'HVP T12'!$B:$B,'P&Ls Detailed'!$G48) -> 66883.06 | K48: =SUMIFS('HVP T12'!F:F,'HVP T12'!$B:$B,'P&Ls Detailed'!$G48) -> 101130.34 | L48: =SUMIFS('HVP T12'!G:G,'HVP T12'!$B:$B,'P&Ls Detailed'!$G48) -> 66987.16 | M48: =SUMIFS('HVP T12'!H:H,'HVP T12'!$B:$B,'P&Ls Detailed'!$G48) -> 67665.49 | N48: =SUMIFS('HVP T12'!I:I,'HVP T12'!$B:$B,'P&Ls Detailed'!$G48) -> 68729.06 | O48: =SUMIFS('HVP T12'!J:J,'HVP T12'!$B:$B,'P&Ls Detailed'!$G48) -> 63397.07 | P48: =SUMIFS('HVP T12'!K:K,'HVP T12'!$B:$B,'P&Ls Detailed'!$G48) -> 95679.37 | Q48: =SUMIFS('HVP T12'!L:L,'HVP T12'!$B:$B,'P&Ls Detailed'!$G48) -> 67488.49 | R48: =SUMIFS('HVP T12'!M:M,'HVP T12'!$B:$B,'P&Ls Detailed'!$G48) -> 68209.06 | S48: =SUMIFS('HVP T12'!N:N,'HVP T12'!$B:$B,'P&Ls Detailed'!$G48) -> 70785.46 | W48: =SUM(H48:S48) -> 868310.88 | X48: =SUM(K48:S48)/9*12 -> 893428.67 | Y48: =SUM(N48:S48)/6*12 -> 868577.02 | Z48: =SUM(Q48:S48)/3*12 -> 825932.04 | AA48: =S48*12 -> 849425.52
D49: =$AB$3 -> Hudson View Park | E49: Personnel | G49: SALARIES-OT | H49: =SUMIFS('HVP T12'!C:C,'HVP T12'!$B:$B,'P&Ls Detailed'!$G49) -> 2222.3 | I49: =SUMIFS('HVP T12'!D:D,'HVP T12'!$B:$B,'P&Ls Detailed'!$G49) -> 2380.19 | J49: =SUMIFS('HVP T12'!E:E,'HVP T12'!$B:$B,'P&Ls Detailed'!$G49) -> 2005.13 | K49: =SUMIFS('HVP T12'!F:F,'HVP T12'!$B:$B,'P&Ls Detailed'!$G49) -> 3162.09 | L49: =SUMIFS('HVP T12'!G:G,'HVP T12'!$B:$B,'P&Ls Detailed'!$G49) -> 2297.88 | M49: =SUMIFS('HVP T12'!H:H,'HVP T12'!$B:$B,'P&Ls Detailed'!$G49) -> 1981.22 | N49: =SUMIFS('HVP T12'!I:I,'HVP T12'!$B:$B,'P&Ls Detailed'!$G49) -> 1833.82 | O49: =SUMIFS('HVP T12'!J:J,'HVP T12'!$B:$B,'P&Ls Detailed'!$G49) -> 2542.46 | P49: =SUMIFS('HVP T12'!K:K,'HVP T12'!$B:$B,'P&Ls Detailed'!$G49) -> 5904.94 | Q49: =SUMIFS('HVP T12'!L:L,'HVP T12'!$B:$B,'P&Ls Detailed'!$G49) -> 4229.42 | R49: =SUMIFS('HVP T12'!M:M,'HVP T12'!$B:$B,'P&Ls Detailed'!$G49) -> 1870.26 | S49: =SUMIFS('HVP T12'!N:N,'HVP T12'!$B:$B,'P&Ls Detailed'!$G49) -> 1938.3 | W49: =SUM(H49:S49) -> 32368.01 | X49: =SUM(K49:S49)/9*12 -> 34347.187 | Y49: =SUM(N49:S49)/6*12 -> 36638.4 | Z49: =SUM(Q49:S49)/3*12 -> 32151.92 | AA49: =S49*12 -> 23259.6
D50: =$AB$3 -> Hudson View Park | E50: Personnel | G50: SALARIES-V/H/SL | H50: =SUMIFS('HVP T12'!C:C,'HVP T12'!$B:$B,'P&Ls Detailed'!$G50) -> 8067.02 | I50: =SUMIFS('HVP T12'!D:D,'HVP T12'!$B:$B,'P&Ls Detailed'!$G50) -> 19535.91 | J50: =SUMIFS('HVP T12'!E:E,'HVP T12'!$B:$B,'P&Ls Detailed'!$G50) -> 5057.19 | K50: =SUMIFS('HVP T12'!F:F,'HVP T12'!$B:$B,'P&Ls Detailed'!$G50) -> 4801.94 | L50: =SUMIFS('HVP T12'!G:G,'HVP T12'!$B:$B,'P&Ls Detailed'!$G50) -> 3333.97 | M50: =SUMIFS('HVP T12'!H:H,'HVP T12'!$B:$B,'P&Ls Detailed'!$G50) -> 1447.8 | N50: =SUMIFS('HVP T12'!I:I,'HVP T12'!$B:$B,'P&Ls Detailed'!$G50) -> 1567.46 | O50: =SUMIFS('HVP T12'!J:J,'HVP T12'!$B:$B,'P&Ls Detailed'!$G50) -> 50266.61 | P50: =SUMIFS('HVP T12'!K:K,'HVP T12'!$B:$B,'P&Ls Detailed'!$G50) -> 16426.76 | Q50: =SUMIFS('HVP T12'!L:L,'HVP T12'!$B:$B,'P&Ls Detailed'!$G50) -> 13074.76 | R50: =SUMIFS('HVP T12'!M:M,'HVP T12'!$B:$B,'P&Ls Detailed'!$G50) -> 5380.21 | S50: =SUMIFS('HVP T12'!N:N,'HVP T12'!$B:$B,'P&Ls Detailed'!$G50) -> 2999.67 | W50: =SUM(H50:S50) -> 131959.3 | X50: =SUM(K50:S50)/9*12 -> 132398.91 | Y50: =SUM(N50:S50)/6*12 -> 179430.94 | Z50: =SUM(Q50:S50)/3*12 -> 85818.56 | AA50: =S50*12 -> 35996.04
D51: =$AB$3 -> Hudson View Park | E51: Personnel | G51: P/R TAXES-FICA | H51: =SUMIFS('HVP T12'!C:C,'HVP T12'!$B:$B,'P&Ls Detailed'!$G51) -> 5740.02 | I51: =SUMIFS('HVP T12'!D:D,'HVP T12'!$B:$B,'P&Ls Detailed'!$G51) -> 6385.61 | J51: =SUMIFS('HVP T12'!E:E,'HVP T12'!$B:$B,'P&Ls Detailed'!$G51) -> 5459.81 | K51: =SUMIFS('HVP T12'!F:F,'HVP T12'!$B:$B,'P&Ls Detailed'!$G51) -> 8044.8 | L51: =SUMIFS('HVP T12'!G:G,'HVP T12'!$B:$B,'P&Ls Detailed'!$G51) -> 5354.74 | M51: =SUMIFS('HVP T12'!H:H,'HVP T12'!$B:$B,'P&Ls Detailed'!$G51) -> 5238.12 | N51: =SUMIFS('HVP T12'!I:I,'HVP T12'!$B:$B,'P&Ls Detailed'!$G51) -> 5329.92 | O51: =SUMIFS('HVP T12'!J:J,'HVP T12'!$B:$B,'P&Ls Detailed'!$G51) -> 8701.7 | P51: =SUMIFS('HVP T12'!K:K,'HVP T12'!$B:$B,'P&Ls Detailed'!$G51) -> 8678.76 | Q51: =SUMIFS('HVP T12'!L:L,'HVP T12'!$B:$B,'P&Ls Detailed'!$G51) -> 6253.9 | R51: =SUMIFS('HVP T12'!M:M,'HVP T12'!$B:$B,'P&Ls Detailed'!$G51) -> 5539.93 | S51: =SUMIFS('HVP T12'!N:N,'HVP T12'!$B:$B,'P&Ls Detailed'!$G51) -> 5560.12 | W51: =SUM(H51:S51) -> 76287.43 | X51: =SUM(K51:S51)/9*12 -> 78269.32 | Y51: =SUM(N51:S51)/6*12 -> 80128.66 | Z51: =SUM(Q51:S51)/3*12 -> 69415.8 | AA51: =S51*12 -> 66721.44
D52: =$AB$3 -> Hudson View Park | E52: Personnel | G52: P/R TAXES FUTA | H52: =SUMIFS('HVP T12'!C:C,'HVP T12'!$B:$B,'P&Ls Detailed'!$G52) -> 0 | I52: =SUMIFS('HVP T12'!D:D,'HVP T12'!$B:$B,'P&Ls Detailed'!$G52) -> 0 | J52: =SUMIFS('HVP T12'!E:E,'HVP T12'!$B:$B,'P&Ls Detailed'!$G52) -> 0 | K52: =SUMIFS('HVP T12'!F:F,'HVP T12'!$B:$B,'P&Ls Detailed'!$G52) -> 0 | L52: =SUMIFS('HVP T12'!G:G,'HVP T12'!$B:$B,'P&Ls Detailed'!$G52) -> 5.76 | M52: =SUMIFS('HVP T12'!H:H,'HVP T12'!$B:$B,'P&Ls Detailed'!$G52) -> 14.4 | N52: =SUMIFS('HVP T12'!I:I,'HVP T12'!$B:$B,'P&Ls Detailed'!$G52) -> 13.44 | O52: =SUMIFS('HVP T12'!J:J,'HVP T12'!$B:$B,'P&Ls Detailed'!$G52) -> 0 | P52: =SUMIFS('HVP T12'!K:K,'HVP T12'!$B:$B,'P&Ls Detailed'!$G52) -> 593.48 | Q52: =SUMIFS('HVP T12'!L:L,'HVP T12'!$B:$B,'P&Ls Detailed'!$G52) -> 50.23 | R52: =SUMIFS('HVP T12'!M:M,'HVP T12'!$B:$B,'P&Ls Detailed'!$G52) -> 0.8 | S52: =SUMIFS('HVP T12'!N:N,'HVP T12'!$B:$B,'P&Ls Detailed'!$G52) -> 0 | W52: =SUM(H52:S52) -> 678.11 | X52: =SUM(K52:S52)/9*12 -> 904.14667 | Y52: =SUM(N52:S52)/6*12 -> 1315.9 | Z52: =SUM(Q52:S52)/3*12 -> 204.12 | AA52: =S52*12 -> 0
D53: =$AB$3 -> Hudson View Park | E53: Personnel | G53: P/R TAX--NY UNEMP | H53: =SUMIFS('HVP T12'!C:C,'HVP T12'!$B:$B,'P&Ls Detailed'!$G53) -> 0 | I53: =SUMIFS('HVP T12'!D:D,'HVP T12'!$B:$B,'P&Ls Detailed'!$G53) -> 0 | J53: =SUMIFS('HVP T12'!E:E,'HVP T12'!$B:$B,'P&Ls Detailed'!$G53) -> 0 | K53: =SUMIFS('HVP T12'!F:F,'HVP T12'!$B:$B,'P&Ls Detailed'!$G53) -> 0 | L53: =SUMIFS('HVP T12'!G:G,'HVP T12'!$B:$B,'P&Ls Detailed'!$G53) -> 20.16 | M53: =SUMIFS('HVP T12'!H:H,'HVP T12'!$B:$B,'P&Ls Detailed'!$G53) -> 50.4 | N53: =SUMIFS('HVP T12'!I:I,'HVP T12'!$B:$B,'P&Ls Detailed'!$G53) -> 50.4 | O53: =SUMIFS('HVP T12'!J:J,'HVP T12'!$B:$B,'P&Ls Detailed'!$G53) -> 50.4 | P53: =SUMIFS('HVP T12'!K:K,'HVP T12'!$B:$B,'P&Ls Detailed'!$G53) -> 2478.24 | Q53: =SUMIFS('HVP T12'!L:L,'HVP T12'!$B:$B,'P&Ls Detailed'!$G53) -> 1212.01 | R53: =SUMIFS('HVP T12'!M:M,'HVP T12'!$B:$B,'P&Ls Detailed'!$G53) -> 344.49 | S53: =SUMIFS('HVP T12'!N:N,'HVP T12'!$B:$B,'P&Ls Detailed'!$G53) -> 48.93 | W53: =SUM(H53:S53) -> 4255.03 | X53: =SUM(K53:S53)/9*12 -> 5673.3733 | Y53: =SUM(N53:S53)/6*12 -> 8368.94 | Z53: =SUM(Q53:S53)/3*12 -> 6421.72 | AA53: =S53*12 -> 587.16
D54: =$AB$3 -> Hudson View Park | E54: Personnel | G54: P/R TAX MCTMT TAX | H54: =SUMIFS('HVP T12'!C:C,'HVP T12'!$B:$B,'P&Ls Detailed'!$G54) -> 229.49 | I54: =SUMIFS('HVP T12'!D:D,'HVP T12'!$B:$B,'P&Ls Detailed'!$G54) -> 255.89 | J54: =SUMIFS('HVP T12'!E:E,'HVP T12'!$B:$B,'P&Ls Detailed'!$G54) -> 180.21 | K54: =SUMIFS('HVP T12'!F:F,'HVP T12'!$B:$B,'P&Ls Detailed'!$G54) -> 213.81 | L54: =SUMIFS('HVP T12'!G:G,'HVP T12'!$B:$B,'P&Ls Detailed'!$G54) -> 140.13 | M54: =SUMIFS('HVP T12'!H:H,'HVP T12'!$B:$B,'P&Ls Detailed'!$G54) -> 198.61 | N54: =SUMIFS('HVP T12'!I:I,'HVP T12'!$B:$B,'P&Ls Detailed'!$G54) -> 202.43 | O54: =SUMIFS('HVP T12'!J:J,'HVP T12'!$B:$B,'P&Ls Detailed'!$G54) -> 329.06 | P54: =SUMIFS('HVP T12'!K:K,'HVP T12'!$B:$B,'P&Ls Detailed'!$G54) -> 329.36 | Q54: =SUMIFS('HVP T12'!L:L,'HVP T12'!$B:$B,'P&Ls Detailed'!$G54) -> 240.01 | R54: =SUMIFS('HVP T12'!M:M,'HVP T12'!$B:$B,'P&Ls Detailed'!$G54) -> 210.14 | S54: =SUMIFS('HVP T12'!N:N,'HVP T12'!$B:$B,'P&Ls Detailed'!$G54) -> 213.35 | W54: =SUM(H54:S54) -> 2742.49 | X54: =SUM(K54:S54)/9*12 -> 2769.2 | Y54: =SUM(N54:S54)/6*12 -> 3048.7 | Z54: =SUM(Q54:S54)/3*12 -> 2654 | AA54: =S54*12 -> 2560.2
D55: =$AB$3 -> Hudson View Park | E55: Personnel | G55: NY DISABILITY IN | H55: =SUMIFS('HVP T12'!C:C,'HVP T12'!$B:$B,'P&Ls Detailed'!$G55) -> 663.89 | I55: =SUMIFS('HVP T12'!D:D,'HVP T12'!$B:$B,'P&Ls Detailed'!$G55) -> 669.36 | J55: =SUMIFS('HVP T12'!E:E,'HVP T12'!$B:$B,'P&Ls Detailed'!$G55) -> 686.08 | K55: =SUMIFS('HVP T12'!F:F,'HVP T12'!$B:$B,'P&Ls Detailed'!$G55) -> 693.28 | L55: =SUMIFS('HVP T12'!G:G,'HVP T12'!$B:$B,'P&Ls Detailed'!$G55) -> 664 | M55: =SUMIFS('HVP T12'!H:H,'HVP T12'!$B:$B,'P&Ls Detailed'!$G55) -> 685.32 | N55: =SUMIFS('HVP T12'!I:I,'HVP T12'!$B:$B,'P&Ls Detailed'!$G55) -> 691.34 | O55: =SUMIFS('HVP T12'!J:J,'HVP T12'!$B:$B,'P&Ls Detailed'!$G55) -> 691.34 | P55: =SUMIFS('HVP T12'!K:K,'HVP T12'!$B:$B,'P&Ls Detailed'!$G55) -> 749.88 | Q55: =SUMIFS('HVP T12'!L:L,'HVP T12'!$B:$B,'P&Ls Detailed'!$G55) -> 749.88 | R55: =SUMIFS('HVP T12'!M:M,'HVP T12'!$B:$B,'P&Ls Detailed'!$G55) -> 749.88 | S55: =SUMIFS('HVP T12'!N:N,'HVP T12'!$B:$B,'P&Ls Detailed'!$G55) -> 749.88 | W55: =SUM(H55:S55) -> 8444.13 | X55: =SUM(K55:S55)/9*12 -> 8566.4 | Y55: =SUM(N55:S55)/6*12 -> 8764.4 | Z55: =SUM(Q55:S55)/3*12 -> 8998.56 | AA55: =S55*12 -> 8998.56
D56: =$AB$3 -> Hudson View Park | E56: Personnel | G56: WORKMANS COMP | H56: =SUMIFS('HVP T12'!C:C,'HVP T12'!$B:$B,'P&Ls Detailed'!$G56) -> 3144.38 | I56: =SUMIFS('HVP T12'!D:D,'HVP T12'!$B:$B,'P&Ls Detailed'!$G56) -> 3225 | J56: =SUMIFS('HVP T12'!E:E,'HVP T12'!$B:$B,'P&Ls Detailed'!$G56) -> 2912.57 | K56: =SUMIFS('HVP T12'!F:F,'HVP T12'!$B:$B,'P&Ls Detailed'!$G56) -> 4292.7 | L56: =SUMIFS('HVP T12'!G:G,'HVP T12'!$B:$B,'P&Ls Detailed'!$G56) -> 2805.92 | M56: =SUMIFS('HVP T12'!H:H,'HVP T12'!$B:$B,'P&Ls Detailed'!$G56) -> 2512.36 | N56: =SUMIFS('HVP T12'!I:I,'HVP T12'!$B:$B,'P&Ls Detailed'!$G56) -> 2744.28 | O56: =SUMIFS('HVP T12'!J:J,'HVP T12'!$B:$B,'P&Ls Detailed'!$G56) -> 4464.47 | P56: =SUMIFS('HVP T12'!K:K,'HVP T12'!$B:$B,'P&Ls Detailed'!$G56) -> -4690.94 | Q56: =SUMIFS('HVP T12'!L:L,'HVP T12'!$B:$B,'P&Ls Detailed'!$G56) -> 2174.23 | R56: =SUMIFS('HVP T12'!M:M,'HVP T12'!$B:$B,'P&Ls Detailed'!$G56) -> 1905.6 | S56: =SUMIFS('HVP T12'!N:N,'HVP T12'!$B:$B,'P&Ls Detailed'!$G56) -> 1911.81 | W56: =SUM(H56:S56) -> 27402.38 | X56: =SUM(K56:S56)/9*12 -> 24160.573 | Y56: =SUM(N56:S56)/6*12 -> 17018.9 | Z56: =SUM(Q56:S56)/3*12 -> 23966.56 | AA56: =S56*12 -> 22941.72
D57: =$AB$3 -> Hudson View Park | E57: Personnel | G57: GRP HOSP INS PRM | H57: =SUMIFS('HVP T12'!C:C,'HVP T12'!$B:$B,'P&Ls Detailed'!$G57) -> 9686.91 | I57: =SUMIFS('HVP T12'!D:D,'HVP T12'!$B:$B,'P&Ls Detailed'!$G57) -> 9686.91 | J57: =SUMIFS('HVP T12'!E:E,'HVP T12'!$B:$B,'P&Ls Detailed'!$G57) -> 9767.99 | K57: =SUMIFS('HVP T12'!F:F,'HVP T12'!$B:$B,'P&Ls Detailed'!$G57) -> 9986.72 | L57: =SUMIFS('HVP T12'!G:G,'HVP T12'!$B:$B,'P&Ls Detailed'!$G57) -> 10168.04 | M57: =SUMIFS('HVP T12'!H:H,'HVP T12'!$B:$B,'P&Ls Detailed'!$G57) -> 10024.09 | N57: =SUMIFS('HVP T12'!I:I,'HVP T12'!$B:$B,'P&Ls Detailed'!$G57) -> 8167.69 | O57: =SUMIFS('HVP T12'!J:J,'HVP T12'!$B:$B,'P&Ls Detailed'!$G57) -> 9191.42 | P57: =SUMIFS('HVP T12'!K:K,'HVP T12'!$B:$B,'P&Ls Detailed'!$G57) -> 8063.15 | Q57: =SUMIFS('HVP T12'!L:L,'HVP T12'!$B:$B,'P&Ls Detailed'!$G57) -> 9184.66 | R57: =SUMIFS('HVP T12'!M:M,'HVP T12'!$B:$B,'P&Ls Detailed'!$G57) -> 9184.64 | S57: =SUMIFS('HVP T12'!N:N,'HVP T12'!$B:$B,'P&Ls Detailed'!$G57) -> 9184.65 | W57: =SUM(H57:S57) -> 112296.87 | X57: =SUM(K57:S57)/9*12 -> 110873.41 | Y57: =SUM(N57:S57)/6*12 -> 105952.42 | Z57: =SUM(Q57:S57)/3*12 -> 110215.8 | AA57: =S57*12 -> 110215.8
D58: =$AB$3 -> Hudson View Park | E58: Personnel | G58: GROUP INSURANCE-SELF INSURED | H58: =SUMIFS('HVP T12'!C:C,'HVP T12'!$B:$B,'P&Ls Detailed'!$G58) -> 655.96 | I58: =SUMIFS('HVP T12'!D:D,'HVP T12'!$B:$B,'P&Ls Detailed'!$G58) -> 572.98 | J58: =SUMIFS('HVP T12'!E:E,'HVP T12'!$B:$B,'P&Ls Detailed'!$G58) -> 1321.05 | K58: =SUMIFS('HVP T12'!F:F,'HVP T12'!$B:$B,'P&Ls Detailed'!$G58) -> 4790.6 | L58: =SUMIFS('HVP T12'!G:G,'HVP T12'!$B:$B,'P&Ls Detailed'!$G58) -> 737.81 | M58: =SUMIFS('HVP T12'!H:H,'HVP T12'!$B:$B,'P&Ls Detailed'!$G58) -> 3008.54 | N58: =SUMIFS('HVP T12'!I:I,'HVP T12'!$B:$B,'P&Ls Detailed'!$G58) -> 3700.62 | O58: =SUMIFS('HVP T12'!J:J,'HVP T12'!$B:$B,'P&Ls Detailed'!$G58) -> 1104.1 | P58: =SUMIFS('HVP T12'!K:K,'HVP T12'!$B:$B,'P&Ls Detailed'!$G58) -> 2830.65 | Q58: =SUMIFS('HVP T12'!L:L,'HVP T12'!$B:$B,'P&Ls Detailed'!$G58) -> 2391.31 | R58: =SUMIFS('HVP T12'!M:M,'HVP T12'!$B:$B,'P&Ls Detailed'!$G58) -> 2208.52 | S58: =SUMIFS('HVP T12'!N:N,'HVP T12'!$B:$B,'P&Ls Detailed'!$G58) -> 3470.79 | W58: =SUM(H58:S58) -> 26792.93 | X58: =SUM(K58:S58)/9*12 -> 32323.92 | Y58: =SUM(N58:S58)/6*12 -> 31411.98 | Z58: =SUM(Q58:S58)/3*12 -> 32282.48 | AA58: =S58*12 -> 41649.48
D59: =$AB$3 -> Hudson View Park | E59: Personnel | G59: PROFIT SHARING | H59: =SUMIFS('HVP T12'!C:C,'HVP T12'!$B:$B,'P&Ls Detailed'!$G59) -> 5960.95 | I59: =SUMIFS('HVP T12'!D:D,'HVP T12'!$B:$B,'P&Ls Detailed'!$G59) -> 5960.95 | J59: =SUMIFS('HVP T12'!E:E,'HVP T12'!$B:$B,'P&Ls Detailed'!$G59) -> 5960.95 | K59: =SUMIFS('HVP T12'!F:F,'HVP T12'!$B:$B,'P&Ls Detailed'!$G59) -> 5960.95 | L59: =SUMIFS('HVP T12'!G:G,'HVP T12'!$B:$B,'P&Ls Detailed'!$G59) -> 5960.95 | M59: =SUMIFS('HVP T12'!H:H,'HVP T12'!$B:$B,'P&Ls Detailed'!$G59) -> 5960.95 | N59: =SUMIFS('HVP T12'!I:I,'HVP T12'!$B:$B,'P&Ls Detailed'!$G59) -> 5960.95 | O59: =SUMIFS('HVP T12'!J:J,'HVP T12'!$B:$B,'P&Ls Detailed'!$G59) -> 25729.95 | P59: =SUMIFS('HVP T12'!K:K,'HVP T12'!$B:$B,'P&Ls Detailed'!$G59) -> 7608.33 | Q59: =SUMIFS('HVP T12'!L:L,'HVP T12'!$B:$B,'P&Ls Detailed'!$G59) -> 7608.33 | R59: =SUMIFS('HVP T12'!M:M,'HVP T12'!$B:$B,'P&Ls Detailed'!$G59) -> 7608.33 | S59: =SUMIFS('HVP T12'!N:N,'HVP T12'!$B:$B,'P&Ls Detailed'!$G59) -> 7608.33 | W59: =SUM(H59:S59) -> 97889.92 | X59: =SUM(K59:S59)/9*12 -> 106676.09 | Y59: =SUM(N59:S59)/6*12 -> 124248.44 | Z59: =SUM(Q59:S59)/3*12 -> 91299.96 | AA59: =S59*12 -> 91299.96
D60: =$AB$3 -> Hudson View Park | E60: Personnel | G60: DEFINED BENEFIT | H60: =SUMIFS('HVP T12'!C:C,'HVP T12'!$B:$B,'P&Ls Detailed'!$G60) -> 2084.25 | I60: =SUMIFS('HVP T12'!D:D,'HVP T12'!$B:$B,'P&Ls Detailed'!$G60) -> 2084.25 | J60: =SUMIFS('HVP T12'!E:E,'HVP T12'!$B:$B,'P&Ls Detailed'!$G60) -> 2084.25 | K60: =SUMIFS('HVP T12'!F:F,'HVP T12'!$B:$B,'P&Ls Detailed'!$G60) -> 2084.25 | L60: =SUMIFS('HVP T12'!G:G,'HVP T12'!$B:$B,'P&Ls Detailed'!$G60) -> 2084.25 | M60: =SUMIFS('HVP T12'!H:H,'HVP T12'!$B:$B,'P&Ls Detailed'!$G60) -> 2084.25 | N60: =SUMIFS('HVP T12'!I:I,'HVP T12'!$B:$B,'P&Ls Detailed'!$G60) -> 2084.25 | O60: =SUMIFS('HVP T12'!J:J,'HVP T12'!$B:$B,'P&Ls Detailed'!$G60) -> -22926.75 | P60: =SUMIFS('HVP T12'!K:K,'HVP T12'!$B:$B,'P&Ls Detailed'!$G60) -> 0 | Q60: =SUMIFS('HVP T12'!L:L,'HVP T12'!$B:$B,'P&Ls Detailed'!$G60) -> 0 | R60: =SUMIFS('HVP T12'!M:M,'HVP T12'!$B:$B,'P&Ls Detailed'!$G60) -> 0 | S60: =SUMIFS('HVP T12'!N:N,'HVP T12'!$B:$B,'P&Ls Detailed'!$G60) -> 0 | W60: =SUM(H60:S60) -> -8337 | X60: =SUM(K60:S60)/9*12 -> -19453 | Y60: =SUM(N60:S60)/6*12 -> -41685 | Z60: =SUM(Q60:S60)/3*12 -> 0 | AA60: =S60*12 -> 0
D61: =$AB$3 -> Hudson View Park | G61: Total PAYROLL AND RELATED | H61: =SUM(H48:H60) -> 105727.21 | I61: =SUM(I48:I60) -> 114841.33 | J61: =SUM(J48:J60) -> 102318.29 | K61: =SUM(K48:K60) -> 145161.48 | L61: =SUM(L48:L60) -> 100560.77 | M61: =SUM(M48:M60) -> 100871.55 | N61: =SUM(N48:N60) -> 101075.66 | O61: =SUM(O48:O60) -> 143541.83 | ... S61: =SUM(S48:S60) -> 104471.29 | W61: =SUM(W48:W60) -> 1381090.5 | X61: =SUM(K61:S61)/9*12 -> 1410938.2 | Y61: =SUM(N61:S61)/6*12 -> 1423219.7 | Z61: =SUM(Q61:S61)/3*12 -> 1289361.5 | AA61: =S61*12 -> 1253655.5
D62: =$AB$3 -> Hudson View Park
D63: =$AB$3 -> Hudson View Park | G63: MAINTENANCE
D64: =$AB$3 -> Hudson View Park | E64: Repairs & Maintenance | G64: BLDG REPAIRS & SUPPLIES | H64: =SUMIFS('HVP T12'!C:C,'HVP T12'!$B:$B,'P&Ls Detailed'!$G64) -> 4605.79 | I64: =SUMIFS('HVP T12'!D:D,'HVP T12'!$B:$B,'P&Ls Detailed'!$G64) -> 8797.19 | J64: =SUMIFS('HVP T12'!E:E,'HVP T12'!$B:$B,'P&Ls Detailed'!$G64) -> 5660.9 | K64: =SUMIFS('HVP T12'!F:F,'HVP T12'!$B:$B,'P&Ls Detailed'!$G64) -> 9728.69 | L64: =SUMIFS('HVP T12'!G:G,'HVP T12'!$B:$B,'P&Ls Detailed'!$G64) -> 5202.54 | M64: =SUMIFS('HVP T12'!H:H,'HVP T12'!$B:$B,'P&Ls Detailed'!$G64) -> 9532.74 | N64: =SUMIFS('HVP T12'!I:I,'HVP T12'!$B:$B,'P&Ls Detailed'!$G64) -> 8719.37 | O64: =SUMIFS('HVP T12'!J:J,'HVP T12'!$B:$B,'P&Ls Detailed'!$G64) -> 1538.73 | P64: =SUMIFS('HVP T12'!K:K,'HVP T12'!$B:$B,'P&Ls Detailed'!$G64) -> 2732.69 | Q64: =SUMIFS('HVP T12'!L:L,'HVP T12'!$B:$B,'P&Ls Detailed'!$G64) -> 8086.16 | R64: =SUMIFS('HVP T12'!M:M,'HVP T12'!$B:$B,'P&Ls Detailed'!$G64) -> 8080.73 | S64: =SUMIFS('HVP T12'!N:N,'HVP T12'!$B:$B,'P&Ls Detailed'!$G64) -> 6946.96 | W64: =SUM(H64:S64) -> 79632.49 | X64: =SUM(K64:S64)/9*12 -> 80758.147 | Y64: =SUM(N64:S64)/6*12 -> 72209.28 | Z64: =SUM(Q64:S64)/3*12 -> 92455.4 | AA64: =S64*12 -> 83363.52
D65: =$AB$3 -> Hudson View Park | E65: Repairs & Maintenance | G65: TOOLS & EQUIP REPAIR | H65: =SUMIFS('HVP T12'!C:C,'HVP T12'!$B:$B,'P&Ls Detailed'!$G65) -> 1970.71 | I65: =SUMIFS('HVP T12'!D:D,'HVP T12'!$B:$B,'P&Ls Detailed'!$G65) -> 1198.64 | J65: =SUMIFS('HVP T12'!E:E,'HVP T12'!$B:$B,'P&Ls Detailed'!$G65) -> 1867.17 | K65: =SUMIFS('HVP T12'!F:F,'HVP T12'!$B:$B,'P&Ls Detailed'!$G65) -> 897.72 | L65: =SUMIFS('HVP T12'!G:G,'HVP T12'!$B:$B,'P&Ls Detailed'!$G65) -> 2221.75 | M65: =SUMIFS('HVP T12'!H:H,'HVP T12'!$B:$B,'P&Ls Detailed'!$G65) -> 1336.86 | N65: =SUMIFS('HVP T12'!I:I,'HVP T12'!$B:$B,'P&Ls Detailed'!$G65) -> 844.23 | O65: =SUMIFS('HVP T12'!J:J,'HVP T12'!$B:$B,'P&Ls Detailed'!$G65) -> 1553.86 | P65: =SUMIFS('HVP T12'!K:K,'HVP T12'!$B:$B,'P&Ls Detailed'!$G65) -> 2109.11 | Q65: =SUMIFS('HVP T12'!L:L,'HVP T12'!$B:$B,'P&Ls Detailed'!$G65) -> 102.49 | R65: =SUMIFS('HVP T12'!M:M,'HVP T12'!$B:$B,'P&Ls Detailed'!$G65) -> 1214.51 | S65: =SUMIFS('HVP T12'!N:N,'HVP T12'!$B:$B,'P&Ls Detailed'!$G65) -> 637.96 | W65: =SUM(H65:S65) -> 15955.01 | X65: =SUM(K65:S65)/9*12 -> 14557.987 | Y65: =SUM(N65:S65)/6*12 -> 12924.32 | Z65: =SUM(Q65:S65)/3*12 -> 7819.84 | AA65: =S65*12 -> 7655.52
D66: =$AB$3 -> Hudson View Park | E66: Repairs & Maintenance | G66: PLMBG & HEATING | H66: =SUMIFS('HVP T12'!C:C,'HVP T12'!$B:$B,'P&Ls Detailed'!$G66) -> 4217.44 | I66: =SUMIFS('HVP T12'!D:D,'HVP T12'!$B:$B,'P&Ls Detailed'!$G66) -> 1840.05 | J66: =SUMIFS('HVP T12'!E:E,'HVP T12'!$B:$B,'P&Ls Detailed'!$G66) -> 2679.7 | K66: =SUMIFS('HVP T12'!F:F,'HVP T12'!$B:$B,'P&Ls Detailed'!$G66) -> 9050.46 | L66: =SUMIFS('HVP T12'!G:G,'HVP T12'!$B:$B,'P&Ls Detailed'!$G66) -> 2772.46 | M66: =SUMIFS('HVP T12'!H:H,'HVP T12'!$B:$B,'P&Ls Detailed'!$G66) -> 5378.36 | N66: =SUMIFS('HVP T12'!I:I,'HVP T12'!$B:$B,'P&Ls Detailed'!$G66) -> 11639.93 | O66: =SUMIFS('HVP T12'!J:J,'HVP T12'!$B:$B,'P&Ls Detailed'!$G66) -> 4694.47 | P66: =SUMIFS('HVP T12'!K:K,'HVP T12'!$B:$B,'P&Ls Detailed'!$G66) -> 1247.98 | Q66: =SUMIFS('HVP T12'!L:L,'HVP T12'!$B:$B,'P&Ls Detailed'!$G66) -> 1004.22 | R66: =SUMIFS('HVP T12'!M:M,'HVP T12'!$B:$B,'P&Ls Detailed'!$G66) -> 2422.58 | S66: =SUMIFS('HVP T12'!N:N,'HVP T12'!$B:$B,'P&Ls Detailed'!$G66) -> 4467.62 | W66: =SUM(H66:S66) -> 51415.27 | X66: =SUM(K66:S66)/9*12 -> 56904.107 | Y66: =SUM(N66:S66)/6*12 -> 50953.6 | Z66: =SUM(Q66:S66)/3*12 -> 31577.68 | AA66: =S66*12 -> 53611.44
D67: =$AB$3 -> Hudson View Park | E67: Repairs & Maintenance | G67: ELECTRICAL | H67: =SUMIFS('HVP T12'!C:C,'HVP T12'!$B:$B,'P&Ls Detailed'!$G67) -> 3013.15 | I67: =SUMIFS('HVP T12'!D:D,'HVP T12'!$B:$B,'P&Ls Detailed'!$G67) -> 2100.41 | J67: =SUMIFS('HVP T12'!E:E,'HVP T12'!$B:$B,'P&Ls Detailed'!$G67) -> 1257.79 | K67: =SUMIFS('HVP T12'!F:F,'HVP T12'!$B:$B,'P&Ls Detailed'!$G67) -> 4593.4 | L67: =SUMIFS('HVP T12'!G:G,'HVP T12'!$B:$B,'P&Ls Detailed'!$G67) -> 4024.39 | M67: =SUMIFS('HVP T12'!H:H,'HVP T12'!$B:$B,'P&Ls Detailed'!$G67) -> 3587.81 | N67: =SUMIFS('HVP T12'!I:I,'HVP T12'!$B:$B,'P&Ls Detailed'!$G67) -> 1647.86 | O67: =SUMIFS('HVP T12'!J:J,'HVP T12'!$B:$B,'P&Ls Detailed'!$G67) -> 817.87 | P67: =SUMIFS('HVP T12'!K:K,'HVP T12'!$B:$B,'P&Ls Detailed'!$G67) -> 1940.91 | Q67: =SUMIFS('HVP T12'!L:L,'HVP T12'!$B:$B,'P&Ls Detailed'!$G67) -> 5061.12 | R67: =SUMIFS('HVP T12'!M:M,'HVP T12'!$B:$B,'P&Ls Detailed'!$G67) -> 748.69 | S67: =SUMIFS('HVP T12'!N:N,'HVP T12'!$B:$B,'P&Ls Detailed'!$G67) -> 612.75 | W67: =SUM(H67:S67) -> 29406.15 | X67: =SUM(K67:S67)/9*12 -> 30713.067 | Y67: =SUM(N67:S67)/6*12 -> 21658.4 | Z67: =SUM(Q67:S67)/3*12 -> 25690.24 | AA67: =S67*12 -> 7353
D68: =$AB$3 -> Hudson View Park | E68: Repairs & Maintenance | G68: PAINTING | H68: =SUMIFS('HVP T12'!C:C,'HVP T12'!$B:$B,'P&Ls Detailed'!$G68) -> 6764.01 | I68: =SUMIFS('HVP T12'!D:D,'HVP T12'!$B:$B,'P&Ls Detailed'!$G68) -> 8709.75 | J68: =SUMIFS('HVP T12'!E:E,'HVP T12'!$B:$B,'P&Ls Detailed'!$G68) -> 5958.33 | K68: =SUMIFS('HVP T12'!F:F,'HVP T12'!$B:$B,'P&Ls Detailed'!$G68) -> 14893.49 | L68: =SUMIFS('HVP T12'!G:G,'HVP T12'!$B:$B,'P&Ls Detailed'!$G68) -> 6358.35 | M68: =SUMIFS('HVP T12'!H:H,'HVP T12'!$B:$B,'P&Ls Detailed'!$G68) -> 10814.8 | N68: =SUMIFS('HVP T12'!I:I,'HVP T12'!$B:$B,'P&Ls Detailed'!$G68) -> 8603.67 | O68: =SUMIFS('HVP T12'!J:J,'HVP T12'!$B:$B,'P&Ls Detailed'!$G68) -> 13815.98 | P68: =SUMIFS('HVP T12'!K:K,'HVP T12'!$B:$B,'P&Ls Detailed'!$G68) -> 11616.19 | Q68: =SUMIFS('HVP T12'!L:L,'HVP T12'!$B:$B,'P&Ls Detailed'!$G68) -> 6051.79 | R68: =SUMIFS('HVP T12'!M:M,'HVP T12'!$B:$B,'P&Ls Detailed'!$G68) -> 6286.6 | S68: =SUMIFS('HVP T12'!N:N,'HVP T12'!$B:$B,'P&Ls Detailed'!$G68) -> 9831.38 | W68: =SUM(H68:S68) -> 109704.34 | X68: =SUM(K68:S68)/9*12 -> 117696.33 | Y68: =SUM(N68:S68)/6*12 -> 112411.22 | Z68: =SUM(Q68:S68)/3*12 -> 88679.08 | AA68: =S68*12 -> 117976.56
D69: =$AB$3 -> Hudson View Park | E69: Repairs & Maintenance | G69: CLEANING | H69: =SUMIFS('HVP T12'!C:C,'HVP T12'!$B:$B,'P&Ls Detailed'!$G69) -> 7517.57 | I69: =SUMIFS('HVP T12'!D:D,'HVP T12'!$B:$B,'P&Ls Detailed'!$G69) -> 9005.97 | J69: =SUMIFS('HVP T12'!E:E,'HVP T12'!$B:$B,'P&Ls Detailed'!$G69) -> 9409.96 | K69: =SUMIFS('HVP T12'!F:F,'HVP T12'!$B:$B,'P&Ls Detailed'!$G69) -> 7408.45 | L69: =SUMIFS('HVP T12'!G:G,'HVP T12'!$B:$B,'P&Ls Detailed'!$G69) -> 8039.33 | M69: =SUMIFS('HVP T12'!H:H,'HVP T12'!$B:$B,'P&Ls Detailed'!$G69) -> 10615.19 | N69: =SUMIFS('HVP T12'!I:I,'HVP T12'!$B:$B,'P&Ls Detailed'!$G69) -> 7524.24 | O69: =SUMIFS('HVP T12'!J:J,'HVP T12'!$B:$B,'P&Ls Detailed'!$G69) -> 7302 | P69: =SUMIFS('HVP T12'!K:K,'HVP T12'!$B:$B,'P&Ls Detailed'!$G69) -> 6554.21 | Q69: =SUMIFS('HVP T12'!L:L,'HVP T12'!$B:$B,'P&Ls Detailed'!$G69) -> 7726.46 | R69: =SUMIFS('HVP T12'!M:M,'HVP T12'!$B:$B,'P&Ls Detailed'!$G69) -> 6878.72 | S69: =SUMIFS('HVP T12'!N:N,'HVP T12'!$B:$B,'P&Ls Detailed'!$G69) -> 6579.1 | W69: =SUM(H69:S69) -> 94561.2 | X69: =SUM(K69:S69)/9*12 -> 91503.6 | Y69: =SUM(N69:S69)/6*12 -> 85129.46 | Z69: =SUM(Q69:S69)/3*12 -> 84737.12 | AA69: =S69*12 -> 78949.2
D70: =$AB$3 -> Hudson View Park | E70: Repairs & Maintenance | G70: POOL SUPPLIES | H70: =SUMIFS('HVP T12'!C:C,'HVP T12'!$B:$B,'P&Ls Detailed'!$G70) -> 2711.69 | I70: =SUMIFS('HVP T12'!D:D,'HVP T12'!$B:$B,'P&Ls Detailed'!$G70) -> 950.42 | J70: =SUMIFS('HVP T12'!E:E,'HVP T12'!$B:$B,'P&Ls Detailed'!$G70) -> 106.86 | K70: =SUMIFS('HVP T12'!F:F,'HVP T12'!$B:$B,'P&Ls Detailed'!$G70) -> 177.81 | L70: =SUMIFS('HVP T12'!G:G,'HVP T12'!$B:$B,'P&Ls Detailed'!$G70) -> 0 | M70: =SUMIFS('HVP T12'!H:H,'HVP T12'!$B:$B,'P&Ls Detailed'!$G70) -> 0 | N70: =SUMIFS('HVP T12'!I:I,'HVP T12'!$B:$B,'P&Ls Detailed'!$G70) -> 0 | O70: =SUMIFS('HVP T12'!J:J,'HVP T12'!$B:$B,'P&Ls Detailed'!$G70) -> 0 | P70: =SUMIFS('HVP T12'!K:K,'HVP T12'!$B:$B,'P&Ls Detailed'!$G70) -> 328 | Q70: =SUMIFS('HVP T12'!L:L,'HVP T12'!$B:$B,'P&Ls Detailed'!$G70) -> 0 | R70: =SUMIFS('HVP T12'!M:M,'HVP T12'!$B:$B,'P&Ls Detailed'!$G70) -> 0 | S70: =SUMIFS('HVP T12'!N:N,'HVP T12'!$B:$B,'P&Ls Detailed'!$G70) -> 0 | W70: =SUM(H70:S70) -> 4274.78 | X70: =SUM(K70:S70)/9*12 -> 674.41333 | Y70: =SUM(N70:S70)/6*12 -> 656 | Z70: =SUM(Q70:S70)/3*12 -> 0 | AA70: =S70*12 -> 0
D71: =$AB$3 -> Hudson View Park | E71: Repairs & Maintenance | G71: POOL MAINT | H71: =SUMIFS('HVP T12'!C:C,'HVP T12'!$B:$B,'P&Ls Detailed'!$G71) -> 8622.54 | I71: =SUMIFS('HVP T12'!D:D,'HVP T12'!$B:$B,'P&Ls Detailed'!$G71) -> 7312.54 | J71: =SUMIFS('HVP T12'!E:E,'HVP T12'!$B:$B,'P&Ls Detailed'!$G71) -> 7312.54 | K71: =SUMIFS('HVP T12'!F:F,'HVP T12'!$B:$B,'P&Ls Detailed'!$G71) -> 7312.54 | L71: =SUMIFS('HVP T12'!G:G,'HVP T12'!$B:$B,'P&Ls Detailed'!$G71) -> 1828.14 | M71: =SUMIFS('HVP T12'!H:H,'HVP T12'!$B:$B,'P&Ls Detailed'!$G71) -> 0 | N71: =SUMIFS('HVP T12'!I:I,'HVP T12'!$B:$B,'P&Ls Detailed'!$G71) -> 0 | O71: =SUMIFS('HVP T12'!J:J,'HVP T12'!$B:$B,'P&Ls Detailed'!$G71) -> 0 | P71: =SUMIFS('HVP T12'!K:K,'HVP T12'!$B:$B,'P&Ls Detailed'!$G71) -> 0 | Q71: =SUMIFS('HVP T12'!L:L,'HVP T12'!$B:$B,'P&Ls Detailed'!$G71) -> 0 | R71: =SUMIFS('HVP T12'!M:M,'HVP T12'!$B:$B,'P&Ls Detailed'!$G71) -> 0 | S71: =SUMIFS('HVP T12'!N:N,'HVP T12'!$B:$B,'P&Ls Detailed'!$G71) -> 5713.27 | W71: =SUM(H71:S71) -> 38101.57 | X71: =SUM(K71:S71)/9*12 -> 19805.267 | Y71: =SUM(N71:S71)/6*12 -> 11426.54 | Z71: =SUM(Q71:S71)/3*12 -> 22853.08 | AA71: =S71*12 -> 68559.24
D72: =$AB$3 -> Hudson View Park | E72: Repairs & Maintenance | G72: VEHICLES EXPENSE | H72: =SUMIFS('HVP T12'!C:C,'HVP T12'!$B:$B,'P&Ls Detailed'!$G72) -> 14340.37 | I72: =SUMIFS('HVP T12'!D:D,'HVP T12'!$B:$B,'P&Ls Detailed'!$G72) -> 1572.27 | J72: =SUMIFS('HVP T12'!E:E,'HVP T12'!$B:$B,'P&Ls Detailed'!$G72) -> 3005.59 | K72: =SUMIFS('HVP T12'!F:F,'HVP T12'!$B:$B,'P&Ls Detailed'!$G72) -> 4772.61 | L72: =SUMIFS('HVP T12'!G:G,'HVP T12'!$B:$B,'P&Ls Detailed'!$G72) -> 2940.51 | M72: =SUMIFS('HVP T12'!H:H,'HVP T12'!$B:$B,'P&Ls Detailed'!$G72) -> 8863.22 | N72: =SUMIFS('HVP T12'!I:I,'HVP T12'!$B:$B,'P&Ls Detailed'!$G72) -> 6362.8 | O72: =SUMIFS('HVP T12'!J:J,'HVP T12'!$B:$B,'P&Ls Detailed'!$G72) -> 18229.29 | P72: =SUMIFS('HVP T12'!K:K,'HVP T12'!$B:$B,'P&Ls Detailed'!$G72) -> 1279.47 | Q72: =SUMIFS('HVP T12'!L:L,'HVP T12'!$B:$B,'P&Ls Detailed'!$G72) -> 2816.14 | R72: =SUMIFS('HVP T12'!M:M,'HVP T12'!$B:$B,'P&Ls Detailed'!$G72) -> 5368.49 | S72: =SUMIFS('HVP T12'!N:N,'HVP T12'!$B:$B,'P&Ls Detailed'!$G72) -> 3126.39 | W72: =SUM(H72:S72) -> 72677.15 | X72: =SUM(K72:S72)/9*12 -> 71678.56 | Y72: =SUM(N72:S72)/6*12 -> 74365.16 | Z72: =SUM(Q72:S72)/3*12 -> 45244.08 | AA72: =S72*12 -> 37516.68
D73: =$AB$3 -> Hudson View Park | E73: Contract Services | G73: LANDSCAPING | H73: =SUMIFS('HVP T12'!C:C,'HVP T12'!$B:$B,'P&Ls Detailed'!$G73) -> 6562.65 | I73: =SUMIFS('HVP T12'!D:D,'HVP T12'!$B:$B,'P&Ls Detailed'!$G73) -> 6598.33 | J73: =SUMIFS('HVP T12'!E:E,'HVP T12'!$B:$B,'P&Ls Detailed'!$G73) -> 33514.49 | K73: =SUMIFS('HVP T12'!F:F,'HVP T12'!$B:$B,'P&Ls Detailed'!$G73) -> 31373.78 | L73: =SUMIFS('HVP T12'!G:G,'HVP T12'!$B:$B,'P&Ls Detailed'!$G73) -> 6148.27 | M73: =SUMIFS('HVP T12'!H:H,'HVP T12'!$B:$B,'P&Ls Detailed'!$G73) -> 28299.74 | N73: =SUMIFS('HVP T12'!I:I,'HVP T12'!$B:$B,'P&Ls Detailed'!$G73) -> 10308.37 | O73: =SUMIFS('HVP T12'!J:J,'HVP T12'!$B:$B,'P&Ls Detailed'!$G73) -> 439.88 | P73: =SUMIFS('HVP T12'!K:K,'HVP T12'!$B:$B,'P&Ls Detailed'!$G73) -> 710.38 | Q73: =SUMIFS('HVP T12'!L:L,'HVP T12'!$B:$B,'P&Ls Detailed'!$G73) -> 1218.25 | R73: =SUMIFS('HVP T12'!M:M,'HVP T12'!$B:$B,'P&Ls Detailed'!$G73) -> 2721.85 | S73: =SUMIFS('HVP T12'!N:N,'HVP T12'!$B:$B,'P&Ls Detailed'!$G73) -> 7454.08 | W73: =SUM(H73:S73) -> 135350.07 | X73: =SUM(K73:S73)/9*12 -> 118232.8 | Y73: =SUM(N73:S73)/6*12 -> 45705.62 | Z73: =SUM(Q73:S73)/3*12 -> 45576.72 | AA73: =S73*12 -> 89448.96
D74: =$AB$3 -> Hudson View Park | E74: Contract Services | G74: SNOW REMOVAL | H74: =SUMIFS('HVP T12'!C:C,'HVP T12'!$B:$B,'P&Ls Detailed'!$G74) -> 25.94 | I74: =SUMIFS('HVP T12'!D:D,'HVP T12'!$B:$B,'P&Ls Detailed'!$G74) -> 0 | J74: =SUMIFS('HVP T12'!E:E,'HVP T12'!$B:$B,'P&Ls Detailed'!$G74) -> 0 | K74: =SUMIFS('HVP T12'!F:F,'HVP T12'!$B:$B,'P&Ls Detailed'!$G74) -> 0 | L74: =SUMIFS('HVP T12'!G:G,'HVP T12'!$B:$B,'P&Ls Detailed'!$G74) -> 0 | M74: =SUMIFS('HVP T12'!H:H,'HVP T12'!$B:$B,'P&Ls Detailed'!$G74) -> 844.38 | N74: =SUMIFS('HVP T12'!I:I,'HVP T12'!$B:$B,'P&Ls Detailed'!$G74) -> 0 | O74: =SUMIFS('HVP T12'!J:J,'HVP T12'!$B:$B,'P&Ls Detailed'!$G74) -> 0 | P74: =SUMIFS('HVP T12'!K:K,'HVP T12'!$B:$B,'P&Ls Detailed'!$G74) -> 8959.83 | Q74: =SUMIFS('HVP T12'!L:L,'HVP T12'!$B:$B,'P&Ls Detailed'!$G74) -> 0 | R74: =SUMIFS('HVP T12'!M:M,'HVP T12'!$B:$B,'P&Ls Detailed'!$G74) -> 0 | S74: =SUMIFS('HVP T12'!N:N,'HVP T12'!$B:$B,'P&Ls Detailed'!$G74) -> -10.81 | W74: =SUM(H74:S74) -> 9819.34 | X74: =SUM(K74:S74)/9*12 -> 13057.867 | Y74: =SUM(N74:S74)/6*12 -> 17898.04 | Z74: =SUM(Q74:S74)/3*12 -> -43.24 | AA74: =S74*12 -> -129.72
D75: =$AB$3 -> Hudson View Park | E75: Repairs & Maintenance | G75: CARPET REPAIR | H75: =SUMIFS('HVP T12'!C:C,'HVP T12'!$B:$B,'P&Ls Detailed'!$G75) -> 0 | I75: =SUMIFS('HVP T12'!D:D,'HVP T12'!$B:$B,'P&Ls Detailed'!$G75) -> 0 | J75: =SUMIFS('HVP T12'!E:E,'HVP T12'!$B:$B,'P&Ls Detailed'!$G75) -> 162.18 | K75: =SUMIFS('HVP T12'!F:F,'HVP T12'!$B:$B,'P&Ls Detailed'!$G75) -> 0 | L75: =SUMIFS('HVP T12'!G:G,'HVP T12'!$B:$B,'P&Ls Detailed'!$G75) -> 0 | M75: =SUMIFS('HVP T12'!H:H,'HVP T12'!$B:$B,'P&Ls Detailed'!$G75) -> 0 | N75: =SUMIFS('HVP T12'!I:I,'HVP T12'!$B:$B,'P&Ls Detailed'!$G75) -> 0 | O75: =SUMIFS('HVP T12'!J:J,'HVP T12'!$B:$B,'P&Ls Detailed'!$G75) -> 0 | P75: =SUMIFS('HVP T12'!K:K,'HVP T12'!$B:$B,'P&Ls Detailed'!$G75) -> 0 | Q75: =SUMIFS('HVP T12'!L:L,'HVP T12'!$B:$B,'P&Ls Detailed'!$G75) -> 81.09 | R75: =SUMIFS('HVP T12'!M:M,'HVP T12'!$B:$B,'P&Ls Detailed'!$G75) -> 0 | S75: =SUMIFS('HVP T12'!N:N,'HVP T12'!$B:$B,'P&Ls Detailed'!$G75) -> 0 | W75: =SUM(H75:S75) -> 243.27 | X75: =SUM(K75:S75)/9*12 -> 108.12 | Y75: =SUM(N75:S75)/6*12 -> 162.18 | Z75: =SUM(Q75:S75)/3*12 -> 324.36 | AA75: =S75*12 -> 0
... D80: =$AB$3 -> Hudson View Park | E80: General & Administrative | G80: OPERATING LICENSES & PERMITS HVP | H80: =SUMIFS('HVP T12'!C:C,'HVP T12'!$B:$B,'P&Ls Detailed'!$G80) -> 0 | I80: =SUMIFS('HVP T12'!D:D,'HVP T12'!$B:$B,'P&Ls Detailed'!$G80) -> 3450 | J80: =SUMIFS('HVP T12'!E:E,'HVP T12'!$B:$B,'P&Ls Detailed'!$G80) -> 0 | K80: =SUMIFS('HVP T12'!F:F,'HVP T12'!$B:$B,'P&Ls Detailed'!$G80) -> 25 | L80: =SUMIFS('HVP T12'!G:G,'HVP T12'!$B:$B,'P&Ls Detailed'!$G80) -> 250 | M80: =SUMIFS('HVP T12'!H:H,'HVP T12'!$B:$B,'P&Ls Detailed'!$G80) -> 0 | N80: =SUMIFS('HVP T12'!I:I,'HVP T12'!$B:$B,'P&Ls Detailed'!$G80) -> 0 | O80: =SUMIFS('HVP T12'!J:J,'HVP T12'!$B:$B,'P&Ls Detailed'!$G80) -> 0 | P80: =SUMIFS('HVP T12'!K:K,'HVP T12'!$B:$B,'P&Ls Detailed'!$G80) -> 0 | Q80: =SUMIFS('HVP T12'!L:L,'HVP T12'!$B:$B,'P&Ls Detailed'!$G80) -> 0 | R80: =SUMIFS('HVP T12'!M:M,'HVP T12'!$B:$B,'P&Ls Detailed'!$G80) -> 0 | S80: =SUMIFS('HVP T12'!N:N,'HVP T12'!$B:$B,'P&Ls Detailed'!$G80) -> 0 | W80: =SUM(H80:S80) -> 3725 | X80: =SUM(K80:S80)/9*12 -> 366.66667 | Y80: =SUM(N80:S80)/6*12 -> 0 | Z80: =SUM(Q80:S80)/3*12 -> 0 | AA80: =S80*12 -> 0
D81: =$AB$3 -> Hudson View Park | G81: Total MAINTENANCE | H81: =SUM(H64:H80) -> 109092.1 | I81: =SUM(I64:I80) -> 94353.18 | J81: =SUM(J64:J80) -> 119278.93 | K81: =SUM(K64:K80) -> 133772.12 | L81: =SUM(L64:L80) -> 82047.85 | M81: =SUM(M64:M80) -> 123768.37 | N81: =SUM(N64:N80) -> 99883.61 | O81: =SUM(O64:O80) -> 91879.02 | ... S81: =SUM(S64:S80) -> 88233.24 | W81: =SUM(W64:W80) -> 1179306.6 | X81: =SUM(K81:S81)/9*12 -> 1142109.8 | Y81: =SUM(N81:S81)/6*12 -> 1033988.1 | Z81: =SUM(Q81:S81)/3*12 -> 978404.08 | AA81: =S81*12 -> 1058798.9
D82: =$AB$3 -> Hudson View Park | G82: ADMIN & GENERAL
D83: =$AB$3 -> Hudson View Park | E83: General & Administrative | G83: PROFESSIONAL SER | H83: =SUMIFS('HVP T12'!C:C,'HVP T12'!$B:$B,'P&Ls Detailed'!$G83) -> 1326 | I83: =SUMIFS('HVP T12'!D:D,'HVP T12'!$B:$B,'P&Ls Detailed'!$G83) -> 0 | J83: =SUMIFS('HVP T12'!E:E,'HVP T12'!$B:$B,'P&Ls Detailed'!$G83) -> 0 | K83: =SUMIFS('HVP T12'!F:F,'HVP T12'!$B:$B,'P&Ls Detailed'!$G83) -> 0 | L83: =SUMIFS('HVP T12'!G:G,'HVP T12'!$B:$B,'P&Ls Detailed'!$G83) -> 0 | M83: =SUMIFS('HVP T12'!H:H,'HVP T12'!$B:$B,'P&Ls Detailed'!$G83) -> 0 | N83: =SUMIFS('HVP T12'!I:I,'HVP T12'!$B:$B,'P&Ls Detailed'!$G83) -> 0 | O83: =SUMIFS('HVP T12'!J:J,'HVP T12'!$B:$B,'P&Ls Detailed'!$G83) -> 0 | P83: =SUMIFS('HVP T12'!K:K,'HVP T12'!$B:$B,'P&Ls Detailed'!$G83) -> 6758.7 | Q83: =SUMIFS('HVP T12'!L:L,'HVP T12'!$B:$B,'P&Ls Detailed'!$G83) -> 0 | R83: =SUMIFS('HVP T12'!M:M,'HVP T12'!$B:$B,'P&Ls Detailed'!$G83) -> 0 | S83: =SUMIFS('HVP T12'!N:N,'HVP T12'!$B:$B,'P&Ls Detailed'!$G83) -> 0 | W83: =SUM(H83:S83) -> 8084.7 | X83: =SUM(K83:S83)/9*12 -> 9011.6 | Y83: =SUM(N83:S83)/6*12 -> 13517.4 | Z83: =SUM(Q83:S83)/3*12 -> 0 | AA83: =S83*12 -> 0
D84: =$AB$3 -> Hudson View Park | E84: General & Administrative | G84: TELEPHONE | H84: =SUMIFS('HVP T12'!C:C,'HVP T12'!$B:$B,'P&Ls Detailed'!$G84) -> 1841.47 | I84: =SUMIFS('HVP T12'!D:D,'HVP T12'!$B:$B,'P&Ls Detailed'!$G84) -> 1833.62 | J84: =SUMIFS('HVP T12'!E:E,'HVP T12'!$B:$B,'P&Ls Detailed'!$G84) -> 1711.14 | K84: =SUMIFS('HVP T12'!F:F,'HVP T12'!$B:$B,'P&Ls Detailed'!$G84) -> 1929.38 | L84: =SUMIFS('HVP T12'!G:G,'HVP T12'!$B:$B,'P&Ls Detailed'!$G84) -> 1843.62 | M84: =SUMIFS('HVP T12'!H:H,'HVP T12'!$B:$B,'P&Ls Detailed'!$G84) -> 1759.22 | N84: =SUMIFS('HVP T12'!I:I,'HVP T12'!$B:$B,'P&Ls Detailed'!$G84) -> 1804.66 | O84: =SUMIFS('HVP T12'!J:J,'HVP T12'!$B:$B,'P&Ls Detailed'!$G84) -> 2348.55 | P84: =SUMIFS('HVP T12'!K:K,'HVP T12'!$B:$B,'P&Ls Detailed'!$G84) -> 1334.94 | Q84: =SUMIFS('HVP T12'!L:L,'HVP T12'!$B:$B,'P&Ls Detailed'!$G84) -> 1810.5 | R84: =SUMIFS('HVP T12'!M:M,'HVP T12'!$B:$B,'P&Ls Detailed'!$G84) -> 1842.67 | S84: =SUMIFS('HVP T12'!N:N,'HVP T12'!$B:$B,'P&Ls Detailed'!$G84) -> 1916.86 | W84: =SUM(H84:S84) -> 21976.63 | X84: =SUM(K84:S84)/9*12 -> 22120.533 | Y84: =SUM(N84:S84)/6*12 -> 22116.36 | Z84: =SUM(Q84:S84)/3*12 -> 22280.12 | AA84: =S84*12 -> 23002.32
D85: =$AB$3 -> Hudson View Park | E85: General & Administrative | G85: CHARITABLE CONTRIBUTIONS | H85: =SUMIFS('HVP T12'!C:C,'HVP T12'!$B:$B,'P&Ls Detailed'!$G85) -> 530 | I85: =SUMIFS('HVP T12'!D:D,'HVP T12'!$B:$B,'P&Ls Detailed'!$G85) -> 7500 | J85: =SUMIFS('HVP T12'!E:E,'HVP T12'!$B:$B,'P&Ls Detailed'!$G85) -> 1500 | K85: =SUMIFS('HVP T12'!F:F,'HVP T12'!$B:$B,'P&Ls Detailed'!$G85) -> 2463.29 | L85: =SUMIFS('HVP T12'!G:G,'HVP T12'!$B:$B,'P&Ls Detailed'!$G85) -> 3500 | M85: =SUMIFS('HVP T12'!H:H,'HVP T12'!$B:$B,'P&Ls Detailed'!$G85) -> 6000 | N85: =SUMIFS('HVP T12'!I:I,'HVP T12'!$B:$B,'P&Ls Detailed'!$G85) -> 0 | O85: =SUMIFS('HVP T12'!J:J,'HVP T12'!$B:$B,'P&Ls Detailed'!$G85) -> 0 | P85: =SUMIFS('HVP T12'!K:K,'HVP T12'!$B:$B,'P&Ls Detailed'!$G85) -> 0 | Q85: =SUMIFS('HVP T12'!L:L,'HVP T12'!$B:$B,'P&Ls Detailed'!$G85) -> 0 | R85: =SUMIFS('HVP T12'!M:M,'HVP T12'!$B:$B,'P&Ls Detailed'!$G85) -> 12950 | S85: =SUMIFS('HVP T12'!N:N,'HVP T12'!$B:$B,'P&Ls Detailed'!$G85) -> 3530 | W85: =SUM(H85:S85) -> 37973.29 | X85: =SUM(K85:S85)/9*12 -> 37924.387 | Y85: =SUM(N85:S85)/6*12 -> 32960 | Z85: =SUM(Q85:S85)/3*12 -> 65920 | AA85: =S85*12 -> 42360
D86: =$AB$3 -> Hudson View Park | E86: General & Administrative | G86: ACCOUNTING | H86: =SUMIFS('HVP T12'!C:C,'HVP T12'!$B:$B,'P&Ls Detailed'!$G86) -> 0 | I86: =SUMIFS('HVP T12'!D:D,'HVP T12'!$B:$B,'P&Ls Detailed'!$G86) -> 0 | J86: =SUMIFS('HVP T12'!E:E,'HVP T12'!$B:$B,'P&Ls Detailed'!$G86) -> 0 | K86: =SUMIFS('HVP T12'!F:F,'HVP T12'!$B:$B,'P&Ls Detailed'!$G86) -> 0 | L86: =SUMIFS('HVP T12'!G:G,'HVP T12'!$B:$B,'P&Ls Detailed'!$G86) -> 4000 | M86: =SUMIFS('HVP T12'!H:H,'HVP T12'!$B:$B,'P&Ls Detailed'!$G86) -> 0 | N86: =SUMIFS('HVP T12'!I:I,'HVP T12'!$B:$B,'P&Ls Detailed'!$G86) -> 0 | O86: =SUMIFS('HVP T12'!J:J,'HVP T12'!$B:$B,'P&Ls Detailed'!$G86) -> 0 | P86: =SUMIFS('HVP T12'!K:K,'HVP T12'!$B:$B,'P&Ls Detailed'!$G86) -> 0 | Q86: =SUMIFS('HVP T12'!L:L,'HVP T12'!$B:$B,'P&Ls Detailed'!$G86) -> 0 | R86: =SUMIFS('HVP T12'!M:M,'HVP T12'!$B:$B,'P&Ls Detailed'!$G86) -> 0 | S86: =SUMIFS('HVP T12'!N:N,'HVP T12'!$B:$B,'P&Ls Detailed'!$G86) -> 0 | W86: =SUM(H86:S86) -> 4000 | X86: =SUM(K86:S86)/9*12 -> 5333.3333 | Y86: =SUM(N86:S86)/6*12 -> 0 | Z86: =SUM(Q86:S86)/3*12 -> 0 | AA86: =S86*12 -> 0
D87: =$AB$3 -> Hudson View Park | E87: General & Administrative | G87: NYS FRANC TAX | H87: =SUMIFS('HVP T12'!C:C,'HVP T12'!$B:$B,'P&Ls Detailed'!$G87) -> 0 | I87: =SUMIFS('HVP T12'!D:D,'HVP T12'!$B:$B,'P&Ls Detailed'!$G87) -> 0 | J87: =SUMIFS('HVP T12'!E:E,'HVP T12'!$B:$B,'P&Ls Detailed'!$G87) -> 0 | K87: =SUMIFS('HVP T12'!F:F,'HVP T12'!$B:$B,'P&Ls Detailed'!$G87) -> 0 | L87: =SUMIFS('HVP T12'!G:G,'HVP T12'!$B:$B,'P&Ls Detailed'!$G87) -> 0 | M87: =SUMIFS('HVP T12'!H:H,'HVP T12'!$B:$B,'P&Ls Detailed'!$G87) -> 0 | N87: =SUMIFS('HVP T12'!I:I,'HVP T12'!$B:$B,'P&Ls Detailed'!$G87) -> 0 | O87: =SUMIFS('HVP T12'!J:J,'HVP T12'!$B:$B,'P&Ls Detailed'!$G87) -> 0 | P87: =SUMIFS('HVP T12'!K:K,'HVP T12'!$B:$B,'P&Ls Detailed'!$G87) -> 0 | Q87: =SUMIFS('HVP T12'!L:L,'HVP T12'!$B:$B,'P&Ls Detailed'!$G87) -> 0 | R87: =SUMIFS('HVP T12'!M:M,'HVP T12'!$B:$B,'P&Ls Detailed'!$G87) -> 25 | S87: =SUMIFS('HVP T12'!N:N,'HVP T12'!$B:$B,'P&Ls Detailed'!$G87) -> 0 | W87: =SUM(H87:S87) -> 25 | X87: =SUM(K87:S87)/9*12 -> 33.333333 | Y87: =SUM(N87:S87)/6*12 -> 50 | Z87: =SUM(Q87:S87)/3*12 -> 100 | AA87: =S87*12 -> 0
D88: =$AB$3 -> Hudson View Park | E88: General & Administrative | G88: LEGAL | H88: =SUMIFS('HVP T12'!C:C,'HVP T12'!$B:$B,'P&Ls Detailed'!$G88) -> 0 | I88: =SUMIFS('HVP T12'!D:D,'HVP T12'!$B:$B,'P&Ls Detailed'!$G88) -> 0 | J88: =SUMIFS('HVP T12'!E:E,'HVP T12'!$B:$B,'P&Ls Detailed'!$G88) -> 700.54 | K88: =SUMIFS('HVP T12'!F:F,'HVP T12'!$B:$B,'P&Ls Detailed'!$G88) -> 0 | L88: =SUMIFS('HVP T12'!G:G,'HVP T12'!$B:$B,'P&Ls Detailed'!$G88) -> 0 | M88: =SUMIFS('HVP T12'!H:H,'HVP T12'!$B:$B,'P&Ls Detailed'!$G88) -> 0 | N88: =SUMIFS('HVP T12'!I:I,'HVP T12'!$B:$B,'P&Ls Detailed'!$G88) -> 0 | O88: =SUMIFS('HVP T12'!J:J,'HVP T12'!$B:$B,'P&Ls Detailed'!$G88) -> 2441.4 | P88: =SUMIFS('HVP T12'!K:K,'HVP T12'!$B:$B,'P&Ls Detailed'!$G88) -> 0 | Q88: =SUMIFS('HVP T12'!L:L,'HVP T12'!$B:$B,'P&Ls Detailed'!$G88) -> 0 | R88: =SUMIFS('HVP T12'!M:M,'HVP T12'!$B:$B,'P&Ls Detailed'!$G88) -> 357.5 | S88: =SUMIFS('HVP T12'!N:N,'HVP T12'!$B:$B,'P&Ls Detailed'!$G88) -> 0 | W88: =SUM(H88:S88) -> 3499.44 | X88: =SUM(K88:S88)/9*12 -> 3731.8667 | Y88: =SUM(N88:S88)/6*12 -> 5597.8 | Z88: =SUM(Q88:S88)/3*12 -> 1430 | AA88: =S88*12 -> 0
D89: =$AB$3 -> Hudson View Park | E89: General & Administrative | G89: OFFICE EXP | H89: =SUMIFS('HVP T12'!C:C,'HVP T12'!$B:$B,'P&Ls Detailed'!$G89) -> 2567.72 | I89: =SUMIFS('HVP T12'!D:D,'HVP T12'!$B:$B,'P&Ls Detailed'!$G89) -> 2223.03 | J89: =SUMIFS('HVP T12'!E:E,'HVP T12'!$B:$B,'P&Ls Detailed'!$G89) -> 3593.01 | K89: =SUMIFS('HVP T12'!F:F,'HVP T12'!$B:$B,'P&Ls Detailed'!$G89) -> 1946.61 | L89: =SUMIFS('HVP T12'!G:G,'HVP T12'!$B:$B,'P&Ls Detailed'!$G89) -> 2861.59 | M89: =SUMIFS('HVP T12'!H:H,'HVP T12'!$B:$B,'P&Ls Detailed'!$G89) -> 3032.01 | N89: =SUMIFS('HVP T12'!I:I,'HVP T12'!$B:$B,'P&Ls Detailed'!$G89) -> 4702.87 | O89: =SUMIFS('HVP T12'!J:J,'HVP T12'!$B:$B,'P&Ls Detailed'!$G89) -> 3413.74 | P89: =SUMIFS('HVP T12'!K:K,'HVP T12'!$B:$B,'P&Ls Detailed'!$G89) -> 3015.06 | Q89: =SUMIFS('HVP T12'!L:L,'HVP T12'!$B:$B,'P&Ls Detailed'!$G89) -> 2696.93 | R89: =SUMIFS('HVP T12'!M:M,'HVP T12'!$B:$B,'P&Ls Detailed'!$G89) -> 3098.09 | S89: =SUMIFS('HVP T12'!N:N,'HVP T12'!$B:$B,'P&Ls Detailed'!$G89) -> 2454.53 | W89: =SUM(H89:S89) -> 35605.19 | X89: =SUM(K89:S89)/9*12 -> 36295.24 | Y89: =SUM(N89:S89)/6*12 -> 38762.44 | Z89: =SUM(Q89:S89)/3*12 -> 32998.2 | AA89: =S89*12 -> 29454.36
D90: =$AB$3 -> Hudson View Park | E90: General & Administrative | G90: SUPPLIES | H90: =SUMIFS('HVP T12'!C:C,'HVP T12'!$B:$B,'P&Ls Detailed'!$G90) -> 3119.94 | I90: =SUMIFS('HVP T12'!D:D,'HVP T12'!$B:$B,'P&Ls Detailed'!$G90) -> 3262.47 | J90: =SUMIFS('HVP T12'!E:E,'HVP T12'!$B:$B,'P&Ls Detailed'!$G90) -> 10250.44 | K90: =SUMIFS('HVP T12'!F:F,'HVP T12'!$B:$B,'P&Ls Detailed'!$G90) -> 5799.27 | L90: =SUMIFS('HVP T12'!G:G,'HVP T12'!$B:$B,'P&Ls Detailed'!$G90) -> 4233.77 | M90: =SUMIFS('HVP T12'!H:H,'HVP T12'!$B:$B,'P&Ls Detailed'!$G90) -> 5039.43 | N90: =SUMIFS('HVP T12'!I:I,'HVP T12'!$B:$B,'P&Ls Detailed'!$G90) -> 7289.32 | O90: =SUMIFS('HVP T12'!J:J,'HVP T12'!$B:$B,'P&Ls Detailed'!$G90) -> 4702.27 | P90: =SUMIFS('HVP T12'!K:K,'HVP T12'!$B:$B,'P&Ls Detailed'!$G90) -> 2749.7 | Q90: =SUMIFS('HVP T12'!L:L,'HVP T12'!$B:$B,'P&Ls Detailed'!$G90) -> 3224.59 | R90: =SUMIFS('HVP T12'!M:M,'HVP T12'!$B:$B,'P&Ls Detailed'!$G90) -> 3033.79 | S90: =SUMIFS('HVP T12'!N:N,'HVP T12'!$B:$B,'P&Ls Detailed'!$G90) -> 2985.75 | W90: =SUM(H90:S90) -> 55690.74 | X90: =SUM(K90:S90)/9*12 -> 52077.187 | Y90: =SUM(N90:S90)/6*12 -> 47970.84 | Z90: =SUM(Q90:S90)/3*12 -> 36976.52 | AA90: =S90*12 -> 35829
D91: =$AB$3 -> Hudson View Park | E91: General & Administrative | G91: POSTAGE | H91: =SUMIFS('HVP T12'!C:C,'HVP T12'!$B:$B,'P&Ls Detailed'!$G91) -> 216.98 | I91: =SUMIFS('HVP T12'!D:D,'HVP T12'!$B:$B,'P&Ls Detailed'!$G91) -> 652 | J91: =SUMIFS('HVP T12'!E:E,'HVP T12'!$B:$B,'P&Ls Detailed'!$G91) -> 356.2 | K91: =SUMIFS('HVP T12'!F:F,'HVP T12'!$B:$B,'P&Ls Detailed'!$G91) -> 398.07 | L91: =SUMIFS('HVP T12'!G:G,'HVP T12'!$B:$B,'P&Ls Detailed'!$G91) -> 420.28 | M91: =SUMIFS('HVP T12'!H:H,'HVP T12'!$B:$B,'P&Ls Detailed'!$G91) -> 252.17 | N91: =SUMIFS('HVP T12'!I:I,'HVP T12'!$B:$B,'P&Ls Detailed'!$G91) -> 289.34 | O91: =SUMIFS('HVP T12'!J:J,'HVP T12'!$B:$B,'P&Ls Detailed'!$G91) -> 1260.4 | P91: =SUMIFS('HVP T12'!K:K,'HVP T12'!$B:$B,'P&Ls Detailed'!$G91) -> 177.31 | Q91: =SUMIFS('HVP T12'!L:L,'HVP T12'!$B:$B,'P&Ls Detailed'!$G91) -> 648.53 | R91: =SUMIFS('HVP T12'!M:M,'HVP T12'!$B:$B,'P&Ls Detailed'!$G91) -> 824.91 | S91: =SUMIFS('HVP T12'!N:N,'HVP T12'!$B:$B,'P&Ls Detailed'!$G91) -> 142.23 | W91: =SUM(H91:S91) -> 5638.42 | X91: =SUM(K91:S91)/9*12 -> 5884.32 | Y91: =SUM(N91:S91)/6*12 -> 6685.44 | Z91: =SUM(Q91:S91)/3*12 -> 6462.68 | AA91: =S91*12 -> 1706.76
D92: =$AB$3 -> Hudson View Park | E92: General & Administrative | G92: BANK SERVICE CHARGE | H92: =SUMIFS('HVP T12'!C:C,'HVP T12'!$B:$B,'P&Ls Detailed'!$G92) -> 15 | I92: =SUMIFS('HVP T12'!D:D,'HVP T12'!$B:$B,'P&Ls Detailed'!$G92) -> 15 | J92: =SUMIFS('HVP T12'!E:E,'HVP T12'!$B:$B,'P&Ls Detailed'!$G92) -> 45 | K92: =SUMIFS('HVP T12'!F:F,'HVP T12'!$B:$B,'P&Ls Detailed'!$G92) -> 15 | L92: =SUMIFS('HVP T12'!G:G,'HVP T12'!$B:$B,'P&Ls Detailed'!$G92) -> 15 | M92: =SUMIFS('HVP T12'!H:H,'HVP T12'!$B:$B,'P&Ls Detailed'!$G92) -> 45 | N92: =SUMIFS('HVP T12'!I:I,'HVP T12'!$B:$B,'P&Ls Detailed'!$G92) -> 15 | O92: =SUMIFS('HVP T12'!J:J,'HVP T12'!$B:$B,'P&Ls Detailed'!$G92) -> 85.8 | P92: =SUMIFS('HVP T12'!K:K,'HVP T12'!$B:$B,'P&Ls Detailed'!$G92) -> 65.7 | Q92: =SUMIFS('HVP T12'!L:L,'HVP T12'!$B:$B,'P&Ls Detailed'!$G92) -> -264.3 | R92: =SUMIFS('HVP T12'!M:M,'HVP T12'!$B:$B,'P&Ls Detailed'!$G92) -> 35.55 | S92: =SUMIFS('HVP T12'!N:N,'HVP T12'!$B:$B,'P&Ls Detailed'!$G92) -> 29.4 | W92: =SUM(H92:S92) -> 117.15 | X92: =SUM(K92:S92)/9*12 -> 56.2 | Y92: =SUM(N92:S92)/6*12 -> -65.7 | Z92: =SUM(Q92:S92)/3*12 -> -797.4 | AA92: =S92*12 -> 352.8
D93: =$AB$3 -> Hudson View Park | E93: General & Administrative | G93: RENTING EXP | H93: =SUMIFS('HVP T12'!C:C,'HVP T12'!$B:$B,'P&Ls Detailed'!$G93) -> 2336.64 | I93: =SUMIFS('HVP T12'!D:D,'HVP T12'!$B:$B,'P&Ls Detailed'!$G93) -> 3429.41 | J93: =SUMIFS('HVP T12'!E:E,'HVP T12'!$B:$B,'P&Ls Detailed'!$G93) -> 5769.32 | K93: =SUMIFS('HVP T12'!F:F,'HVP T12'!$B:$B,'P&Ls Detailed'!$G93) -> 980.64 | L93: =SUMIFS('HVP T12'!G:G,'HVP T12'!$B:$B,'P&Ls Detailed'!$G93) -> 4766.9 | M93: =SUMIFS('HVP T12'!H:H,'HVP T12'!$B:$B,'P&Ls Detailed'!$G93) -> 1695.79 | N93: =SUMIFS('HVP T12'!I:I,'HVP T12'!$B:$B,'P&Ls Detailed'!$G93) -> 1386.54 | O93: =SUMIFS('HVP T12'!J:J,'HVP T12'!$B:$B,'P&Ls Detailed'!$G93) -> 1246.73 | P93: =SUMIFS('HVP T12'!K:K,'HVP T12'!$B:$B,'P&Ls Detailed'!$G93) -> 389.65 | Q93: =SUMIFS('HVP T12'!L:L,'HVP T12'!$B:$B,'P&Ls Detailed'!$G93) -> 922.74 | R93: =SUMIFS('HVP T12'!M:M,'HVP T12'!$B:$B,'P&Ls Detailed'!$G93) -> 265.64 | S93: =SUMIFS('HVP T12'!N:N,'HVP T12'!$B:$B,'P&Ls Detailed'!$G93) -> 691.28 | W93: =SUM(H93:S93) -> 23881.28 | X93: =SUM(K93:S93)/9*12 -> 16461.213 | Y93: =SUM(N93:S93)/6*12 -> 9805.16 | Z93: =SUM(Q93:S93)/3*12 -> 7518.64 | AA93: =S93*12 -> 8295.36
D94: =$AB$3 -> Hudson View Park | E94: General & Administrative | G94: TENANT EVENTS | H94: =SUMIFS('HVP T12'!C:C,'HVP T12'!$B:$B,'P&Ls Detailed'!$G94) -> 0 | I94: =SUMIFS('HVP T12'!D:D,'HVP T12'!$B:$B,'P&Ls Detailed'!$G94) -> 0 | J94: =SUMIFS('HVP T12'!E:E,'HVP T12'!$B:$B,'P&Ls Detailed'!$G94) -> 0 | K94: =SUMIFS('HVP T12'!F:F,'HVP T12'!$B:$B,'P&Ls Detailed'!$G94) -> 0 | L94: =SUMIFS('HVP T12'!G:G,'HVP T12'!$B:$B,'P&Ls Detailed'!$G94) -> 0 | M94: =SUMIFS('HVP T12'!H:H,'HVP T12'!$B:$B,'P&Ls Detailed'!$G94) -> 0 | N94: =SUMIFS('HVP T12'!I:I,'HVP T12'!$B:$B,'P&Ls Detailed'!$G94) -> 0 | O94: =SUMIFS('HVP T12'!J:J,'HVP T12'!$B:$B,'P&Ls Detailed'!$G94) -> 0 | P94: =SUMIFS('HVP T12'!K:K,'HVP T12'!$B:$B,'P&Ls Detailed'!$G94) -> 250.04 | Q94: =SUMIFS('HVP T12'!L:L,'HVP T12'!$B:$B,'P&Ls Detailed'!$G94) -> 0 | R94: =SUMIFS('HVP T12'!M:M,'HVP T12'!$B:$B,'P&Ls Detailed'!$G94) -> 2122.27 | S94: =SUMIFS('HVP T12'!N:N,'HVP T12'!$B:$B,'P&Ls Detailed'!$G94) -> 911.78 | W94: =SUM(H94:S94) -> 3284.09 | X94: =SUM(K94:S94)/9*12 -> 4378.7867 | Y94: =SUM(N94:S94)/6*12 -> 6568.18 | Z94: =SUM(Q94:S94)/3*12 -> 12136.2 | AA94: =S94*12 -> 10941.36
... D98: =$AB$3 -> Hudson View Park | E98: General & Administrative | G98: EMPLOYEE TRAININ | H98: =SUMIFS('HVP T12'!C:C,'HVP T12'!$B:$B,'P&Ls Detailed'!$G98) -> 0 | I98: =SUMIFS('HVP T12'!D:D,'HVP T12'!$B:$B,'P&Ls Detailed'!$G98) -> 0 | J98: =SUMIFS('HVP T12'!E:E,'HVP T12'!$B:$B,'P&Ls Detailed'!$G98) -> 0 | K98: =SUMIFS('HVP T12'!F:F,'HVP T12'!$B:$B,'P&Ls Detailed'!$G98) -> 0 | L98: =SUMIFS('HVP T12'!G:G,'HVP T12'!$B:$B,'P&Ls Detailed'!$G98) -> 0 | M98: =SUMIFS('HVP T12'!H:H,'HVP T12'!$B:$B,'P&Ls Detailed'!$G98) -> 0 | N98: =SUMIFS('HVP T12'!I:I,'HVP T12'!$B:$B,'P&Ls Detailed'!$G98) -> 570.18 | O98: =SUMIFS('HVP T12'!J:J,'HVP T12'!$B:$B,'P&Ls Detailed'!$G98) -> 0 | P98: =SUMIFS('HVP T12'!K:K,'HVP T12'!$B:$B,'P&Ls Detailed'!$G98) -> 0 | Q98: =SUMIFS('HVP T12'!L:L,'HVP T12'!$B:$B,'P&Ls Detailed'!$G98) -> 1147.34 | R98: =SUMIFS('HVP T12'!M:M,'HVP T12'!$B:$B,'P&Ls Detailed'!$G98) -> 106.82 | S98: =SUMIFS('HVP T12'!N:N,'HVP T12'!$B:$B,'P&Ls Detailed'!$G98) -> 0 | W98: =SUM(H98:S98) -> 1824.34 | X98: =SUM(K98:S98)/9*12 -> 2432.4533 | Y98: =SUM(N98:S98)/6*12 -> 3648.68 | Z98: =SUM(Q98:S98)/3*12 -> 5016.64 | AA98: =S98*12 -> 0
D99: =$AB$3 -> Hudson View Park | G99: Total ADMIN & GENERAL | H99: =SUM(H83:H98) -> 12427.59 | I99: =SUM(I83:I98) -> 19977.07 | J99: =SUM(J83:J98) -> 25408.69 | K99: =SUM(K83:K98) -> 20873.39 | L99: =SUM(L83:L98) -> 22449.04 | M99: =SUM(M83:M98) -> 18102.35 | N99: =SUM(N83:N98) -> 24833.87 | O99: =SUM(O83:O98) -> 16947.22 | ... S99: =SUM(S83:S98) -> 13268.14 | W99: =SUM(W83:W98) -> 224688.23 | X99: =SUM(K99:S99)/9*12 -> 222499.84 | Y99: =SUM(N99:S99)/6*12 -> 210900.2 | Z99: =SUM(Q99:S99)/3*12 -> 194302.96 | AA99: =S99*12 -> 159217.68
D100: =$AB$3 -> Hudson View Park | G100: ADVERTISING & MARKETING
D101: =$AB$3 -> Hudson View Park | E101: Advertising & Marketing | G101: TENANT REFERRALS | H101: =SUMIFS('HVP T12'!C:C,'HVP T12'!$B:$B,'P&Ls Detailed'!$G101) -> 400 | I101: =SUMIFS('HVP T12'!D:D,'HVP T12'!$B:$B,'P&Ls Detailed'!$G101) -> 1200 | J101: =SUMIFS('HVP T12'!E:E,'HVP T12'!$B:$B,'P&Ls Detailed'!$G101) -> 1600 | K101: =SUMIFS('HVP T12'!F:F,'HVP T12'!$B:$B,'P&Ls Detailed'!$G101) -> 400 | L101: =SUMIFS('HVP T12'!G:G,'HVP T12'!$B:$B,'P&Ls Detailed'!$G101) -> 400 | M101: =SUMIFS('HVP T12'!H:H,'HVP T12'!$B:$B,'P&Ls Detailed'!$G101) -> 0 | N101: =SUMIFS('HVP T12'!I:I,'HVP T12'!$B:$B,'P&Ls Detailed'!$G101) -> 800 | O101: =SUMIFS('HVP T12'!J:J,'HVP T12'!$B:$B,'P&Ls Detailed'!$G101) -> 400 | P101: =SUMIFS('HVP T12'!K:K,'HVP T12'!$B:$B,'P&Ls Detailed'!$G101) -> 800 | Q101: =SUMIFS('HVP T12'!L:L,'HVP T12'!$B:$B,'P&Ls Detailed'!$G101) -> 400 | R101: =SUMIFS('HVP T12'!M:M,'HVP T12'!$B:$B,'P&Ls Detailed'!$G101) -> 400 | S101: =SUMIFS('HVP T12'!N:N,'HVP T12'!$B:$B,'P&Ls Detailed'!$G101) -> 0 | W101: =SUM(H101:S101) -> 6800 | X101: =SUM(K101:S101)/9*12 -> 4800 | Y101: =SUM(N101:S101)/6*12 -> 5600 | Z101: =SUM(Q101:S101)/3*12 -> 3200 | AA101: =S101*12 -> 0
D102: =$AB$3 -> Hudson View Park | E102: Advertising & Marketing | G102: OTHER ADVERTISING | H102: =SUMIFS('HVP T12'!C:C,'HVP T12'!$B:$B,'P&Ls Detailed'!$G102) -> 0 | I102: =SUMIFS('HVP T12'!D:D,'HVP T12'!$B:$B,'P&Ls Detailed'!$G102) -> 0 | J102: =SUMIFS('HVP T12'!E:E,'HVP T12'!$B:$B,'P&Ls Detailed'!$G102) -> 0 | K102: =SUMIFS('HVP T12'!F:F,'HVP T12'!$B:$B,'P&Ls Detailed'!$G102) -> 0 | L102: =SUMIFS('HVP T12'!G:G,'HVP T12'!$B:$B,'P&Ls Detailed'!$G102) -> 0 | M102: =SUMIFS('HVP T12'!H:H,'HVP T12'!$B:$B,'P&Ls Detailed'!$G102) -> 0 | N102: =SUMIFS('HVP T12'!I:I,'HVP T12'!$B:$B,'P&Ls Detailed'!$G102) -> 0 | O102: =SUMIFS('HVP T12'!J:J,'HVP T12'!$B:$B,'P&Ls Detailed'!$G102) -> 0 | P102: =SUMIFS('HVP T12'!K:K,'HVP T12'!$B:$B,'P&Ls Detailed'!$G102) -> 20 | Q102: =SUMIFS('HVP T12'!L:L,'HVP T12'!$B:$B,'P&Ls Detailed'!$G102) -> 0 | R102: =SUMIFS('HVP T12'!M:M,'HVP T12'!$B:$B,'P&Ls Detailed'!$G102) -> 0 | S102: =SUMIFS('HVP T12'!N:N,'HVP T12'!$B:$B,'P&Ls Detailed'!$G102) -> 0 | W102: =SUM(H102:S102) -> 20 | X102: =SUM(K102:S102)/9*12 -> 26.666667 | Y102: =SUM(N102:S102)/6*12 -> 40 | Z102: =SUM(Q102:S102)/3*12 -> 0 | AA102: =S102*12 -> 0
D103: =$AB$3 -> Hudson View Park | E103: Advertising & Marketing | G103: ZILLOW.COM | H103: =SUMIFS('HVP T12'!C:C,'HVP T12'!$B:$B,'P&Ls Detailed'!$G103) -> 810 | I103: =SUMIFS('HVP T12'!D:D,'HVP T12'!$B:$B,'P&Ls Detailed'!$G103) -> 810 | J103: =SUMIFS('HVP T12'!E:E,'HVP T12'!$B:$B,'P&Ls Detailed'!$G103) -> 810 | K103: =SUMIFS('HVP T12'!F:F,'HVP T12'!$B:$B,'P&Ls Detailed'!$G103) -> 810 | L103: =SUMIFS('HVP T12'!G:G,'HVP T12'!$B:$B,'P&Ls Detailed'!$G103) -> 810 | M103: =SUMIFS('HVP T12'!H:H,'HVP T12'!$B:$B,'P&Ls Detailed'!$G103) -> 828.87 | N103: =SUMIFS('HVP T12'!I:I,'HVP T12'!$B:$B,'P&Ls Detailed'!$G103) -> 875 | O103: =SUMIFS('HVP T12'!J:J,'HVP T12'!$B:$B,'P&Ls Detailed'!$G103) -> 875 | P103: =SUMIFS('HVP T12'!K:K,'HVP T12'!$B:$B,'P&Ls Detailed'!$G103) -> 875 | Q103: =SUMIFS('HVP T12'!L:L,'HVP T12'!$B:$B,'P&Ls Detailed'!$G103) -> 875 | R103: =SUMIFS('HVP T12'!M:M,'HVP T12'!$B:$B,'P&Ls Detailed'!$G103) -> 875 | S103: =SUMIFS('HVP T12'!N:N,'HVP T12'!$B:$B,'P&Ls Detailed'!$G103) -> 875 | W103: =SUM(H103:S103) -> 10128.87 | X103: =SUM(K103:S103)/9*12 -> 10265.16 | Y103: =SUM(N103:S103)/6*12 -> 10500 | Z103: =SUM(Q103:S103)/3*12 -> 10500 | AA103: =S103*12 -> 10500
D104: =$AB$3 -> Hudson View Park | G104: Total ADVERTISING & MARKETING | H104: =SUM(H101:H103) -> 1210 | I104: =SUM(I101:I103) -> 2010 | J104: =SUM(J101:J103) -> 2410 | K104: =SUM(K101:K103) -> 1210 | L104: =SUM(L101:L103) -> 1210 | M104: =SUM(M101:M103) -> 828.87 | N104: =SUM(N101:N103) -> 1675 | O104: =SUM(O101:O103) -> 1275 | ... S104: =SUM(S101:S103) -> 875 | W104: =SUM(W101:W103) -> 16948.87 | X104: =SUM(K104:S104)/9*12 -> 15091.827 | Y104: =SUM(N104:S104)/6*12 -> 16140 | Z104: =SUM(Q104:S104)/3*12 -> 13700 | AA104: =S104*12 -> 10500
D105: =$AB$3 -> Hudson View Park | G105: MANAGEMENT
D106: =$AB$3 -> Hudson View Park | E106: Management Fee | G106: MANAGEMENT FEE | H106: =SUMIFS('HVP T12'!C:C,'HVP T12'!$B:$B,'P&Ls Detailed'!$G106) -> 42349 | I106: =SUMIFS('HVP T12'!D:D,'HVP T12'!$B:$B,'P&Ls Detailed'!$G106) -> 42321 | J106: =SUMIFS('HVP T12'!E:E,'HVP T12'!$B:$B,'P&Ls Detailed'!$G106) -> 42660 | K106: =SUMIFS('HVP T12'!F:F,'HVP T12'!$B:$B,'P&Ls Detailed'!$G106) -> 42848 | L106: =SUMIFS('HVP T12'!G:G,'HVP T12'!$B:$B,'P&Ls Detailed'!$G106) -> 43638 | M106: =SUMIFS('HVP T12'!H:H,'HVP T12'!$B:$B,'P&Ls Detailed'!$G106) -> 43914 | N106: =SUMIFS('HVP T12'!I:I,'HVP T12'!$B:$B,'P&Ls Detailed'!$G106) -> 43962 | O106: =SUMIFS('HVP T12'!J:J,'HVP T12'!$B:$B,'P&Ls Detailed'!$G106) -> 49199 | P106: =SUMIFS('HVP T12'!K:K,'HVP T12'!$B:$B,'P&Ls Detailed'!$G106) -> 44485 | Q106: =SUMIFS('HVP T12'!L:L,'HVP T12'!$B:$B,'P&Ls Detailed'!$G106) -> 44887 | R106: =SUMIFS('HVP T12'!M:M,'HVP T12'!$B:$B,'P&Ls Detailed'!$G106) -> 45107 | S106: =SUMIFS('HVP T12'!N:N,'HVP T12'!$B:$B,'P&Ls Detailed'!$G106) -> 45202 | W106: =SUM(H106:S106) -> 530572 | X106: =SUM(K106:S106)/9*12 -> 537656 | Y106: =SUM(N106:S106)/6*12 -> 545684 | Z106: =SUM(Q106:S106)/3*12 -> 540784 | AA106: =S106*12 -> 542424
D107: =$AB$3 -> Hudson View Park | G107: Total MANAGEMENT | H107: =H106 -> 42349 | I107: =I106 -> 42321 | J107: =J106 -> 42660 | K107: =K106 -> 42848 | L107: =L106 -> 43638 | M107: =M106 -> 43914 | N107: =N106 -> 43962 | O107: =O106 -> 49199 | ... S107: =S106 -> 45202 | W107: =SUM(H107:S107) -> 530572 | X107: =SUM(K107:S107)/9*12 -> 537656 | Y107: =SUM(N107:S107)/6*12 -> 545684 | Z107: =SUM(Q107:S107)/3*12 -> 540784 | AA107: =S107*12 -> 542424
D108: =$AB$3 -> Hudson View Park | G108: UTILITIES
D109: =$AB$3 -> Hudson View Park | E109: Utilities - Gas | G109: GAS | H109: =SUMIFS('HVP T12'!C:C,'HVP T12'!$B:$B,'P&Ls Detailed'!$G109) -> 17152.08 | I109: =SUMIFS('HVP T12'!D:D,'HVP T12'!$B:$B,'P&Ls Detailed'!$G109) -> 8042.1 | J109: =SUMIFS('HVP T12'!E:E,'HVP T12'!$B:$B,'P&Ls Detailed'!$G109) -> 9971.46 | K109: =SUMIFS('HVP T12'!F:F,'HVP T12'!$B:$B,'P&Ls Detailed'!$G109) -> 8644.66 | L109: =SUMIFS('HVP T12'!G:G,'HVP T12'!$B:$B,'P&Ls Detailed'!$G109) -> 11456.13 | M109: =SUMIFS('HVP T12'!H:H,'HVP T12'!$B:$B,'P&Ls Detailed'!$G109) -> 20029.95 | N109: =SUMIFS('HVP T12'!I:I,'HVP T12'!$B:$B,'P&Ls Detailed'!$G109) -> 27161.42 | O109: =SUMIFS('HVP T12'!J:J,'HVP T12'!$B:$B,'P&Ls Detailed'!$G109) -> 43548.46 | P109: =SUMIFS('HVP T12'!K:K,'HVP T12'!$B:$B,'P&Ls Detailed'!$G109) -> 41188.07 | Q109: =SUMIFS('HVP T12'!L:L,'HVP T12'!$B:$B,'P&Ls Detailed'!$G109) -> 36127.02 | R109: =SUMIFS('HVP T12'!M:M,'HVP T12'!$B:$B,'P&Ls Detailed'!$G109) -> 33813.84 | S109: =SUMIFS('HVP T12'!N:N,'HVP T12'!$B:$B,'P&Ls Detailed'!$G109) -> 25777.09 | W109: =SUM(H109:S109) -> 282912.28 | X109: =SUM(K109:S109)/9*12 -> 330328.85 | Y109: =SUM(N109:S109)/6*12 -> 415231.8 | Z109: =SUM(Q109:S109)/3*12 -> 382871.8 | AA109: =S109*12 -> 309325.08
D110: =$AB$3 -> Hudson View Park | E110: Utilities - Electric | G110: ELECTRIC | H110: =SUMIFS('HVP T12'!C:C,'HVP T12'!$B:$B,'P&Ls Detailed'!$G110) -> 5667.04 | I110: =SUMIFS('HVP T12'!D:D,'HVP T12'!$B:$B,'P&Ls Detailed'!$G110) -> 4776.23 | J110: =SUMIFS('HVP T12'!E:E,'HVP T12'!$B:$B,'P&Ls Detailed'!$G110) -> 5875.13 | K110: =SUMIFS('HVP T12'!F:F,'HVP T12'!$B:$B,'P&Ls Detailed'!$G110) -> 6825.24 | L110: =SUMIFS('HVP T12'!G:G,'HVP T12'!$B:$B,'P&Ls Detailed'!$G110) -> 6187.51 | M110: =SUMIFS('HVP T12'!H:H,'HVP T12'!$B:$B,'P&Ls Detailed'!$G110) -> 7601.99 | N110: =SUMIFS('HVP T12'!I:I,'HVP T12'!$B:$B,'P&Ls Detailed'!$G110) -> 7339.54 | O110: =SUMIFS('HVP T12'!J:J,'HVP T12'!$B:$B,'P&Ls Detailed'!$G110) -> 9460.19 | P110: =SUMIFS('HVP T12'!K:K,'HVP T12'!$B:$B,'P&Ls Detailed'!$G110) -> 8120.92 | Q110: =SUMIFS('HVP T12'!L:L,'HVP T12'!$B:$B,'P&Ls Detailed'!$G110) -> 6882.78 | R110: =SUMIFS('HVP T12'!M:M,'HVP T12'!$B:$B,'P&Ls Detailed'!$G110) -> 7095.09 | S110: =SUMIFS('HVP T12'!N:N,'HVP T12'!$B:$B,'P&Ls Detailed'!$G110) -> 7333.54 | W110: =SUM(H110:S110) -> 83165.2 | X110: =SUM(K110:S110)/9*12 -> 89129.067 | Y110: =SUM(N110:S110)/6*12 -> 92464.12 | Z110: =SUM(Q110:S110)/3*12 -> 85245.64 | AA110: =S110*12 -> 88002.48
D111: =$AB$3 -> Hudson View Park | E111: Utilities - Sewer & Water | G111: WATER | H111: =SUMIFS('HVP T12'!C:C,'HVP T12'!$B:$B,'P&Ls Detailed'!$G111) -> 10836.79 | I111: =SUMIFS('HVP T12'!D:D,'HVP T12'!$B:$B,'P&Ls Detailed'!$G111) -> 10900 | J111: =SUMIFS('HVP T12'!E:E,'HVP T12'!$B:$B,'P&Ls Detailed'!$G111) -> 11300 | K111: =SUMIFS('HVP T12'!F:F,'HVP T12'!$B:$B,'P&Ls Detailed'!$G111) -> 10585 | L111: =SUMIFS('HVP T12'!G:G,'HVP T12'!$B:$B,'P&Ls Detailed'!$G111) -> 10330.09 | M111: =SUMIFS('HVP T12'!H:H,'HVP T12'!$B:$B,'P&Ls Detailed'!$G111) -> 11420 | N111: =SUMIFS('HVP T12'!I:I,'HVP T12'!$B:$B,'P&Ls Detailed'!$G111) -> 8852.21 | O111: =SUMIFS('HVP T12'!J:J,'HVP T12'!$B:$B,'P&Ls Detailed'!$G111) -> 10425 | P111: =SUMIFS('HVP T12'!K:K,'HVP T12'!$B:$B,'P&Ls Detailed'!$G111) -> 10425 | Q111: =SUMIFS('HVP T12'!L:L,'HVP T12'!$B:$B,'P&Ls Detailed'!$G111) -> 9415 | R111: =SUMIFS('HVP T12'!M:M,'HVP T12'!$B:$B,'P&Ls Detailed'!$G111) -> 10582.35 | S111: =SUMIFS('HVP T12'!N:N,'HVP T12'!$B:$B,'P&Ls Detailed'!$G111) -> 10200 | W111: =SUM(H111:S111) -> 125271.44 | X111: =SUM(K111:S111)/9*12 -> 122979.53 | Y111: =SUM(N111:S111)/6*12 -> 119799.12 | Z111: =SUM(Q111:S111)/3*12 -> 120789.4 | AA111: =S111*12 -> 122400
...

Sheet Unit Mix
C3: UNIT MIX & RENT ROLL SUMMARY | Y3: ='Exec Summ'!$F$6 -> Hudson View Park | AA3: =OneLineRR!$C$70 -> 45931 | AB3: <---- RR Date | AC3: =IF(COUNTIF(E83:AB85,"False")=0,"OK","ERROR") -> OK
D5: Property Name | E5: Floor Plan | F5: Total Units | G5: Total SF | H5: Avg SF | I5: In-Place Rent | J5: In-Place/Unit | K5: In-Place/SF | L5: RR Mkt Rent | M5: RR Mkt/Unit | N5: RR Mkt/SF | O5: Mkt Rent | P5: Mkt/Unit | Q5: Mkt/SF | R5: Reno Rent | S5: Reno/Unit | T5: Reno/SF | U5: Min IP Rent | V5: Max IP Rent | W5: Other Inc. | AA5: Occ Units | AB5: Sq. Ft. (Occ) | AC5: Avg Comps Rent | AH5: UNIT TYPE | AI5: ICON UNIT TYPE
D6: =OneLineRR!B5 -> Hudson View Park | E6: =OneLineRR!C5 -> Studio - Small, Gold | F6: =COUNTIFS('Rent Roll'!$G:$G,'Unit Mix'!$E6,'Rent Roll'!$D:$D,'Unit Mix'!D6) -> 0 | G6: =SUMIFS('Rent Roll'!$K:$K,'Rent Roll'!$G:$G,'Unit Mix'!$E6,'Rent Roll'!$D:$D,'Unit Mix'!D6) -> 0 | H6: =G6/F6 -> #DIV/0! | I6: =SUMIFS('Rent Roll'!$M:$M,'Rent Roll'!$G:$G,'Unit Mix'!$E6,'Rent Roll'!$D:$D,'Unit Mix'!D6)+SUMIFS('Rent Roll'!$N:$N,'Rent Roll'!$G:$G,'Unit Mix'!$E6,'Rent Roll'!$D:$D,'Unit Mix'!D6) -> 0 | J6: =IFERROR(I6/F6,"") | K6: =IFERROR(J6/H6,"") | L6: =SUMIFS('Rent Roll'!$O:$O,'Rent Roll'!$G:$G,'Unit Mix'!$E6,'Rent Roll'!$D:$D,'Unit Mix'!D6) -> 0 | M6: =L6/F6 -> #DIV/0! | N6: =IFERROR(M6/H6,"") | O6: =P6*F6 -> #DIV/0! | P6: =MAX(M6,V6) -> #DIV/0! | Q6: =IFERROR(P6/H6,"") | R6: =S6*F6 -> #DIV/0! | S6: =IF($S$83=0,P6,ROUNDUP(P6*(1+$S$83),-2)) -> #DIV/0! | T6: =IFERROR(S6/H6,"") | U6: =_xlfn.MINIFS('Rent Roll'!$M:$M,'Rent Roll'!$G:$G,'Unit Mix'!E6,'Rent Roll'!$D:$D,'Unit Mix'!D6,'Rent Roll'!$J:$J,"<>Vacant",'Rent Roll'!$M:$M,">100") -> 0 | V6: =_xlfn.MAXIFS('Rent Roll'!$M:$M,'Rent Roll'!$G:$G,'Unit Mix'!E6,'Rent Roll'!$D:$D,'Unit Mix'!D6,'Rent Roll'!$J:$J,"<>Vacant") -> 0 | W6: =SUMIFS('Rent Roll'!$Q:$Q,'Rent Roll'!$G:$G,'Unit Mix'!$E6,'Rent Roll'!$D:$D,'Unit Mix'!D6) -> 0 | AA6: =COUNTIFS('Rent Roll'!$G:$G,'Unit Mix'!$E6,'Rent Roll'!$L:$L,"Occ",'Rent Roll'!$D:$D,'Unit Mix'!D6)+COUNTIFS('Rent Roll'!$G:$G,'Unit Mix'!$E6,'Rent Roll'!$L:$L,"Admin",'Rent Roll'!$D:$D,'Unit Mix'!D6)+COUNTIFS('Rent Roll'!$G:$G,'Unit Mix'!$E6,'Rent Roll'!$L:$L,"Model",'Rent Roll'!$D:$D,'Unit Mix'!D6)+COUNTIFS('Rent Roll'!$G:$G,'Unit Mix'!$E6,'Rent Roll'!$L:$L,"Down",'Rent Roll'!$D:$D,'Unit Mix'!D6) -> 0 | AB6: =SUMIFS('Rent Roll'!$K:$K,'Rent Roll'!$G:$G,'Unit Mix'!$E6,'Rent Roll'!$L:$L,"Occ",'Rent Roll'!$D:$D,'Unit Mix'!D6)+SUMIFS('Rent Roll'!$K:$K,'Rent Roll'!$G:$G,'Unit Mix'!$E6,'Rent Roll'!$L:$L,"Admin",'Rent Roll'!$D:$D,'Unit Mix'!D6)+SUMIFS('Rent Roll'!$K:$K,'Rent Roll'!$G:$G,'Unit Mix'!$E6,'Rent Roll'!$L:$L,"Model",'Rent Roll'!$D:$D,'Unit Mix'!D6)+SUMIFS('Rent Roll'!$K:$K,'Rent Roll'!$G:$G,'Unit Mix'!$E6,'Rent Roll'!$L:$L,"Down",'Rent Roll'!$D:$D,'Unit Mix'!D6) -> 0 | AC6: {=INDEX('Lease Comps'!$I$10:$I$24,MATCH('Unit Mix'!AI6,'Lease Comps'!$A$10:$A$24,0)+1)} -> #DIV/0! | AH6: =IF(LEFT($E6,1)="1","1 Bedroom",IF(LEFT($E6,1)="2","2 Bedroom",IF(LEFT($E6,1)="3","3 Bedroom",IF(LEFT($E6,1)="4","4 Bedroom","Studio")))) -> Studio | AI6: =IF(LEFT($E6,1)="1","1BR",IF(LEFT($E6,1)="2","2BR",IF(LEFT($E6,1)="3","3BR",IF(LEFT($E6,1)="4","4BR","Studio")))) -> Studio
D7: =OneLineRR!B6 -> Hudson View Park | E7: =OneLineRR!C6 -> Studio - Small, Platinum | F7: =COUNTIFS('Rent Roll'!$G:$G,'Unit Mix'!$E7,'Rent Roll'!$D:$D,'Unit Mix'!D7) -> 0 | G7: =SUMIFS('Rent Roll'!$K:$K,'Rent Roll'!$G:$G,'Unit Mix'!$E7,'Rent Roll'!$D:$D,'Unit Mix'!D7) -> 0 | H7: =G7/F7 -> #DIV/0! | I7: =SUMIFS('Rent Roll'!$M:$M,'Rent Roll'!$G:$G,'Unit Mix'!$E7,'Rent Roll'!$D:$D,'Unit Mix'!D7)+SUMIFS('Rent Roll'!$N:$N,'Rent Roll'!$G:$G,'Unit Mix'!$E7,'Rent Roll'!$D:$D,'Unit Mix'!D7) -> 0 | J7: =IFERROR(I7/F7,"") | K7: =IFERROR(J7/H7,"") | L7: =SUMIFS('Rent Roll'!$O:$O,'Rent Roll'!$G:$G,'Unit Mix'!$E7,'Rent Roll'!$D:$D,'Unit Mix'!D7) -> 0 | M7: =L7/F7 -> #DIV/0! | N7: =IFERROR(M7/H7,"") | O7: =P7*F7 -> #DIV/0! | P7: =MAX(M7,V7) -> #DIV/0! | Q7: =IFERROR(P7/H7,"") | R7: =S7*F7 -> #DIV/0! | S7: =IF($S$83=0,P7,ROUNDUP(P7*(1+$S$83),-2)) -> #DIV/0! | T7: =IFERROR(S7/H7,"") | U7: =_xlfn.MINIFS('Rent Roll'!$M:$M,'Rent Roll'!$G:$G,'Unit Mix'!E7,'Rent Roll'!$D:$D,'Unit Mix'!D7,'Rent Roll'!$J:$J,"<>Vacant",'Rent Roll'!$M:$M,">100") -> 0 | V7: =_xlfn.MAXIFS('Rent Roll'!$M:$M,'Rent Roll'!$G:$G,'Unit Mix'!E7,'Rent Roll'!$D:$D,'Unit Mix'!D7,'Rent Roll'!$J:$J,"<>Vacant") -> 0 | W7: =SUMIFS('Rent Roll'!$Q:$Q,'Rent Roll'!$G:$G,'Unit Mix'!$E7,'Rent Roll'!$D:$D,'Unit Mix'!D7) -> 0 | AA7: =COUNTIFS('Rent Roll'!$G:$G,'Unit Mix'!$E7,'Rent Roll'!$L:$L,"Occ",'Rent Roll'!$D:$D,'Unit Mix'!D7)+COUNTIFS('Rent Roll'!$G:$G,'Unit Mix'!$E7,'Rent Roll'!$L:$L,"Admin",'Rent Roll'!$D:$D,'Unit Mix'!D7)+COUNTIFS('Rent Roll'!$G:$G,'Unit Mix'!$E7,'Rent Roll'!$L:$L,"Model",'Rent Roll'!$D:$D,'Unit Mix'!D7)+COUNTIFS('Rent Roll'!$G:$G,'Unit Mix'!$E7,'Rent Roll'!$L:$L,"Down",'Rent Roll'!$D:$D,'Unit Mix'!D7) -> 0 | AB7: =SUMIFS('Rent Roll'!$K:$K,'Rent Roll'!$G:$G,'Unit Mix'!$E7,'Rent Roll'!$L:$L,"Occ",'Rent Roll'!$D:$D,'Unit Mix'!D7)+SUMIFS('Rent Roll'!$K:$K,'Rent Roll'!$G:$G,'Unit Mix'!$E7,'Rent Roll'!$L:$L,"Admin",'Rent Roll'!$D:$D,'Unit Mix'!D7)+SUMIFS('Rent Roll'!$K:$K,'Rent Roll'!$G:$G,'Unit Mix'!$E7,'Rent Roll'!$L:$L,"Model",'Rent Roll'!$D:$D,'Unit Mix'!D7)+SUMIFS('Rent Roll'!$K:$K,'Rent Roll'!$G:$G,'Unit Mix'!$E7,'Rent Roll'!$L:$L,"Down",'Rent Roll'!$D:$D,'Unit Mix'!D7) -> 0 | AC7: {=INDEX('Lease Comps'!$I$10:$I$24,MATCH('Unit Mix'!AI7,'Lease Comps'!$A$10:$A$24,0)+1)} -> #DIV/0! | AH7: =IF(LEFT($E7,1)="1","1 Bedroom",IF(LEFT($E7,1)="2","2 Bedroom",IF(LEFT($E7,1)="3","3 Bedroom",IF(LEFT($E7,1)="4","4 Bedroom","Studio")))) -> Studio | AI7: =IF(LEFT($E7,1)="1","1BR",IF(LEFT($E7,1)="2","2BR",IF(LEFT($E7,1)="3","3BR",IF(LEFT($E7,1)="4","4BR","Studio")))) -> Studio
D8: =OneLineRR!B7 -> Hudson View Park | E8: =OneLineRR!C7 -> Studio - Medium, Gold | F8: =COUNTIFS('Rent Roll'!$G:$G,'Unit Mix'!$E8,'Rent Roll'!$D:$D,'Unit Mix'!D8) -> 0 | G8: =SUMIFS('Rent Roll'!$K:$K,'Rent Roll'!$G:$G,'Unit Mix'!$E8,'Rent Roll'!$D:$D,'Unit Mix'!D8) -> 0 | H8: =G8/F8 -> #DIV/0! | I8: =SUMIFS('Rent Roll'!$M:$M,'Rent Roll'!$G:$G,'Unit Mix'!$E8,'Rent Roll'!$D:$D,'Unit Mix'!D8)+SUMIFS('Rent Roll'!$N:$N,'Rent Roll'!$G:$G,'Unit Mix'!$E8,'Rent Roll'!$D:$D,'Unit Mix'!D8) -> 0 | J8: =IFERROR(I8/F8,"") | K8: =IFERROR(J8/H8,"") | L8: =SUMIFS('Rent Roll'!$O:$O,'Rent Roll'!$G:$G,'Unit Mix'!$E8,'Rent Roll'!$D:$D,'Unit Mix'!D8) -> 0 | M8: =L8/F8 -> #DIV/0! | N8: =IFERROR(M8/H8,"") | O8: =P8*F8 -> #DIV/0! | P8: =MAX(M8,V8) -> #DIV/0! | Q8: =IFERROR(P8/H8,"") | R8: =S8*F8 -> #DIV/0! | S8: =IF($S$83=0,P8,ROUNDUP(P8*(1+$S$83),-2)) -> #DIV/0! | T8: =IFERROR(S8/H8,"") | U8: =_xlfn.MINIFS('Rent Roll'!$M:$M,'Rent Roll'!$G:$G,'Unit Mix'!E8,'Rent Roll'!$D:$D,'Unit Mix'!D8,'Rent Roll'!$J:$J,"<>Vacant",'Rent Roll'!$M:$M,">100") -> 0 | V8: =_xlfn.MAXIFS('Rent Roll'!$M:$M,'Rent Roll'!$G:$G,'Unit Mix'!E8,'Rent Roll'!$D:$D,'Unit Mix'!D8,'Rent Roll'!$J:$J,"<>Vacant") -> 0 | W8: =SUMIFS('Rent Roll'!$Q:$Q,'Rent Roll'!$G:$G,'Unit Mix'!$E8,'Rent Roll'!$D:$D,'Unit Mix'!D8) -> 0 | AA8: =COUNTIFS('Rent Roll'!$G:$G,'Unit Mix'!$E8,'Rent Roll'!$L:$L,"Occ",'Rent Roll'!$D:$D,'Unit Mix'!D8)+COUNTIFS('Rent Roll'!$G:$G,'Unit Mix'!$E8,'Rent Roll'!$L:$L,"Admin",'Rent Roll'!$D:$D,'Unit Mix'!D8)+COUNTIFS('Rent Roll'!$G:$G,'Unit Mix'!$E8,'Rent Roll'!$L:$L,"Model",'Rent Roll'!$D:$D,'Unit Mix'!D8)+COUNTIFS('Rent Roll'!$G:$G,'Unit Mix'!$E8,'Rent Roll'!$L:$L,"Down",'Rent Roll'!$D:$D,'Unit Mix'!D8) -> 0 | AB8: =SUMIFS('Rent Roll'!$K:$K,'Rent Roll'!$G:$G,'Unit Mix'!$E8,'Rent Roll'!$L:$L,"Occ",'Rent Roll'!$D:$D,'Unit Mix'!D8)+SUMIFS('Rent Roll'!$K:$K,'Rent Roll'!$G:$G,'Unit Mix'!$E8,'Rent Roll'!$L:$L,"Admin",'Rent Roll'!$D:$D,'Unit Mix'!D8)+SUMIFS('Rent Roll'!$K:$K,'Rent Roll'!$G:$G,'Unit Mix'!$E8,'Rent Roll'!$L:$L,"Model",'Rent Roll'!$D:$D,'Unit Mix'!D8)+SUMIFS('Rent Roll'!$K:$K,'Rent Roll'!$G:$G,'Unit Mix'!$E8,'Rent Roll'!$L:$L,"Down",'Rent Roll'!$D:$D,'Unit Mix'!D8) -> 0 | AC8: {=INDEX('Lease Comps'!$I$10:$I$24,MATCH('Unit Mix'!AI8,'Lease Comps'!$A$10:$A$24,0)+1)} -> #DIV/0! | AH8: =IF(LEFT($E8,1)="1","1 Bedroom",IF(LEFT($E8,1)="2","2 Bedroom",IF(LEFT($E8,1)="3","3 Bedroom",IF(LEFT($E8,1)="4","4 Bedroom","Studio")))) -> Studio | AI8: =IF(LEFT($E8,1)="1","1BR",IF(LEFT($E8,1)="2","2BR",IF(LEFT($E8,1)="3","3BR",IF(LEFT($E8,1)="4","4BR","Studio")))) -> Studio
D9: =OneLineRR!B8 -> Hudson View Park | E9: =OneLineRR!C8 -> Studio - Medium, Platinum | F9: =COUNTIFS('Rent Roll'!$G:$G,'Unit Mix'!$E9,'Rent Roll'!$D:$D,'Unit Mix'!D9) -> 0 | G9: =SUMIFS('Rent Roll'!$K:$K,'Rent Roll'!$G:$G,'Unit Mix'!$E9,'Rent Roll'!$D:$D,'Unit Mix'!D9) -> 0 | H9: =G9/F9 -> #DIV/0! | I9: =SUMIFS('Rent Roll'!$M:$M,'Rent Roll'!$G:$G,'Unit Mix'!$E9,'Rent Roll'!$D:$D,'Unit Mix'!D9)+SUMIFS('Rent Roll'!$N:$N,'Rent Roll'!$G:$G,'Unit Mix'!$E9,'Rent Roll'!$D:$D,'Unit Mix'!D9) -> 0 | J9: =IFERROR(I9/F9,"") | K9: =IFERROR(J9/H9,"") | L9: =SUMIFS('Rent Roll'!$O:$O,'Rent Roll'!$G:$G,'Unit Mix'!$E9,'Rent Roll'!$D:$D,'Unit Mix'!D9) -> 0 | M9: =L9/F9 -> #DIV/0! | N9: =IFERROR(M9/H9,"") | O9: =P9*F9 -> #DIV/0! | P9: =MAX(M9,V9) -> #DIV/0! | Q9: =IFERROR(P9/H9,"") | R9: =S9*F9 -> #DIV/0! | S9: =IF($S$83=0,P9,ROUNDUP(P9*(1+$S$83),-2)) -> #DIV/0! | T9: =IFERROR(S9/H9,"") | U9: =_xlfn.MINIFS('Rent Roll'!$M:$M,'Rent Roll'!$G:$G,'Unit Mix'!E9,'Rent Roll'!$D:$D,'Unit Mix'!D9,'Rent Roll'!$J:$J,"<>Vacant",'Rent Roll'!$M:$M,">100") -> 0 | V9: =_xlfn.MAXIFS('Rent Roll'!$M:$M,'Rent Roll'!$G:$G,'Unit Mix'!E9,'Rent Roll'!$D:$D,'Unit Mix'!D9,'Rent Roll'!$J:$J,"<>Vacant") -> 0 | W9: =SUMIFS('Rent Roll'!$Q:$Q,'Rent Roll'!$G:$G,'Unit Mix'!$E9,'Rent Roll'!$D:$D,'Unit Mix'!D9) -> 0 | AA9: =COUNTIFS('Rent Roll'!$G:$G,'Unit Mix'!$E9,'Rent Roll'!$L:$L,"Occ",'Rent Roll'!$D:$D,'Unit Mix'!D9)+COUNTIFS('Rent Roll'!$G:$G,'Unit Mix'!$E9,'Rent Roll'!$L:$L,"Admin",'Rent Roll'!$D:$D,'Unit Mix'!D9)+COUNTIFS('Rent Roll'!$G:$G,'Unit Mix'!$E9,'Rent Roll'!$L:$L,"Model",'Rent Roll'!$D:$D,'Unit Mix'!D9)+COUNTIFS('Rent Roll'!$G:$G,'Unit Mix'!$E9,'Rent Roll'!$L:$L,"Down",'Rent Roll'!$D:$D,'Unit Mix'!D9) -> 0 | AB9: =SUMIFS('Rent Roll'!$K:$K,'Rent Roll'!$G:$G,'Unit Mix'!$E9,'Rent Roll'!$L:$L,"Occ",'Rent Roll'!$D:$D,'Unit Mix'!D9)+SUMIFS('Rent Roll'!$K:$K,'Rent Roll'!$G:$G,'Unit Mix'!$E9,'Rent Roll'!$L:$L,"Admin",'Rent Roll'!$D:$D,'Unit Mix'!D9)+SUMIFS('Rent Roll'!$K:$K,'Rent Roll'!$G:$G,'Unit Mix'!$E9,'Rent Roll'!$L:$L,"Model",'Rent Roll'!$D:$D,'Unit Mix'!D9)+SUMIFS('Rent Roll'!$K:$K,'Rent Roll'!$G:$G,'Unit Mix'!$E9,'Rent Roll'!$L:$L,"Down",'Rent Roll'!$D:$D,'Unit Mix'!D9) -> 0 | AC9: {=INDEX('Lease Comps'!$I$10:$I$24,MATCH('Unit Mix'!AI9,'Lease Comps'!$A$10:$A$24,0)+1)} -> #DIV/0! | AH9: =IF(LEFT($E9,1)="1","1 Bedroom",IF(LEFT($E9,1)="2","2 Bedroom",IF(LEFT($E9,1)="3","3 Bedroom",IF(LEFT($E9,1)="4","4 Bedroom","Studio")))) -> Studio | AI9: =IF(LEFT($E9,1)="1","1BR",IF(LEFT($E9,1)="2","2BR",IF(LEFT($E9,1)="3","3BR",IF(LEFT($E9,1)="4","4BR","Studio")))) -> Studio
D10: =OneLineRR!B9 -> Hudson View Park | E10: =OneLineRR!C9 -> Studio - Medium, Silver | F10: =COUNTIFS('Rent Roll'!$G:$G,'Unit Mix'!$E10,'Rent Roll'!$D:$D,'Unit Mix'!D10) -> 0 | G10: =SUMIFS('Rent Roll'!$K:$K,'Rent Roll'!$G:$G,'Unit Mix'!$E10,'Rent Roll'!$D:$D,'Unit Mix'!D10) -> 0 | H10: =G10/F10 -> #DIV/0! | I10: =SUMIFS('Rent Roll'!$M:$M,'Rent Roll'!$G:$G,'Unit Mix'!$E10,'Rent Roll'!$D:$D,'Unit Mix'!D10)+SUMIFS('Rent Roll'!$N:$N,'Rent Roll'!$G:$G,'Unit Mix'!$E10,'Rent Roll'!$D:$D,'Unit Mix'!D10) -> 0 | J10: =IFERROR(I10/F10,"") | K10: =IFERROR(J10/H10,"") | L10: =SUMIFS('Rent Roll'!$O:$O,'Rent Roll'!$G:$G,'Unit Mix'!$E10,'Rent Roll'!$D:$D,'Unit Mix'!D10) -> 0 | M10: =L10/F10 -> #DIV/0! | N10: =IFERROR(M10/H10,"") | O10: =P10*F10 -> #DIV/0! | P10: =MAX(M10,V10) -> #DIV/0! | Q10: =IFERROR(P10/H10,"") | R10: =S10*F10 -> #DIV/0! | S10: =IF($S$83=0,P10,ROUNDUP(P10*(1+$S$83),-2)) -> #DIV/0! | T10: =IFERROR(S10/H10,"") | U10: =_xlfn.MINIFS('Rent Roll'!$M:$M,'Rent Roll'!$G:$G,'Unit Mix'!E10,'Rent Roll'!$D:$D,'Unit Mix'!D10,'Rent Roll'!$J:$J,"<>Vacant",'Rent Roll'!$M:$M,">100") -> 0 | V10: =_xlfn.MAXIFS('Rent Roll'!$M:$M,'Rent Roll'!$G:$G,'Unit Mix'!E10,'Rent Roll'!$D:$D,'Unit Mix'!D10,'Rent Roll'!$J:$J,"<>Vacant") -> 0 | W10: =SUMIFS('Rent Roll'!$Q:$Q,'Rent Roll'!$G:$G,'Unit Mix'!$E10,'Rent Roll'!$D:$D,'Unit Mix'!D10) -> 0 | AA10: =COUNTIFS('Rent Roll'!$G:$G,'Unit Mix'!$E10,'Rent Roll'!$L:$L,"Occ",'Rent Roll'!$D:$D,'Unit Mix'!D10)+COUNTIFS('Rent Roll'!$G:$G,'Unit Mix'!$E10,'Rent Roll'!$L:$L,"Admin",'Rent Roll'!$D:$D,'Unit Mix'!D10)+COUNTIFS('Rent Roll'!$G:$G,'Unit Mix'!$E10,'Rent Roll'!$L:$L,"Model",'Rent Roll'!$D:$D,'Unit Mix'!D10)+COUNTIFS('Rent Roll'!$G:$G,'Unit Mix'!$E10,'Rent Roll'!$L:$L,"Down",'Rent Roll'!$D:$D,'Unit Mix'!D10) -> 0 | AB10: =SUMIFS('Rent Roll'!$K:$K,'Rent Roll'!$G:$G,'Unit Mix'!$E10,'Rent Roll'!$L:$L,"Occ",'Rent Roll'!$D:$D,'Unit Mix'!D10)+SUMIFS('Rent Roll'!$K:$K,'Rent Roll'!$G:$G,'Unit Mix'!$E10,'Rent Roll'!$L:$L,"Admin",'Rent Roll'!$D:$D,'Unit Mix'!D10)+SUMIFS('Rent Roll'!$K:$K,'Rent Roll'!$G:$G,'Unit Mix'!$E10,'Rent Roll'!$L:$L,"Model",'Rent Roll'!$D:$D,'Unit Mix'!D10)+SUMIFS('Rent Roll'!$K:$K,'Rent Roll'!$G:$G,'Unit Mix'!$E10,'Rent Roll'!$L:$L,"Down",'Rent Roll'!$D:$D,'Unit Mix'!D10) -> 0 | AC10: {=INDEX('Lease Comps'!$I$10:$I$24,MATCH('Unit Mix'!AI10,'Lease Comps'!$A$10:$A$24,0)+1)} -> #DIV/0! | AH10: =IF(LEFT($E10,1)="1","1 Bedroom",IF(LEFT($E10,1)="2","2 Bedroom",IF(LEFT($E10,1)="3","3 Bedroom",IF(LEFT($E10,1)="4","4 Bedroom","Studio")))) -> Studio | AI10: =IF(LEFT($E10,1)="1","1BR",IF(LEFT($E10,1)="2","2BR",IF(LEFT($E10,1)="3","3BR",IF(LEFT($E10,1)="4","4BR","Studio")))) -> Studio
D11: =OneLineRR!B10 -> Hudson View Park | E11: =OneLineRR!C10 -> Studio - Large, Gold | F11: =COUNTIFS('Rent Roll'!$G:$G,'Unit Mix'!$E11,'Rent Roll'!$D:$D,'Unit Mix'!D11) -> 0 | G11: =SUMIFS('Rent Roll'!$K:$K,'Rent Roll'!$G:$G,'Unit Mix'!$E11,'Rent Roll'!$D:$D,'Unit Mix'!D11) -> 0 | H11: =G11/F11 -> #DIV/0! | I11: =SUMIFS('Rent Roll'!$M:$M,'Rent Roll'!$G:$G,'Unit Mix'!$E11,'Rent Roll'!$D:$D,'Unit Mix'!D11)+SUMIFS('Rent Roll'!$N:$N,'Rent Roll'!$G:$G,'Unit Mix'!$E11,'Rent Roll'!$D:$D,'Unit Mix'!D11) -> 0 | J11: =IFERROR(I11/F11,"") | K11: =IFERROR(J11/H11,"") | L11: =SUMIFS('Rent Roll'!$O:$O,'Rent Roll'!$G:$G,'Unit Mix'!$E11,'Rent Roll'!$D:$D,'Unit Mix'!D11) -> 0 | M11: =L11/F11 -> #DIV/0! | N11: =IFERROR(M11/H11,"") | O11: =P11*F11 -> #DIV/0! | P11: =MAX(M11,V11) -> #DIV/0! | Q11: =IFERROR(P11/H11,"") | R11: =S11*F11 -> #DIV/0! | S11: =IF($S$83=0,P11,ROUNDUP(P11*(1+$S$83),-2)) -> #DIV/0! | T11: =IFERROR(S11/H11,"") | U11: =_xlfn.MINIFS('Rent Roll'!$M:$M,'Rent Roll'!$G:$G,'Unit Mix'!E11,'Rent Roll'!$D:$D,'Unit Mix'!D11,'Rent Roll'!$J:$J,"<>Vacant",'Rent Roll'!$M:$M,">100") -> 0 | V11: =_xlfn.MAXIFS('Rent Roll'!$M:$M,'Rent Roll'!$G:$G,'Unit Mix'!E11,'Rent Roll'!$D:$D,'Unit Mix'!D11,'Rent Roll'!$J:$J,"<>Vacant") -> 0 | W11: =SUMIFS('Rent Roll'!$Q:$Q,'Rent Roll'!$G:$G,'Unit Mix'!$E11,'Rent Roll'!$D:$D,'Unit Mix'!D11) -> 0 | AA11: =COUNTIFS('Rent Roll'!$G:$G,'Unit Mix'!$E11,'Rent Roll'!$L:$L,"Occ",'Rent Roll'!$D:$D,'Unit Mix'!D11)+COUNTIFS('Rent Roll'!$G:$G,'Unit Mix'!$E11,'Rent Roll'!$L:$L,"Admin",'Rent Roll'!$D:$D,'Unit Mix'!D11)+COUNTIFS('Rent Roll'!$G:$G,'Unit Mix'!$E11,'Rent Roll'!$L:$L,"Model",'Rent Roll'!$D:$D,'Unit Mix'!D11)+COUNTIFS('Rent Roll'!$G:$G,'Unit Mix'!$E11,'Rent Roll'!$L:$L,"Down",'Rent Roll'!$D:$D,'Unit Mix'!D11) -> 0 | AB11: =SUMIFS('Rent Roll'!$K:$K,'Rent Roll'!$G:$G,'Unit Mix'!$E11,'Rent Roll'!$L:$L,"Occ",'Rent Roll'!$D:$D,'Unit Mix'!D11)+SUMIFS('Rent Roll'!$K:$K,'Rent Roll'!$G:$G,'Unit Mix'!$E11,'Rent Roll'!$L:$L,"Admin",'Rent Roll'!$D:$D,'Unit Mix'!D11)+SUMIFS('Rent Roll'!$K:$K,'Rent Roll'!$G:$G,'Unit Mix'!$E11,'Rent Roll'!$L:$L,"Model",'Rent Roll'!$D:$D,'Unit Mix'!D11)+SUMIFS('Rent Roll'!$K:$K,'Rent Roll'!$G:$G,'Unit Mix'!$E11,'Rent Roll'!$L:$L,"Down",'Rent Roll'!$D:$D,'Unit Mix'!D11) -> 0 | AC11: {=INDEX('Lease Comps'!$I$10:$I$24,MATCH('Unit Mix'!AI11,'Lease Comps'!$A$10:$A$24,0)+1)} -> #DIV/0! | AH11: =IF(LEFT($E11,1)="1","1 Bedroom",IF(LEFT($E11,1)="2","2 Bedroom",IF(LEFT($E11,1)="3","3 Bedroom",IF(LEFT($E11,1)="4","4 Bedroom","Studio")))) -> Studio | AI11: =IF(LEFT($E11,1)="1","1BR",IF(LEFT($E11,1)="2","2BR",IF(LEFT($E11,1)="3","3BR",IF(LEFT($E11,1)="4","4BR","Studio")))) -> Studio
D12: =OneLineRR!B11 -> Hudson View Park | E12: =OneLineRR!C11 -> Studio - Large, Platinum | F12: =COUNTIFS('Rent Roll'!$G:$G,'Unit Mix'!$E12,'Rent Roll'!$D:$D,'Unit Mix'!D12) -> 0 | G12: =SUMIFS('Rent Roll'!$K:$K,'Rent Roll'!$G:$G,'Unit Mix'!$E12,'Rent Roll'!$D:$D,'Unit Mix'!D12) -> 0 | H12: =G12/F12 -> #DIV/0! | I12: =SUMIFS('Rent Roll'!$M:$M,'Rent Roll'!$G:$G,'Unit Mix'!$E12,'Rent Roll'!$D:$D,'Unit Mix'!D12)+SUMIFS('Rent Roll'!$N:$N,'Rent Roll'!$G:$G,'Unit Mix'!$E12,'Rent Roll'!$D:$D,'Unit Mix'!D12) -> 0 | J12: =IFERROR(I12/F12,"") | K12: =IFERROR(J12/H12,"") | L12: =SUMIFS('Rent Roll'!$O:$O,'Rent Roll'!$G:$G,'Unit Mix'!$E12,'Rent Roll'!$D:$D,'Unit Mix'!D12) -> 0 | M12: =L12/F12 -> #DIV/0! | N12: =IFERROR(M12/H12,"") | O12: =P12*F12 -> #DIV/0! | P12: =MAX(M12,V12) -> #DIV/0! | Q12: =IFERROR(P12/H12,"") | R12: =S12*F12 -> #DIV/0! | S12: =IF($S$83=0,P12,ROUNDUP(P12*(1+$S$83),-2)) -> #DIV/0! | T12: =IFERROR(S12/H12,"") | U12: =_xlfn.MINIFS('Rent Roll'!$M:$M,'Rent Roll'!$G:$G,'Unit Mix'!E12,'Rent Roll'!$D:$D,'Unit Mix'!D12,'Rent Roll'!$J:$J,"<>Vacant",'Rent Roll'!$M:$M,">100") -> 0 | V12: =_xlfn.MAXIFS('Rent Roll'!$M:$M,'Rent Roll'!$G:$G,'Unit Mix'!E12,'Rent Roll'!$D:$D,'Unit Mix'!D12,'Rent Roll'!$J:$J,"<>Vacant") -> 0 | W12: =SUMIFS('Rent Roll'!$Q:$Q,'Rent Roll'!$G:$G,'Unit Mix'!$E12,'Rent Roll'!$D:$D,'Unit Mix'!D12) -> 0 | AA12: =COUNTIFS('Rent Roll'!$G:$G,'Unit Mix'!$E12,'Rent Roll'!$L:$L,"Occ",'Rent Roll'!$D:$D,'Unit Mix'!D12)+COUNTIFS('Rent Roll'!$G:$G,'Unit Mix'!$E12,'Rent Roll'!$L:$L,"Admin",'Rent Roll'!$D:$D,'Unit Mix'!D12)+COUNTIFS('Rent Roll'!$G:$G,'Unit Mix'!$E12,'Rent Roll'!$L:$L,"Model",'Rent Roll'!$D:$D,'Unit Mix'!D12)+COUNTIFS('Rent Roll'!$G:$G,'Unit Mix'!$E12,'Rent Roll'!$L:$L,"Down",'Rent Roll'!$D:$D,'Unit Mix'!D12) -> 0 | AB12: =SUMIFS('Rent Roll'!$K:$K,'Rent Roll'!$G:$G,'Unit Mix'!$E12,'Rent Roll'!$L:$L,"Occ",'Rent Roll'!$D:$D,'Unit Mix'!D12)+SUMIFS('Rent Roll'!$K:$K,'Rent Roll'!$G:$G,'Unit Mix'!$E12,'Rent Roll'!$L:$L,"Admin",'Rent Roll'!$D:$D,'Unit Mix'!D12)+SUMIFS('Rent Roll'!$K:$K,'Rent Roll'!$G:$G,'Unit Mix'!$E12,'Rent Roll'!$L:$L,"Model",'Rent Roll'!$D:$D,'Unit Mix'!D12)+SUMIFS('Rent Roll'!$K:$K,'Rent Roll'!$G:$G,'Unit Mix'!$E12,'Rent Roll'!$L:$L,"Down",'Rent Roll'!$D:$D,'Unit Mix'!D12) -> 0 | AC12: {=INDEX('Lease Comps'!$I$10:$I$24,MATCH('Unit Mix'!AI12,'Lease Comps'!$A$10:$A$24,0)+1)} -> #DIV/0! | AH12: =IF(LEFT($E12,1)="1","1 Bedroom",IF(LEFT($E12,1)="2","2 Bedroom",IF(LEFT($E12,1)="3","3 Bedroom",IF(LEFT($E12,1)="4","4 Bedroom","Studio")))) -> Studio | AI12: =IF(LEFT($E12,1)="1","1BR",IF(LEFT($E12,1)="2","2BR",IF(LEFT($E12,1)="3","3BR",IF(LEFT($E12,1)="4","4BR","Studio")))) -> Studio
D13: =OneLineRR!B12 -> Hudson View Park | E13: =OneLineRR!C12 -> Studio - Large, Silver | F13: =COUNTIFS('Rent Roll'!$G:$G,'Unit Mix'!$E13,'Rent Roll'!$D:$D,'Unit Mix'!D13) -> 0 | G13: =SUMIFS('Rent Roll'!$K:$K,'Rent Roll'!$G:$G,'Unit Mix'!$E13,'Rent Roll'!$D:$D,'Unit Mix'!D13) -> 0 | H13: =G13/F13 -> #DIV/0! | I13: =SUMIFS('Rent Roll'!$M:$M,'Rent Roll'!$G:$G,'Unit Mix'!$E13,'Rent Roll'!$D:$D,'Unit Mix'!D13)+SUMIFS('Rent Roll'!$N:$N,'Rent Roll'!$G:$G,'Unit Mix'!$E13,'Rent Roll'!$D:$D,'Unit Mix'!D13) -> 0 | J13: =IFERROR(I13/F13,"") | K13: =IFERROR(J13/H13,"") | L13: =SUMIFS('Rent Roll'!$O:$O,'Rent Roll'!$G:$G,'Unit Mix'!$E13,'Rent Roll'!$D:$D,'Unit Mix'!D13) -> 0 | M13: =L13/F13 -> #DIV/0! | N13: =IFERROR(M13/H13,"") | O13: =P13*F13 -> #DIV/0! | P13: =MAX(M13,V13) -> #DIV/0! | Q13: =IFERROR(P13/H13,"") | R13: =S13*F13 -> #DIV/0! | S13: =IF($S$83=0,P13,ROUNDUP(P13*(1+$S$83),-2)) -> #DIV/0! | T13: =IFERROR(S13/H13,"") | U13: =_xlfn.MINIFS('Rent Roll'!$M:$M,'Rent Roll'!$G:$G,'Unit Mix'!E13,'Rent Roll'!$D:$D,'Unit Mix'!D13,'Rent Roll'!$J:$J,"<>Vacant",'Rent Roll'!$M:$M,">100") -> 0 | V13: =_xlfn.MAXIFS('Rent Roll'!$M:$M,'Rent Roll'!$G:$G,'Unit Mix'!E13,'Rent Roll'!$D:$D,'Unit Mix'!D13,'Rent Roll'!$J:$J,"<>Vacant") -> 0 | W13: =SUMIFS('Rent Roll'!$Q:$Q,'Rent Roll'!$G:$G,'Unit Mix'!$E13,'Rent Roll'!$D:$D,'Unit Mix'!D13) -> 0 | AA13: =COUNTIFS('Rent Roll'!$G:$G,'Unit Mix'!$E13,'Rent Roll'!$L:$L,"Occ",'Rent Roll'!$D:$D,'Unit Mix'!D13)+COUNTIFS('Rent Roll'!$G:$G,'Unit Mix'!$E13,'Rent Roll'!$L:$L,"Admin",'Rent Roll'!$D:$D,'Unit Mix'!D13)+COUNTIFS('Rent Roll'!$G:$G,'Unit Mix'!$E13,'Rent Roll'!$L:$L,"Model",'Rent Roll'!$D:$D,'Unit Mix'!D13)+COUNTIFS('Rent Roll'!$G:$G,'Unit Mix'!$E13,'Rent Roll'!$L:$L,"Down",'Rent Roll'!$D:$D,'Unit Mix'!D13) -> 0 | AB13: =SUMIFS('Rent Roll'!$K:$K,'Rent Roll'!$G:$G,'Unit Mix'!$E13,'Rent Roll'!$L:$L,"Occ",'Rent Roll'!$D:$D,'Unit Mix'!D13)+SUMIFS('Rent Roll'!$K:$K,'Rent Roll'!$G:$G,'Unit Mix'!$E13,'Rent Roll'!$L:$L,"Admin",'Rent Roll'!$D:$D,'Unit Mix'!D13)+SUMIFS('Rent Roll'!$K:$K,'Rent Roll'!$G:$G,'Unit Mix'!$E13,'Rent Roll'!$L:$L,"Model",'Rent Roll'!$D:$D,'Unit Mix'!D13)+SUMIFS('Rent Roll'!$K:$K,'Rent Roll'!$G:$G,'Unit Mix'!$E13,'Rent Roll'!$L:$L,"Down",'Rent Roll'!$D:$D,'Unit Mix'!D13) -> 0 | AC13: {=INDEX('Lease Comps'!$I$10:$I$24,MATCH('Unit Mix'!AI13,'Lease Comps'!$A$10:$A$24,0)+1)} -> #DIV/0! | AH13: =IF(LEFT($E13,1)="1","1 Bedroom",IF(LEFT($E13,1)="2","2 Bedroom",IF(LEFT($E13,1)="3","3 Bedroom",IF(LEFT($E13,1)="4","4 Bedroom","Studio")))) -> Studio | AI13: =IF(LEFT($E13,1)="1","1BR",IF(LEFT($E13,1)="2","2BR",IF(LEFT($E13,1)="3","3BR",IF(LEFT($E13,1)="4","4BR","Studio")))) -> Studio
D14: =OneLineRR!B13 -> Hudson View Park | E14: =OneLineRR!C13 -> 1BD - Small I, Gold | F14: =COUNTIFS('Rent Roll'!$G:$G,'Unit Mix'!$E14,'Rent Roll'!$D:$D,'Unit Mix'!D14) -> 0 | G14: =SUMIFS('Rent Roll'!$K:$K,'Rent Roll'!$G:$G,'Unit Mix'!$E14,'Rent Roll'!$D:$D,'Unit Mix'!D14) -> 0 | H14: =G14/F14 -> #DIV/0! | I14: =SUMIFS('Rent Roll'!$M:$M,'Rent Roll'!$G:$G,'Unit Mix'!$E14,'Rent Roll'!$D:$D,'Unit Mix'!D14)+SUMIFS('Rent Roll'!$N:$N,'Rent Roll'!$G:$G,'Unit Mix'!$E14,'Rent Roll'!$D:$D,'Unit Mix'!D14) -> 0 | J14: =IFERROR(I14/F14,"") | K14: =IFERROR(J14/H14,"") | L14: =SUMIFS('Rent Roll'!$O:$O,'Rent Roll'!$G:$G,'Unit Mix'!$E14,'Rent Roll'!$D:$D,'Unit Mix'!D14) -> 0 | M14: =L14/F14 -> #DIV/0! | N14: =IFERROR(M14/H14,"") | O14: =P14*F14 -> #DIV/0! | P14: =MAX(M14,V14) -> #DIV/0! | Q14: =IFERROR(P14/H14,"") | R14: =S14*F14 -> #DIV/0! | S14: =IF($S$83=0,P14,ROUNDUP(P14*(1+$S$83),-2)) -> #DIV/0! | T14: =IFERROR(S14/H14,"") | U14: =_xlfn.MINIFS('Rent Roll'!$M:$M,'Rent Roll'!$G:$G,'Unit Mix'!E14,'Rent Roll'!$D:$D,'Unit Mix'!D14,'Rent Roll'!$J:$J,"<>Vacant",'Rent Roll'!$M:$M,">100") -> 0 | V14: =_xlfn.MAXIFS('Rent Roll'!$M:$M,'Rent Roll'!$G:$G,'Unit Mix'!E14,'Rent Roll'!$D:$D,'Unit Mix'!D14,'Rent Roll'!$J:$J,"<>Vacant") -> 0 | W14: =SUMIFS('Rent Roll'!$Q:$Q,'Rent Roll'!$G:$G,'Unit Mix'!$E14,'Rent Roll'!$D:$D,'Unit Mix'!D14) -> 0 | AA14: =COUNTIFS('Rent Roll'!$G:$G,'Unit Mix'!$E14,'Rent Roll'!$L:$L,"Occ",'Rent Roll'!$D:$D,'Unit Mix'!D14)+COUNTIFS('Rent Roll'!$G:$G,'Unit Mix'!$E14,'Rent Roll'!$L:$L,"Admin",'Rent Roll'!$D:$D,'Unit Mix'!D14)+COUNTIFS('Rent Roll'!$G:$G,'Unit Mix'!$E14,'Rent Roll'!$L:$L,"Model",'Rent Roll'!$D:$D,'Unit Mix'!D14)+COUNTIFS('Rent Roll'!$G:$G,'Unit Mix'!$E14,'Rent Roll'!$L:$L,"Down",'Rent Roll'!$D:$D,'Unit Mix'!D14) -> 0 | AB14: =SUMIFS('Rent Roll'!$K:$K,'Rent Roll'!$G:$G,'Unit Mix'!$E14,'Rent Roll'!$L:$L,"Occ",'Rent Roll'!$D:$D,'Unit Mix'!D14)+SUMIFS('Rent Roll'!$K:$K,'Rent Roll'!$G:$G,'Unit Mix'!$E14,'Rent Roll'!$L:$L,"Admin",'Rent Roll'!$D:$D,'Unit Mix'!D14)+SUMIFS('Rent Roll'!$K:$K,'Rent Roll'!$G:$G,'Unit Mix'!$E14,'Rent Roll'!$L:$L,"Model",'Rent Roll'!$D:$D,'Unit Mix'!D14)+SUMIFS('Rent Roll'!$K:$K,'Rent Roll'!$G:$G,'Unit Mix'!$E14,'Rent Roll'!$L:$L,"Down",'Rent Roll'!$D:$D,'Unit Mix'!D14) -> 0 | AC14: {=INDEX('Lease Comps'!$I$10:$I$24,MATCH('Unit Mix'!AI14,'Lease Comps'!$A$10:$A$24,0)+1)} -> #DIV/0! | AH14: =IF(LEFT($E14,1)="1","1 Bedroom",IF(LEFT($E14,1)="2","2 Bedroom",IF(LEFT($E14,1)="3","3 Bedroom",IF(LEFT($E14,1)="4","4 Bedroom","Studio")))) -> 1 Bedroom | AI14: =IF(LEFT($E14,1)="1","1BR",IF(LEFT($E14,1)="2","2BR",IF(LEFT($E14,1)="3","3BR",IF(LEFT($E14,1)="4","4BR","Studio")))) -> 1BR
D15: =OneLineRR!B14 -> Hudson View Park | E15: =OneLineRR!C14 -> 1BD - Small I, Platinum | F15: =COUNTIFS('Rent Roll'!$G:$G,'Unit Mix'!$E15,'Rent Roll'!$D:$D,'Unit Mix'!D15) -> 0 | G15: =SUMIFS('Rent Roll'!$K:$K,'Rent Roll'!$G:$G,'Unit Mix'!$E15,'Rent Roll'!$D:$D,'Unit Mix'!D15) -> 0 | H15: =G15/F15 -> #DIV/0! | I15: =SUMIFS('Rent Roll'!$M:$M,'Rent Roll'!$G:$G,'Unit Mix'!$E15,'Rent Roll'!$D:$D,'Unit Mix'!D15)+SUMIFS('Rent Roll'!$N:$N,'Rent Roll'!$G:$G,'Unit Mix'!$E15,'Rent Roll'!$D:$D,'Unit Mix'!D15) -> 0 | J15: =IFERROR(I15/F15,"") | K15: =IFERROR(J15/H15,"") | L15: =SUMIFS('Rent Roll'!$O:$O,'Rent Roll'!$G:$G,'Unit Mix'!$E15,'Rent Roll'!$D:$D,'Unit Mix'!D15) -> 0 | M15: =L15/F15 -> #DIV/0! | N15: =IFERROR(M15/H15,"") | O15: =P15*F15 -> #DIV/0! | P15: =MAX(M15,V15) -> #DIV/0! | Q15: =IFERROR(P15/H15,"") | R15: =S15*F15 -> #DIV/0! | S15: =IF($S$83=0,P15,ROUNDUP(P15*(1+$S$83),-2)) -> #DIV/0! | T15: =IFERROR(S15/H15,"") | U15: =_xlfn.MINIFS('Rent Roll'!$M:$M,'Rent Roll'!$G:$G,'Unit Mix'!E15,'Rent Roll'!$D:$D,'Unit Mix'!D15,'Rent Roll'!$J:$J,"<>Vacant",'Rent Roll'!$M:$M,">100") -> 0 | V15: =_xlfn.MAXIFS('Rent Roll'!$M:$M,'Rent Roll'!$G:$G,'Unit Mix'!E15,'Rent Roll'!$D:$D,'Unit Mix'!D15,'Rent Roll'!$J:$J,"<>Vacant") -> 0 | W15: =SUMIFS('Rent Roll'!$Q:$Q,'Rent Roll'!$G:$G,'Unit Mix'!$E15,'Rent Roll'!$D:$D,'Unit Mix'!D15) -> 0 | AA15: =COUNTIFS('Rent Roll'!$G:$G,'Unit Mix'!$E15,'Rent Roll'!$L:$L,"Occ",'Rent Roll'!$D:$D,'Unit Mix'!D15)+COUNTIFS('Rent Roll'!$G:$G,'Unit Mix'!$E15,'Rent Roll'!$L:$L,"Admin",'Rent Roll'!$D:$D,'Unit Mix'!D15)+COUNTIFS('Rent Roll'!$G:$G,'Unit Mix'!$E15,'Rent Roll'!$L:$L,"Model",'Rent Roll'!$D:$D,'Unit Mix'!D15)+COUNTIFS('Rent Roll'!$G:$G,'Unit Mix'!$E15,'Rent Roll'!$L:$L,"Down",'Rent Roll'!$D:$D,'Unit Mix'!D15) -> 0 | AB15: =SUMIFS('Rent Roll'!$K:$K,'Rent Roll'!$G:$G,'Unit Mix'!$E15,'Rent Roll'!$L:$L,"Occ",'Rent Roll'!$D:$D,'Unit Mix'!D15)+SUMIFS('Rent Roll'!$K:$K,'Rent Roll'!$G:$G,'Unit Mix'!$E15,'Rent Roll'!$L:$L,"Admin",'Rent Roll'!$D:$D,'Unit Mix'!D15)+SUMIFS('Rent Roll'!$K:$K,'Rent Roll'!$G:$G,'Unit Mix'!$E15,'Rent Roll'!$L:$L,"Model",'Rent Roll'!$D:$D,'Unit Mix'!D15)+SUMIFS('Rent Roll'!$K:$K,'Rent Roll'!$G:$G,'Unit Mix'!$E15,'Rent Roll'!$L:$L,"Down",'Rent Roll'!$D:$D,'Unit Mix'!D15) -> 0 | AC15: {=INDEX('Lease Comps'!$I$10:$I$24,MATCH('Unit Mix'!AI15,'Lease Comps'!$A$10:$A$24,0)+1)} -> #DIV/0! | AH15: =IF(LEFT($E15,1)="1","1 Bedroom",IF(LEFT($E15,1)="2","2 Bedroom",IF(LEFT($E15,1)="3","3 Bedroom",IF(LEFT($E15,1)="4","4 Bedroom","Studio")))) -> 1 Bedroom | AI15: =IF(LEFT($E15,1)="1","1BR",IF(LEFT($E15,1)="2","2BR",IF(LEFT($E15,1)="3","3BR",IF(LEFT($E15,1)="4","4BR","Studio")))) -> 1BR
D16: =OneLineRR!B15 -> Hudson View Park | E16: =OneLineRR!C15 -> 1BD - Small II, Gold | F16: =COUNTIFS('Rent Roll'!$G:$G,'Unit Mix'!$E16,'Rent Roll'!$D:$D,'Unit Mix'!D16) -> 0 | G16: =SUMIFS('Rent Roll'!$K:$K,'Rent Roll'!$G:$G,'Unit Mix'!$E16,'Rent Roll'!$D:$D,'Unit Mix'!D16) -> 0 | H16: =G16/F16 -> #DIV/0! | I16: =SUMIFS('Rent Roll'!$M:$M,'Rent Roll'!$G:$G,'Unit Mix'!$E16,'Rent Roll'!$D:$D,'Unit Mix'!D16)+SUMIFS('Rent Roll'!$N:$N,'Rent Roll'!$G:$G,'Unit Mix'!$E16,'Rent Roll'!$D:$D,'Unit Mix'!D16) -> 0 | J16: =IFERROR(I16/F16,"") | K16: =IFERROR(J16/H16,"") | L16: =SUMIFS('Rent Roll'!$O:$O,'Rent Roll'!$G:$G,'Unit Mix'!$E16,'Rent Roll'!$D:$D,'Unit Mix'!D16) -> 0 | M16: =L16/F16 -> #DIV/0! | N16: =IFERROR(M16/H16,"") | O16: =P16*F16 -> #DIV/0! | P16: =MAX(M16,V16) -> #DIV/0! | Q16: =IFERROR(P16/H16,"") | R16: =S16*F16 -> #DIV/0! | S16: =IF($S$83=0,P16,ROUNDUP(P16*(1+$S$83),-2)) -> #DIV/0! | T16: =IFERROR(S16/H16,"") | U16: =_xlfn.MINIFS('Rent Roll'!$M:$M,'Rent Roll'!$G:$G,'Unit Mix'!E16,'Rent Roll'!$D:$D,'Unit Mix'!D16,'Rent Roll'!$J:$J,"<>Vacant",'Rent Roll'!$M:$M,">100") -> 0 | V16: =_xlfn.MAXIFS('Rent Roll'!$M:$M,'Rent Roll'!$G:$G,'Unit Mix'!E16,'Rent Roll'!$D:$D,'Unit Mix'!D16,'Rent Roll'!$J:$J,"<>Vacant") -> 0 | W16: =SUMIFS('Rent Roll'!$Q:$Q,'Rent Roll'!$G:$G,'Unit Mix'!$E16,'Rent Roll'!$D:$D,'Unit Mix'!D16) -> 0 | AA16: =COUNTIFS('Rent Roll'!$G:$G,'Unit Mix'!$E16,'Rent Roll'!$L:$L,"Occ",'Rent Roll'!$D:$D,'Unit Mix'!D16)+COUNTIFS('Rent Roll'!$G:$G,'Unit Mix'!$E16,'Rent Roll'!$L:$L,"Admin",'Rent Roll'!$D:$D,'Unit Mix'!D16)+COUNTIFS('Rent Roll'!$G:$G,'Unit Mix'!$E16,'Rent Roll'!$L:$L,"Model",'Rent Roll'!$D:$D,'Unit Mix'!D16)+COUNTIFS('Rent Roll'!$G:$G,'Unit Mix'!$E16,'Rent Roll'!$L:$L,"Down",'Rent Roll'!$D:$D,'Unit Mix'!D16) -> 0 | AB16: =SUMIFS('Rent Roll'!$K:$K,'Rent Roll'!$G:$G,'Unit Mix'!$E16,'Rent Roll'!$L:$L,"Occ",'Rent Roll'!$D:$D,'Unit Mix'!D16)+SUMIFS('Rent Roll'!$K:$K,'Rent Roll'!$G:$G,'Unit Mix'!$E16,'Rent Roll'!$L:$L,"Admin",'Rent Roll'!$D:$D,'Unit Mix'!D16)+SUMIFS('Rent Roll'!$K:$K,'Rent Roll'!$G:$G,'Unit Mix'!$E16,'Rent Roll'!$L:$L,"Model",'Rent Roll'!$D:$D,'Unit Mix'!D16)+SUMIFS('Rent Roll'!$K:$K,'Rent Roll'!$G:$G,'Unit Mix'!$E16,'Rent Roll'!$L:$L,"Down",'Rent Roll'!$D:$D,'Unit Mix'!D16) -> 0 | AC16: {=INDEX('Lease Comps'!$I$10:$I$24,MATCH('Unit Mix'!AI16,'Lease Comps'!$A$10:$A$24,0)+1)} -> #DIV/0! | AH16: =IF(LEFT($E16,1)="1","1 Bedroom",IF(LEFT($E16,1)="2","2 Bedroom",IF(LEFT($E16,1)="3","3 Bedroom",IF(LEFT($E16,1)="4","4 Bedroom","Studio")))) -> 1 Bedroom | AI16: =IF(LEFT($E16,1)="1","1BR",IF(LEFT($E16,1)="2","2BR",IF(LEFT($E16,1)="3","3BR",IF(LEFT($E16,1)="4","4BR","Studio")))) -> 1BR
D17: =OneLineRR!B16 -> Hudson View Park | E17: =OneLineRR!C16 -> 1BD - Small II, Platinum | F17: =COUNTIFS('Rent Roll'!$G:$G,'Unit Mix'!$E17,'Rent Roll'!$D:$D,'Unit Mix'!D17) -> 0 | G17: =SUMIFS('Rent Roll'!$K:$K,'Rent Roll'!$G:$G,'Unit Mix'!$E17,'Rent Roll'!$D:$D,'Unit Mix'!D17) -> 0 | H17: =G17/F17 -> #DIV/0! | I17: =SUMIFS('Rent Roll'!$M:$M,'Rent Roll'!$G:$G,'Unit Mix'!$E17,'Rent Roll'!$D:$D,'Unit Mix'!D17)+SUMIFS('Rent Roll'!$N:$N,'Rent Roll'!$G:$G,'Unit Mix'!$E17,'Rent Roll'!$D:$D,'Unit Mix'!D17) -> 0 | J17: =IFERROR(I17/F17,"") | K17: =IFERROR(J17/H17,"") | L17: =SUMIFS('Rent Roll'!$O:$O,'Rent Roll'!$G:$G,'Unit Mix'!$E17,'Rent Roll'!$D:$D,'Unit Mix'!D17) -> 0 | M17: =L17/F17 -> #DIV/0! | N17: =IFERROR(M17/H17,"") | O17: =P17*F17 -> #DIV/0! | P17: =MAX(M17,V17) -> #DIV/0! | Q17: =IFERROR(P17/H17,"") | R17: =S17*F17 -> #DIV/0! | S17: =IF($S$83=0,P17,ROUNDUP(P17*(1+$S$83),-2)) -> #DIV/0! | T17: =IFERROR(S17/H17,"") | U17: =_xlfn.MINIFS('Rent Roll'!$M:$M,'Rent Roll'!$G:$G,'Unit Mix'!E17,'Rent Roll'!$D:$D,'Unit Mix'!D17,'Rent Roll'!$J:$J,"<>Vacant",'Rent Roll'!$M:$M,">100") -> 0 | V17: =_xlfn.MAXIFS('Rent Roll'!$M:$M,'Rent Roll'!$G:$G,'Unit Mix'!E17,'Rent Roll'!$D:$D,'Unit Mix'!D17,'Rent Roll'!$J:$J,"<>Vacant") -> 0 | W17: =SUMIFS('Rent Roll'!$Q:$Q,'Rent Roll'!$G:$G,'Unit Mix'!$E17,'Rent Roll'!$D:$D,'Unit Mix'!D17) -> 0 | AA17: =COUNTIFS('Rent Roll'!$G:$G,'Unit Mix'!$E17,'Rent Roll'!$L:$L,"Occ",'Rent Roll'!$D:$D,'Unit Mix'!D17)+COUNTIFS('Rent Roll'!$G:$G,'Unit Mix'!$E17,'Rent Roll'!$L:$L,"Admin",'Rent Roll'!$D:$D,'Unit Mix'!D17)+COUNTIFS('Rent Roll'!$G:$G,'Unit Mix'!$E17,'Rent Roll'!$L:$L,"Model",'Rent Roll'!$D:$D,'Unit Mix'!D17)+COUNTIFS('Rent Roll'!$G:$G,'Unit Mix'!$E17,'Rent Roll'!$L:$L,"Down",'Rent Roll'!$D:$D,'Unit Mix'!D17) -> 0 | AB17: =SUMIFS('Rent Roll'!$K:$K,'Rent Roll'!$G:$G,'Unit Mix'!$E17,'Rent Roll'!$L:$L,"Occ",'Rent Roll'!$D:$D,'Unit Mix'!D17)+SUMIFS('Rent Roll'!$K:$K,'Rent Roll'!$G:$G,'Unit Mix'!$E17,'Rent Roll'!$L:$L,"Admin",'Rent Roll'!$D:$D,'Unit Mix'!D17)+SUMIFS('Rent Roll'!$K:$K,'Rent Roll'!$G:$G,'Unit Mix'!$E17,'Rent Roll'!$L:$L,"Model",'Rent Roll'!$D:$D,'Unit Mix'!D17)+SUMIFS('Rent Roll'!$K:$K,'Rent Roll'!$G:$G,'Unit Mix'!$E17,'Rent Roll'!$L:$L,"Down",'Rent Roll'!$D:$D,'Unit Mix'!D17) -> 0 | AC17: {=INDEX('Lease Comps'!$I$10:$I$24,MATCH('Unit Mix'!AI17,'Lease Comps'!$A$10:$A$24,0)+1)} -> #DIV/0! | AH17: =IF(LEFT($E17,1)="1","1 Bedroom",IF(LEFT($E17,1)="2","2 Bedroom",IF(LEFT($E17,1)="3","3 Bedroom",IF(LEFT($E17,1)="4","4 Bedroom","Studio")))) -> 1 Bedroom | AI17: =IF(LEFT($E17,1)="1","1BR",IF(LEFT($E17,1)="2","2BR",IF(LEFT($E17,1)="3","3BR",IF(LEFT($E17,1)="4","4BR","Studio")))) -> 1BR
... D62: =OneLineRR!B61 -> Hudson View Park | E62: =OneLineRR!C61 -> 4BD - HalfMoon 8, Gold | F62: =COUNTIFS('Rent Roll'!$G:$G,'Unit Mix'!$E62,'Rent Roll'!$D:$D,'Unit Mix'!D62) -> 0 | G62: =SUMIFS('Rent Roll'!$K:$K,'Rent Roll'!$G:$G,'Unit Mix'!$E62,'Rent Roll'!$D:$D,'Unit Mix'!D62) -> 0 | H62: =G62/F62 -> #DIV/0! | I62: =SUMIFS('Rent Roll'!$M:$M,'Rent Roll'!$G:$G,'Unit Mix'!$E62,'Rent Roll'!$D:$D,'Unit Mix'!D62)+SUMIFS('Rent Roll'!$N:$N,'Rent Roll'!$G:$G,'Unit Mix'!$E62,'Rent Roll'!$D:$D,'Unit Mix'!D62) -> 0 | J62: =IFERROR(I62/F62,"") | K62: =IFERROR(J62/H62,"") | L62: =SUMIFS('Rent Roll'!$O:$O,'Rent Roll'!$G:$G,'Unit Mix'!$E62,'Rent Roll'!$D:$D,'Unit Mix'!D62) -> 0 | M62: =L62/F62 -> #DIV/0! | N62: =IFERROR(M62/H62,"") | O62: =P62*F62 -> #DIV/0! | P62: =MAX(M62,V62) -> #DIV/0! | Q62: =IFERROR(P62/H62,"") | R62: =S62*F62 -> #DIV/0! | S62: =IF($S$83=0,P62,ROUNDUP(P62*(1+$S$83),-2)) -> #DIV/0! | T62: =IFERROR(S62/H62,"") | U62: =_xlfn.MINIFS('Rent Roll'!$M:$M,'Rent Roll'!$G:$G,'Unit Mix'!E62,'Rent Roll'!$D:$D,'Unit Mix'!D62,'Rent Roll'!$J:$J,"<>Vacant",'Rent Roll'!$M:$M,">100") -> 0 | V62: =_xlfn.MAXIFS('Rent Roll'!$M:$M,'Rent Roll'!$G:$G,'Unit Mix'!E62,'Rent Roll'!$D:$D,'Unit Mix'!D62,'Rent Roll'!$J:$J,"<>Vacant") -> 0 | W62: =SUMIFS('Rent Roll'!$Q:$Q,'Rent Roll'!$G:$G,'Unit Mix'!$E62,'Rent Roll'!$D:$D,'Unit Mix'!D62) -> 0 | AA62: =COUNTIFS('Rent Roll'!$G:$G,'Unit Mix'!$E62,'Rent Roll'!$L:$L,"Occ",'Rent Roll'!$D:$D,'Unit Mix'!D62)+COUNTIFS('Rent Roll'!$G:$G,'Unit Mix'!$E62,'Rent Roll'!$L:$L,"Admin",'Rent Roll'!$D:$D,'Unit Mix'!D62)+COUNTIFS('Rent Roll'!$G:$G,'Unit Mix'!$E62,'Rent Roll'!$L:$L,"Model",'Rent Roll'!$D:$D,'Unit Mix'!D62)+COUNTIFS('Rent Roll'!$G:$G,'Unit Mix'!$E62,'Rent Roll'!$L:$L,"Down",'Rent Roll'!$D:$D,'Unit Mix'!D62) -> 0 | AB62: =SUMIFS('Rent Roll'!$K:$K,'Rent Roll'!$G:$G,'Unit Mix'!$E62,'Rent Roll'!$L:$L,"Occ",'Rent Roll'!$D:$D,'Unit Mix'!D62)+SUMIFS('Rent Roll'!$K:$K,'Rent Roll'!$G:$G,'Unit Mix'!$E62,'Rent Roll'!$L:$L,"Admin",'Rent Roll'!$D:$D,'Unit Mix'!D62)+SUMIFS('Rent Roll'!$K:$K,'Rent Roll'!$G:$G,'Unit Mix'!$E62,'Rent Roll'!$L:$L,"Model",'Rent Roll'!$D:$D,'Unit Mix'!D62)+SUMIFS('Rent Roll'!$K:$K,'Rent Roll'!$G:$G,'Unit Mix'!$E62,'Rent Roll'!$L:$L,"Down",'Rent Roll'!$D:$D,'Unit Mix'!D62) -> 0 | AC62: {=INDEX('Lease Comps'!$I$10:$I$24,MATCH('Unit Mix'!AI62,'Lease Comps'!$A$10:$A$24,0)+1)} -> #DIV/0! | AH62: =IF(LEFT($E62,1)="1","1 Bedroom",IF(LEFT($E62,1)="2","2 Bedroom",IF(LEFT($E62,1)="3","3 Bedroom",IF(LEFT($E62,1)="4","4 Bedroom","Studio")))) -> 4 Bedroom | AI62: =IF(LEFT($E62,1)="1","1BR",IF(LEFT($E62,1)="2","2BR",IF(LEFT($E62,1)="3","3BR",IF(LEFT($E62,1)="4","4BR","Studio")))) -> 4BR
C63: Total/Wtd Average | F63: =SUM(F6:F62) -> 0 | G63: =SUM(G6:G62) -> 0 | H63: =SUMPRODUCT(H6:H62,F6:F62)/$F$63 -> #DIV/0! | I63: =SUM(I6:I62) -> 0 | J63: =SUMPRODUCT(J6:J62,$F$6:$F$62)/$F$63 -> #DIV/0! | K63: =SUMPRODUCT(K6:K62,$G$6:$G$62)/G63 -> #DIV/0! | L63: =SUM(L6:L62) -> 0 | M63: =SUMPRODUCT(M6:M62,$F$6:$F$62)/$F$63 -> #DIV/0! | N63: =SUMPRODUCT(N6:N62,$G$6:$G$62)/$G$63 -> #DIV/0! | O63: =SUM(O6:O62) -> #DIV/0! | P63: =SUMPRODUCT(P6:P62,$F$6:$F$62)/$F$63 -> #DIV/0! | Q63: =SUMPRODUCT(Q6:Q62,$G$6:$G$62)/$G$63 -> #DIV/0! | R63: =SUM(R6:R62) -> #DIV/0! | S63: =SUMPRODUCT(S6:S62,$F$6:$F$62)/$F$63 -> #DIV/0! | T63: =SUMPRODUCT(T6:T62,$G$6:$G$62)/G63 -> #DIV/0! | U63: =SUMPRODUCT(U6:U62,$F$6:$F$62)/$F$63 -> #DIV/0! | V63: =SUMPRODUCT(V6:V62,$F$6:$F$62)/$F$63 -> #DIV/0! | W63: =SUM(W6:W62) -> 0 | AA63: =SUM(AA6:AA62) -> 0 | AB63: =SUM(AB6:AB62) -> 0
D64: =IF(OneLineRR!C67="","",OneLineRR!C67) -> Hudson View Park | F64: =SUMIF($D$6:$D$62,$D64,$F$6:$F$62) -> 0 | G64: =SUMIF($D$6:$D$62,$D64,$G$6:$G$62) -> 0 | H64: {=IFERROR(SUMPRODUCT(--($D$6:$D$62=$D64),$H$6:$H$62,$F$6:$F$62)/$F64,"")} | I64: =SUMIF($D$6:$D$62,$D64,$I$6:$I$62) -> 0 | J64: {=SUMPRODUCT(--($D$6:$D$62=$D64),$J$6:$J$62,$F$6:$F$62)/$F64} -> #DIV/0! | K64: {=IFERROR(SUMPRODUCT(--($D$6:$D$62=$D64),$K$6:$K$62,$G$6:$G$62)/$G64,"")} | L64: =SUMIF($D$6:$D$62,$D64,$L$6:$L$62) -> 0 | M64: {=SUMPRODUCT(--($D$6:$D$62=$D64),$M$6:$M$62,$F$6:$F$62)/$F64} -> #DIV/0! | N64: {=IFERROR(SUMPRODUCT(--($D$6:$D$62=$D64),$N$6:$N$62,$G$6:$G$62)/$G64,"")} | O64: =SUMIF($D$6:$D$62,$D64,$O$6:$O$62) -> #DIV/0! | P64: {=SUMPRODUCT(--($D$6:$D$62=$D64),$P$6:$P$62,$F$6:$F$62)/$F64} -> #DIV/0! | Q64: {=SUMPRODUCT(--($D$6:$D$62=$D64),$Q$6:$Q$62,$G$6:$G$62)/$G64} -> #DIV/0! | R64: =SUMIF($D$6:$D$62,$D64,$R$6:$R$62) -> #DIV/0! | S64: {=SUMPRODUCT(--($D$6:$D$62=$D64),$S$6:$S$62,$F$6:$F$62)/$F64} -> #DIV/0! | T64: {=IFERROR(SUMPRODUCT(--($D$6:$D$62=$D64),$T$6:$T$62,$G$6:$G$62)/$G64,"")} | U64: {=SUMPRODUCT(--($D$6:$D$62=$D64),$U$6:$U$62,$F$6:$F$62)/$F64} -> #DIV/0! | V64: {=SUMPRODUCT(--($D$6:$D$62=$D64),$V$6:$V$62,$F$6:$F$62)/$F64} -> #DIV/0! | AA64: =SUMIF($D$6:$D$62,$D64,$AA$6:$AA$62) -> 0 | AB64: =SUMIF($D$6:$D$62,$D64,$AB$6:$AB$62) -> 0
D65: =IF(OneLineRR!C72="","",OneLineRR!C72) -> [Property 2 Name] | F65: =SUMIF($D$6:$D$62,$D65,$F$6:$F$62) -> 0 | G65: =SUMIF($D$6:$D$62,$D65,$G$6:$G$62) -> 0 | H65: {=IFERROR(SUMPRODUCT(--($D$6:$D$62=$D65),$H$6:$H$62,$F$6:$F$62)/$F65,"")} | I65: =SUMIF($D$6:$D$62,$D65,$I$6:$I$62) -> 0 | J65: {=SUMPRODUCT(--($D$6:$D$62=$D65),$J$6:$J$62,$F$6:$F$62)/$F65} -> #DIV/0! | K65: {=IFERROR(SUMPRODUCT(--($D$6:$D$62=$D65),$K$6:$K$62,$G$6:$G$62)/$G65,"")} | L65: =SUMIF($D$6:$D$62,$D65,$L$6:$L$62) -> 0 | M65: {=SUMPRODUCT(--($D$6:$D$62=$D65),$M$6:$M$62,$F$6:$F$62)/$F65} -> #DIV/0! | N65: {=IFERROR(SUMPRODUCT(--($D$6:$D$62=$D65),$N$6:$N$62,$G$6:$G$62)/$G65,"")} | O65: =SUMIF($D$6:$D$62,$D65,$O$6:$O$62) -> 0 | P65: {=SUMPRODUCT(--($D$6:$D$62=$D65),$P$6:$P$62,$F$6:$F$62)/$F65} -> #DIV/0! | Q65: {=SUMPRODUCT(--($D$6:$D$62=$D65),$Q$6:$Q$62,$G$6:$G$62)/$G65} -> #DIV/0! | R65: =SUMIF($D$6:$D$62,$D65,$R$6:$R$62) -> 0 | S65: {=SUMPRODUCT(--($D$6:$D$62=$D65),$S$6:$S$62,$F$6:$F$62)/$F65} -> #DIV/0! | T65: {=IFERROR(SUMPRODUCT(--($D$6:$D$62=$D65),$T$6:$T$62,$G$6:$G$62)/$G65,"")} | U65: {=SUMPRODUCT(--($D$6:$D$62=$D65),$U$6:$U$62,$F$6:$F$62)/$F65} -> #DIV/0! | V65: {=SUMPRODUCT(--($D$6:$D$62=$D65),$V$6:$V$62,$F$6:$F$62)/$F65} -> #DIV/0! | AA65: =SUMIF($D$6:$D$62,$D65,$AA$6:$AA$62) -> 0 | AB65: =SUMIF($D$6:$D$62,$D65,$AB$6:$AB$62) -> 0
D66: =IF(OneLineRR!C77="","",OneLineRR!C77) -> [Property 3 Name] | F66: =SUMIF($D$6:$D$6,$D66,$F$6:$F$6) -> 0 | G66: =SUMIF($D$6:$D$6,$D66,$G$6:$G$6) -> 0 | H66: {=IFERROR(SUMPRODUCT(--($D$6:$D$62=$D66),$H$6:$H$62,$F$6:$F$62)/$F66,"")} | I66: =SUMIF($D$6:$D$6,$D66,$I$6:$I$6) -> 0 | J66: {=SUMPRODUCT(--($D$6:$D$62=$D66),$J$6:$J$62,$F$6:$F$62)/$F66} -> #DIV/0! | K66: {=IFERROR(SUMPRODUCT(--($D$6:$D$62=$D66),$K$6:$K$62,$G$6:$G$62)/$G66,"")} | L66: =SUMIF($D$6:$D$62,$D66,$L$6:$L$62) -> 0 | M66: {=SUMPRODUCT(--($D$6:$D$62=$D66),$M$6:$M$62,$F$6:$F$62)/$F66} -> #DIV/0! | N66: {=IFERROR(SUMPRODUCT(--($D$6:$D$62=$D66),$N$6:$N$62,$G$6:$G$62)/$G66,"")} | O66: =SUMIF($D$6:$D$62,$D66,$O$6:$O$62) -> 0 | P66: {=SUMPRODUCT(--($D$6:$D$62=$D66),$P$6:$P$62,$F$6:$F$62)/$F66} -> #DIV/0! | Q66: {=SUMPRODUCT(--($D$6:$D$62=$D66),$Q$6:$Q$62,$G$6:$G$62)/$G66} -> #DIV/0! | R66: =SUMIF($D$6:$D$62,$D66,$R$6:$R$62) -> 0 | S66: {=SUMPRODUCT(--($D$6:$D$62=$D66),$S$6:$S$62,$F$6:$F$62)/$F66} -> #DIV/0! | T66: {=IFERROR(SUMPRODUCT(--($D$6:$D$62=$D66),$T$6:$T$62,$G$6:$G$62)/$G66,"")} | U66: {=SUMPRODUCT(--($D$6:$D$62=$D66),$U$6:$U$62,$F$6:$F$62)/$F66} -> #DIV/0! | V66: {=SUMPRODUCT(--($D$6:$D$62=$D66),$V$6:$V$62,$F$6:$F$62)/$F66} -> #DIV/0! | AA66: =SUMIF($D$6:$D$6,$D66,$AA$6:$AA$6) -> 0 | AB66: =SUMIF($D$6:$D$6,$D66,$AB$6:$AB$6) -> 0
D67: =IF(OneLineRR!C82="","",OneLineRR!C82) -> [Property 4 Name] | F67: =SUMIF($D$6:$D$6,$D67,$F$6:$F$6) -> 0 | G67: =SUMIF($D$6:$D$6,$D67,$G$6:$G$6) -> 0 | H67: {=IFERROR(SUMPRODUCT(--($D$6:$D$62=$D67),$H$6:$H$62,$F$6:$F$62)/$F67,"")} | I67: =SUMIF($D$6:$D$6,$D67,$I$6:$I$6) -> 0 | J67: {=SUMPRODUCT(--($D$6:$D$62=$D67),$J$6:$J$62,$F$6:$F$62)/$F67} -> #DIV/0! | K67: {=IFERROR(SUMPRODUCT(--($D$6:$D$62=$D67),$K$6:$K$62,$G$6:$G$62)/$G67,"")} | L67: =SUMIF($D$6:$D$62,$D67,$L$6:$L$62) -> 0 | M67: {=SUMPRODUCT(--($D$6:$D$62=$D67),$M$6:$M$62,$F$6:$F$62)/$F67} -> #DIV/0! | N67: {=IFERROR(SUMPRODUCT(--($D$6:$D$62=$D67),$N$6:$N$62,$G$6:$G$62)/$G67,"")} | O67: =SUMIF($D$6:$D$62,$D67,$O$6:$O$62) -> 0 | P67: {=SUMPRODUCT(--($D$6:$D$62=$D67),$P$6:$P$62,$F$6:$F$62)/$F67} -> #DIV/0! | Q67: {=SUMPRODUCT(--($D$6:$D$62=$D67),$Q$6:$Q$62,$G$6:$G$62)/$G67} -> #DIV/0! | R67: =SUMIF($D$6:$D$62,$D67,$R$6:$R$62) -> 0 | S67: {=SUMPRODUCT(--($D$6:$D$62=$D67),$S$6:$S$62,$F$6:$F$62)/$F67} -> #DIV/0! | T67: {=IFERROR(SUMPRODUCT(--($D$6:$D$62=$D67),$T$6:$T$62,$G$6:$G$62)/$G67,"")} | U67: {=SUMPRODUCT(--($D$6:$D$62=$D67),$U$6:$U$62,$F$6:$F$62)/$F67} -> #DIV/0! | V67: {=SUMPRODUCT(--($D$6:$D$62=$D67),$V$6:$V$62,$F$6:$F$62)/$F67} -> #DIV/0! | AA67: =SUMIF($D$6:$D$6,$D67,$AA$6:$AA$6) -> 0 | AB67: =SUMIF($D$6:$D$6,$D67,$AB$6:$AB$6) -> 0
D68: =IF(OneLineRR!C87="","",OneLineRR!C87) -> [Property 5 Name] | F68: =SUMIF($D$6:$D$6,$D68,$F$6:$F$6) -> 0 | G68: =SUMIF($D$6:$D$6,$D68,$G$6:$G$6) -> 0 | H68: {=IFERROR(SUMPRODUCT(--($D$6:$D$62=$D68),$H$6:$H$62,$F$6:$F$62)/$F68,"")} | I68: =SUMIF($D$6:$D$6,$D68,$I$6:$I$6) -> 0 | J68: {=SUMPRODUCT(--($D$6:$D$62=$D68),$J$6:$J$62,$F$6:$F$62)/$F68} -> #DIV/0! | K68: {=IFERROR(SUMPRODUCT(--($D$6:$D$62=$D68),$K$6:$K$62,$G$6:$G$62)/$G68,"")} | L68: =SUMIF($D$6:$D$62,$D68,$L$6:$L$62) -> 0 | M68: {=SUMPRODUCT(--($D$6:$D$62=$D68),$M$6:$M$62,$F$6:$F$62)/$F68} -> #DIV/0! | N68: {=IFERROR(SUMPRODUCT(--($D$6:$D$62=$D68),$N$6:$N$62,$G$6:$G$62)/$G68,"")} | O68: =SUMIF($D$6:$D$62,$D68,$O$6:$O$62) -> 0 | P68: {=SUMPRODUCT(--($D$6:$D$62=$D68),$P$6:$P$62,$F$6:$F$62)/$F68} -> #DIV/0! | Q68: {=SUMPRODUCT(--($D$6:$D$62=$D68),$Q$6:$Q$62,$G$6:$G$62)/$G68} -> #DIV/0! | R68: =SUMIF($D$6:$D$62,$D68,$R$6:$R$62) -> 0 | S68: {=SUMPRODUCT(--($D$6:$D$62=$D68),$S$6:$S$62,$F$6:$F$62)/$F68} -> #DIV/0! | T68: {=IFERROR(SUMPRODUCT(--($D$6:$D$62=$D68),$T$6:$T$62,$G$6:$G$62)/$G68,"")} | U68: {=SUMPRODUCT(--($D$6:$D$62=$D68),$U$6:$U$62,$F$6:$F$62)/$F68} -> #DIV/0! | V68: {=SUMPRODUCT(--($D$6:$D$62=$D68),$V$6:$V$62,$F$6:$F$62)/$F68} -> #DIV/0! | AA68: =SUMIF($D$6:$D$6,$D68,$AA$6:$AA$6) -> 0 | AB68: =SUMIF($D$6:$D$6,$D68,$AB$6:$AB$6) -> 0
C70: Total Units | G70: =$F$63 -> 0
C71: Occupied Units | G71: =$AA$63 -> 0
C72: Unit Occupancy | G72: =$AA$63/$F$63 -> #DIV/0!
C74: Total Square Feet | G74: =$G$63 -> 0
C75: Occupied Square Feet | G75: =$AB$63 -> 0
C76: Square Feet Occupancy | G76: =$AB$63/$G$63 -> #DIV/0!
C78: RR Market Rent Annualized | G78: =$L$63*12 -> 0
C79: Market Rent Annualized | G79: =O63*12 -> #DIV/0!
C80: In-Place Rent Annualized | G80: =$I$63*12 -> 0
C81: Other Income Annualized | G81: =IFERROR($W$63*12,"n/a") -> 0
F83: =F63=AD101 -> TRUE | G83: =G63=AD104 -> TRUE | I83: =I63=AD108 -> TRUE | L83: =L63=AD107 -> TRUE | S83: 0 | W83: =W63=AD110 -> TRUE | AA83: =AA63=$AD$102 -> TRUE | AB83: =AB63=AD105 -> TRUE
F84: =G72=$AD$103 -> #DIV/0! | G84: =SUM(F64:F68)=F63 -> TRUE | I84: =SUM(I64:I68)=I63 -> TRUE | L84: =SUM(L64:L68)=L63 -> TRUE | R84: =SUM(R64:R68)=R63 -> #DIV/0! | AA84: =SUM(AA64:AA68)=AA63 -> TRUE | AB84: =SUM(AB64:AB68)=AB63 -> TRUE
F85: =IFERROR(G76=$AD$106,"") | G85: =SUM(G64:G68)=G63 -> TRUE
AC100: Links from source data:
AC101: Total # units | AD101: ='Rent Roll'!$AG$526 -> 0
AC102: Occ Units | AD102: ='Rent Roll'!$AG$527 -> 0
AC103: Unit %Occ | AD103: ='Rent Roll'!$AG$528 -> #DIV/0!
AC104: Net Sq Ft | AD104: ='Rent Roll'!$AG$529 -> 0
AC105: SF Occ | AD105: ='Rent Roll'!$AG$530 -> 0
AC106: % SF Occ | AD106: ='Rent Roll'!$AG$531 -> #DIV/0!
AC107: Mkt Rent | AD107: ='Rent Roll'!$AG$532 -> 0
AC108: Cont Rent | AD108: ='Rent Roll'!M516+'Rent Roll'!N516 -> 0
AC109: Conc | AD109: ='Rent Roll'!$AG$535 -> 0
AC110: Other Inc | AD110: ='Rent Roll'!$AG$534 -> 0

Sheet Exhibits-->

Sheet Tax-Assessor Info
C3: ="PROPERTY TAX INFORMATION ("&$T$3&")" -> PROPERTY TAX INFORMATION (2025) | P3: ='Exec Summ'!F6 -> Hudson View Park | S3: Year Available | T3: 2025
D4: If deal is not portfolio, no need to fill out the property level tax info grouped rows [delete this comment and the grouped rows]
D5: Street Address | E5: Owner | F5: City | G5: Parcel ID | H5: Units | I5: Site Size | J5: Year Built | K5: Improved Value | L5: Land Value | M5: Market Value | N5: Annual Tax | O5: Eff. Tax Rate | P5: Link to Source Info | S5: Tax Link Info: | T5: Property:
D6: =D25 -> 0 | E6: =E25 -> 0 | F6: =F25 -> 0 | G6: =G25 -> 0 | H6: =H25 -> 0 | I6: =I25 -> 0 | J6: =J25 -> 0 | K6: =K25 -> 0 | L6: =L25 -> 0 | M6: =SUM(K6:L6) -> 0 | N6: =N25 -> 0 | O6: =N6/M6 -> #DIV/0! | T6: =$P$22 -> Hudson View Park
D7: =D26 -> 0 | E7: =E26 -> 0 | F7: =F26 -> 0 | G7: =G26 -> 0 | H7: =H26 -> 0 | I7: =I26 -> 0 | J7: =J26 -> 0 | K7: =K26 -> 0 | L7: =L26 -> 0 | M7: =SUM(K7:L7) -> 0 | N7: =N26 -> 0 | O7: =N7/M7 -> #DIV/0! | T7: =$P$22 -> Hudson View Park
D8: Property Total | I8: =SUM(I6:I7) -> 0 | K8: =SUM(K6:K7) -> 0 | L8: =SUM(L6:L7) -> 0 | M8: =SUM(M6:M7) -> 0 | N8: =SUM(N6:N7) -> 0 | O8: =IFERROR(N8/M8,"n/a") -> n/a
D10: Estimated Taxes Based on Purchase Price | H10: Transfer/Sales History | K10: delete this table if portfolio | M10: Historical Tax Summary
D11: Purchase Price | F11: ='Exec Summ'!G19 -> #DIV/0! | H11: Most Recent Transfer Date | K11: n/a | M11: Tax Year | N11: Market Value | O11: Annual Tax | P11: Eff. Tax Rate
D12: 1 | F12: =F11*$D$12 -> #DIV/0! | H12: Grantor/Seller | K12: n/a | M12: =$T$3-3 -> 2022 | N12: =IFERROR(N31+N47,"n/a") -> 0 | O12: =IFERROR(O31+O47,"n/a") -> 0 | P12: =IFERROR(O12/N12,"n/a") -> n/a
D13: Special Assessments | F13: 0 | H13: Grantee/Buyer | K13: n/a | M13: =M12+1 -> 2023 | N13: =N32+N48 -> 0 | O13: =O32+O48 -> 0 | P13: =IFERROR(O13/N13,"n/a") -> n/a
D14: Potential Tax Liability | F14: =(F12*P15)+F13 -> #DIV/0! | H14: Amount of Sale | K14: n/a | M14: =M13+1 -> 2024 | N14: =N33+N49 -> 0 | O14: =O33+O49 -> 0 | P14: =IFERROR(O14/N14,"n/a") -> n/a
H15: Previous Transfer Date | K15: n/a | M15: =M14+1 -> 2025 | N15: =M8 -> 0 | O15: =N8 -> 0 | P15: =IFERROR(O15/N15,"n/a") -> n/a
D16: County | E16: Dutchess, NY | H16: Grantor/Seller | K16: n/a | M16: Last 4 Quarters | N16: 2025 Q3 - 2026 Q2
H17: Grantee/Buyer | K17: n/a
H18: Amount of Sale | K18: n/a
C20: ▼ PROPERTY-LEVEL TAX INFORMATION ▼
C22: ="PROPERTY TAX INFORMATION ("&$T$3&")" -> PROPERTY TAX INFORMATION (2025) | P22: ='Unit Mix'!D64 -> Hudson View Park
D24: Street Address | E24: Owner | F24: City | G24: Parcel ID | H24: Units | I24: Site Size | J24: Year Built | K24: Improved Value | L24: Land Value | M24: Market Value | N24: Annual Tax | O24: Eff. Tax Rate | P24: Link to Source Info | S24: Tax Link Info:
M25: =SUM(K25:L25) -> 0 | O25: =IFERROR(N25/M25,"n/a") -> n/a
M26: =SUM(K26:L26) -> 0 | O26: =IFERROR(N26/M26,"n/a") -> n/a
D27: Property Total | I27: =SUM(I25:I26) -> 0 | K27: =SUM(K25:K26) -> 0 | L27: =SUM(L25:L26) -> 0 | M27: =SUM(M25:M26) -> 0 | N27: =SUM(N25:N26) -> 0 | O27: =IFERROR(N27/M27,"n/a") -> n/a
H29: Transfer/Sales History | M29: Historical Tax Summary | S29: =G25 -> 0 | X29: =G26 -> 0
H30: Most Recent Transfer Date | K30: n/a | M30: Tax Year | N30: Market Value | O30: Annual Tax | P30: Eff. Tax Rate | S30: Market Value | T30: Assessed Value | U30: Tax | V30: Assessment % | X30: Market Value | Y30: Assessed Value | Z30: Tax | AA30: Assessment %
H31: Grantor/Seller | K31: n/a | M31: =$T$3-3 -> 2022 | N31: =IFERROR(S31+X31+AC31+AH31+AM31,"n/a") -> 0 | O31: =IFERROR(U31+Z31+AE31+AJ31+AO31,"n/a") -> 0 | P31: =IFERROR(O31/N31,"n/a") -> n/a | V31: =IFERROR(T31/S31,"n/a") -> n/a | AA31: =IFERROR(Y31/X31,"n/a") -> n/a
H32: Grantee/Buyer | K32: n/a | M32: =M31+1 -> 2023 | N32: =IFERROR(S32+X32+AC32+AH32+AM32,"n/a") -> 0 | O32: =U32+Z32+AE32+AJ32+AO32 -> 0 | P32: =IFERROR(O32/N32,"n/a") -> n/a | V32: =IFERROR(T32/S32,"n/a") -> n/a | AA32: =IFERROR(Y32/X32,"n/a") -> n/a
H33: Amount of Sale | K33: n/a | M33: =M32+1 -> 2024 | N33: =IFERROR(S33+X33+AC33+AH33+AM33,"n/a") -> 0 | O33: =U33+Z33+AE33+AJ33+AO33 -> 0 | P33: =IFERROR(O33/N33,"n/a") -> n/a | V33: =IFERROR(T33/S33,"n/a") -> n/a | AA33: =IFERROR(Y33/X33,"n/a") -> n/a
H34: Previous Transfer Date | K34: n/a | M34: =M33+1 -> 2025 | N34: =M27 -> 0 | O34: =N27 -> 0 | P34: =IFERROR(O34/N34,"n/a") -> n/a | S34: =M25 -> 0 | U34: =N25 -> 0 | V34: =IFERROR(T34/S34,"n/a") -> n/a | X34: =M26 -> 0 | Z34: =N26 -> 0 | AA34: =IFERROR(Y34/X34,"n/a") -> n/a
D35: County | E35: Dutchess, NY | H35: Grantor/Seller | K35: n/a
H36: Grantee/Buyer | K36: n/a
H37: Amount of Sale | K37: n/a
C39: ="PROPERTY TAX INFORMATION ("&$T$3&")" -> PROPERTY TAX INFORMATION (2025) | P39: ='Unit Mix'!D65 -> [Property 2 Name]
D41: Street Address | E41: Owner | F41: City | G41: Parcel ID | H41: Units | I41: Site Size | J41: Year Built | K41: Improved Value | L41: Land Value | M41: Market Value | N41: Annual Tax | O41: Eff. Tax Rate | P41: Link to Source Info | S41: Tax Link Info:
M42: =SUM(K42:L42) -> 0 | O42: =IFERROR(N42/M42,"n/a") -> n/a
